Workbook
Name _zz8: #REF!
Name _zz8: #REF!
Name ABCcostPerLine: #REF!
Name ABCcostPerLine: #REF!
Name ABCcostPerLine: #REF!
Name ABCcostPerLine: #REF!
Name ABClinesMax: #REF!
Name ABClinesMax: #REF!
Name ABClinesMax: #REF!
Name ABClinesMax: #REF!
Name ABClinesMin: #REF!
Name ABClinesMin: #REF!
Name ABClinesMin: #REF!
Name ABClinesMin: #REF!
Name ABCterminalCost: #REF!
Name ABCterminalCost: #REF!
Name ABCterminalCost: #REF!
Name ABCterminalCost: #REF!
Name ABCutil: #REF!
Name ABCutil: #REF!
Name ABCutil: #REF!
Name ABCutil: #REF!
Name AccessNodeSize: #REF!
Name AccessNodeSize: #REF!
Name AccessNodeSize: #REF!
Name AccessNodeSize: #REF!
Name ActCabinetTelcoCost: #REF!
Name ActCabinetTelcoCost: #REF!
Name ActCabinetTelcoCost: #REF!
Name ActCabinetTelcoCost: #REF!
Name ActCabinetVideoCost: #REF!
Name ActCabinetVideoCost: #REF!
Name ActCabinetVideoCost: #REF!
Name ActCabinetVideoCost: #REF!
Name ActiveLines: #REF!
Name ActiveLines: #REF!
Name ActiveLines: #REF!
Name ActiveLines: #REF!
Name ActiveUtil: #REF!
Name ActiveUtil: #REF!
Name ActiveUtil: #REF!
Name ActiveUtil: #REF!
Name AreaPerEmployee: #REF!
Name AreaPerEmployee: #REF!
Name AreaPerEmployee: #REF!
Name AreaPerEmployee: #REF!
Name AreaPerHeadend: #REF!
Name AreaPerHeadend: #REF!
Name AreaPerHeadend: #REF!
Name AreaPerHeadend: #REF!
Name AreaPerSwitch: #REF!
Name AreaPerSwitch: #REF!
Name AreaPerSwitch: #REF!
Name AreaPerSwitch: #REF!
Name ArialCoaxLabor: #REF!
Name ArialCoaxLabor: #REF!
Name ArialCoaxLabor: #REF!
Name ArialCoaxLabor: #REF!
Name ArialCoaxMaterial: #REF!
Name ArialCoaxMaterial: #REF!

Sheet Sommaire
A1: SANCY - SLP | C1: 46022
A2: Méthode de comptabilisation des intérêts | B2: Coupon couru
A5: Particularités du FPCI
A8: Fonds investi
A10: Périodicité de la VL | B10: Trimestrielle
A12: Date de constitution | B12: 44825
A14: Date de clôture du premier exercice comptable | B14: 44926
A16: Type de parts
A17: Parts A
A18: Commandité
A19: Valeur nominale des parts
A20: Parts A
A21: Commandité
A23: Frais de gestion | B23: N/A
A25: Frais dépositaire | B25: Caceis
A27: Frais commissaire aux comptes | B27: Deloitte
A30: Evaluation des OPC | B30: dernière VL connue
A32: Devise de comptabilisation | B32: Euro
A34: Zone de saisie
A37: Onglets | B37: Synthèse des contrôles
A38: Inventaire | B38: =Inventaire!F13
A39: Calcul VL | B39: ='Calcul VL'!F6 -> OK
A40: OD Rééval | B40: =IF(AND('O.D Rééval'!G43="OK",'O.D Rééval'!G86="OK",'O.D Rééval'!G127="OK"),"OK","Anomalies") -> OK
A41: Int courus OC | B41: ='Intérêts OC'!L22 -> OK
A42: Rappro titres | B42: ='Rappro Titres & Parts'!C20 -> OK
B43: ='Rappro Titres & Parts'!F18 -> OK
B44: ='Rappro Titres & Parts'!I18 -> OK
A45: PVMV | B45: =PVMV!O29 -> OK
A46: Liste porteurs selon versement | B46: ='Liste porteurs selon versement '!D32 -> OK
B47: ='Liste porteurs selon versement '!D32 -> OK
A48: Frais de gestion | B48: ='Frais de gestion'!H112 -> OK
A49: Bilan | B49: =Bilan!I100 -> OK
A50: N-1 | B50: =Bilan!J100 -> OK
A51: Résultat | B51: =Résultat!H193 -> OK
A52: N-1 | B52: =Résultat!I193 -> OK
A53: Var actif net après valorisation | B53: =IF(B38="",'Capitaux propres'!D36,"") -> OK
A54: Var actif net avant valorisation | B54: =IF(B38="","",'Capitaux propres'!D39)
A55: N-1 | B55: ='Capitaux propres'!E36 -> OK
A56: Rappro banque | B56: ='Rappro Banque'!C13 -> OK
A57: rapprobalance | B57: ='Rappro Balance'!E33 -> OK
B58: ='Rappro Balance'!G33 -> OK
A59: rapprobalance classe 1-6-7 | B59: =IF(B38="",'Rappro Balance'!H16,"") -> OK
A60: rapprobalance classe 3-4-5 | B60: =IF(B38="",'Rappro Balance'!H30,"") -> OK
A61: rapprobalance classe 3 avant valorisation | B61: =IF(B29="","",'Rappro Balance'!K22)
A63: Délaration BDF
A64: Inventaire: BDF : complément Composition de l'actif net | B64: =IF(Inventaire!F62="OK","VRAI","FAUX") -> VRAI

Sheet Inventaire
B1: =Sommaire!A1 -> SANCY - SLP | G1: Inventaire au : | H1: =Sommaire!C1 -> 46022
B2: Code isin bdf | C2: FR001400CQD5
C3: FR001400CQE3
B7: Actif net : | C7: =D44 -> 11465750 | D7: Type de parts : | E7: Total | F7: Parts A1 | G7: Parts de Commandité
D8: Nbre de parts : | E8: =SUM(F8:I8) -> 15380.56 | F8: =+'Calcul VL'!C9 -> 15379.56 | G8: =+'Calcul VL'!C10 -> 1
D9: valeur liquidative : | F9: ='Calcul VL'!E9 -> 745.47027 | G9: ='Calcul VL'!E10 -> 745.47027
A12: G ou I | B12: Code Titre | C12: Libellé | D12: Quantité | E12: Prix de revient unitaire | F12: Estimation unitaire | G12: Origine du cours | H12: Prix de revient | I12: Intérêts capitalisés | J12: Prix de revient global | K12: Valeur d'estimation hors coupon | L12: +/- value potentielle | M12: Coupon couru | N12: Valeur d'estimation coupon inclus | O12: % actif net | Q12: Valeur totale de la participation | R12: Ecart | S12: Cours unitaire de valorisation
B13: FONDS GENERAL | F13: =IF(ABS('Rappro Balance'!$G$22)>0.009,"ANOMALIE DE VALORISATION","")
B14: Instruments financiers de capital Investissement
A16: G | B16: FRACEUR00294 | C16: =PVMV!B15 -> Heka Invest - Actions | D16: =+PVMV!E15 -> 14423076 | E16: =PVMV!N15 -> 1.04 | F16: 0.78809726 | G16: =H1 -> 46022 | H16: =PVMV!M15 -> 14999999 | J16: =+I16+H16 -> 14999999 | K16: =D16*F16 -> 11366787 | L16: =ROUND(K16-J16,2) -> -3633212.3 | N16: =ROUND(+M16+K16,2) -> 11366787 | O16: =+N16/$D$44*100 -> 99.136877 | Q16: 11366787 | R16: =Q16-N16 -> 0.0047987998 | S16: =Q16/D16 -> 0.78809726
B18: Total | H18: =SUM(H16:H17) -> 14999999 | I18: =SUM(I16:I17) -> 0 | J18: =SUM(J16:J17) -> 14999999 | K18: =SUM(K16:K17) -> 11366787 | L18: =SUM(L16:L17) -> -3633212.3 | M18: =SUM(M16:M17) -> 0 | N18: =SUM(N16:N17) -> 11366787 | O18: =SUM(O15:O17) -> 99.136877
B19: Autres instruments financiers
A21: I | O21: =+N21/$D$44*100 -> 0
A22: I | O22: =+N22/$D$44*100 -> 0
C24: Total | H24: =SUM(H21:H22) -> 0 | I24: =SUM(I21:I22) -> 0 | J24: =SUM(J21:J22) -> 0 | K24: =SUM(K21:K22) -> 0 | L24: =SUM(L21:L22) -> 0 | N24: =SUM(N21:N22) -> 0 | O24: =SUM(O19:O22) -> 0
C27: Total fonds général | H27: =+H18+H24 -> 14999999 | I27: =+I18+I24 -> 0 | J27: =+J18+J24 -> 14999999 | K27: =+K18+K24 -> 11366787 | L27: =+L18+L24 -> -3633212.3 | M27: =+M18+M24 -> 0 | N27: =ROUND(+N18+N24,2) -> 11366787 | O27: =+O18+O24 -> 99.136877
B30: Total inventaire : | H30: =H27 -> 14999999 | I30: =I27 -> 0 | J30: =J27 -> 14999999 | K30: =K27 -> 11366787 | L30: =L27 -> -3633212.3 | M30: =M27 -> 0 | N30: =N27 -> 11366787 | O30: =+O27 -> 99.136877
B32: Composition de l'actif net | D32: Fonds général | E32: %
B34: Inventaire | D34: =+N30 -> 11366787 | E34: =+D34/$D$44*100 -> 99.136877
B36: Disponibilités | D36: ='Rappro Banque'!C17 -> 109211.49 | E36: =+D36/$D$44*100 -> 0.95250191
B38: Créances | D38: =+'Créances_&_dettes'!G13 -> 0 | E38: =+D38/$D$44*100 -> 0
B40: Dettes | D40: =-+'Créances_&_dettes'!G59 -> -10248 | E40: =+D40/$D$44*100 -> -0.089379237
B42: Dettes financières | D42: =-(Emprunt!K68+Emprunt!K69) -> 0 | E42: =+D42/$D$44*100 -> 0
B44: Actif net | D44: =ROUNDDOWN(SUM(D34:D43),2) -> 11465750 | E44: =SUM(E33:E43) -> 100
B47: BDF : complément Composition de l'actif net | D47: Fonds général | E47: Reemploi/Compte bloqué/Clawback | F47: Reinvestissement | G47: Total | H47: %
B49: Inventaire BDF | D49: =D34 -> 11366787 | G49: =D49+E49+F49 -> 11366787 | H49: =+G49/$G$59 -> 0.99136877
B51: Disponibilité BDF | D51: =D36 -> 109211.49 | G51: =D51+E51+F51 -> 109211.49 | H51: =+G51/$G$59 -> 0.0095250191
B53: Créances BDF | D53: =D38 -> 0 | G53: =D53+E53+F53 -> 0 | H53: =+G53/$G$59 -> 0
B55: Dettes BDF | D55: =D40 -> -10248 | G55: =D55+E55+F55 -> -10248 | H55: =+G55/$G$59 -> -0.00089379237
B57: Dettes financières BDF | D57: =D42 -> 0 | G57: =D57+E57+F57 -> 0 | H57: =+G57/$G$59 -> 0
B59: Actif net BDF | D59: =ROUNDDOWN(SUM(D48:D58),2) -> 11465750 | E59: =ROUNDDOWN(SUM(E48:E58),2) -> 0 | F59: =ROUNDDOWN(SUM(F48:F58),2) -> 0 | G59: =ROUNDDOWN(SUM(G48:G58),2) -> 11465750 | H59: =SUM(H48:H58) -> 1
E62: Contrôle: | F62: =IF((D44-G59)=0,"OK","Anomalies") -> OK

Sheet Calcul VL
B1: =+Inventaire!B1 -> SANCY - SLP | D1: Calcul des valeurs liquidatives : | F1: =+Inventaire!H1 -> 46022
B4: Actif net | D4: =Inventaire!C7 -> 11465750
F6: =IF(F7=0,"OK","Anomalie") -> OK
B7: Type de parts | C7: Nombre de parts | D7: Actif net réparti | E7: VL | F7: =D4-D12 -> 0 | H7: Valeur liquidative recalculée | I7: Ecart non affectable | J7: Vérification | K7: SI l'écart divisé par le nombre de parts est inférieur à 0,01= OK
A9: FR001400CQD5 | B9: Parts A | C9: 15379.56 | D9: =$D$4*C9/$C$12 -> 11465005 | E9: =ROUNDDOWN(D9/C9,6) -> 745.47027 | H9: =E9*C9 -> 11465005 | I9: =D9-H9 -> 0.014808957 | J9: =+I9/C9/100 -> 9.6289858e-09 | K9: =IF(J9>0.01,"'ANOMALIE","'OK") -> 'OK
A10: FR001400CQE3 | B10: Part de commandité | C10: 1 | D10: =$D$4*C10/$C$12 -> 745.47027 | E10: =ROUNDDOWN(D10/C10,6) -> 745.47027 | H10: =E10*C10 -> 745.47027 | I10: =D10-H10 -> 9.6289853e-07 | J10: =+I10/C10/100 -> 9.6289853e-09 | K10: =IF(J10>0.01,"'ANOMALIE","'OK") -> 'OK
B12: Total | C12: =SUM(C9:C11) -> 15380.56 | D12: =SUM(D9:D11) -> 11465750 | H12: =SUM(H9:H11) -> 11465750 | I12: =SUM(I9:I11) -> 0.014809919 | J12: =+I12/C12/100 -> 9.6289858e-09 | K12: =IF(J12>0.01,"'ANOMALIE","'OK") -> 'OK

Sheet O.D Rééval
A1: Date | B1: journal | C1: Compte | D1: N° Piéces | E1: Libellé | F1: Debit | G1: Credit | H1: Monnaie
A2: =Sommaire!$C$1 -> 46022 | B2: OD-SITU | C2: 31800000 | E2: ="Valorisation au "&TEXT(Sommaire!$C$1,"jj/mm/aa") -> Valorisation au 31/12/25 | F2: =IF(SUMIF(Inventaire!B13:B90,"??OC*",Inventaire!M13:M90)>0,SUMIF(Inventaire!B13:B90,"??OC*",Inventaire!M13:M90),0) -> 0 | G2: =IF(SUMIF(Inventaire!B13:B90,"??OC*",Inventaire!M13:M90)<0,-SUMIF(Inventaire!B13:B90,"??OC*",Inventaire!M13:M90),0) -> 0 | H2: E | I2: Intérêts Courus sur OC
A3: =Sommaire!$C$1 -> 46022 | B3: OD-SITU | C3: 70110000 | E3: ="Valorisation au "&TEXT(Sommaire!$C$1,"jj/mm/aa") -> Valorisation au 31/12/25 | G3: =IF(SUMIF(Inventaire!B13:B90,"??OC*",Inventaire!M13:M90)>0,SUMIF(Inventaire!B13:B90,"??OC*",Inventaire!M13:M90),0) -> 0 | H3: E | I3: Intérêts courus sur OC | J3: OC
A5: =Sommaire!$C$1 -> 46022 | B5: OD-SITU | C5: 31800000 | E5: ="Valorisation au "&TEXT(Sommaire!$C$1,"jj/mm/aa") -> Valorisation au 31/12/25 | F5: =IF(SUMIF(Inventaire!B13:B90,"??OS*",Inventaire!M13:M90)+SUMIF(Inventaire!B13:B90,"??OR*",Inventaire!M13:M90)+SUMIF(Inventaire!B13:B90,"??CN*",Inventaire!M13:M90)>0,SUMIF(Inventaire!B13:B90,"??OS*",Inventaire!M13:M90)+SUMIF(Inventaire!B13:B90,"??OR*",Inventaire!M13:M90)+SUMIF(Inventaire!B13:B90,"??CN*",Inventaire!M13:M90),0) -> 0 | G5: =IF(SUMIF(Inventaire!B13:B90,"??OS*",Inventaire!M13:M90)+SUMIF(Inventaire!B13:B90,"??OR*",Inventaire!M13:M90)+SUMIF(Inventaire!B13:B90,"??CN*",Inventaire!M13:M90)<0,-(SUMIF(Inventaire!B13:B90,"??OS*",Inventaire!M13:M90)+SUMIF(Inventaire!B13:B90,"??OR*",Inventaire!M13:M90)+SUMIF(Inventaire!B13:B90,"??CN*",Inventaire!M13:M90)),0) -> 0 | H5: E | I5: Intérêts courus sur autres obligations
A6: =Sommaire!$C$1 -> 46022 | B6: OD-SITU | C6: 70000000 | E6: ="Valorisation au "&TEXT(Sommaire!$C$1,"jj/mm/aa") -> Valorisation au 31/12/25 | G6: =IF(SUMIF(Inventaire!B13:B90,"??OS*",Inventaire!M13:M90)+SUMIF(Inventaire!B13:B90,"??OR*",Inventaire!M13:M90)+SUMIF(Inventaire!B13:B90,"??CN*",Inventaire!M13:M90)>0,SUMIF(Inventaire!B13:B90,"??OS*",Inventaire!M13:M90)+SUMIF(Inventaire!B13:B90,"??OR*",Inventaire!M13:M90)+SUMIF(Inventaire!B13:B90,"??CN*",Inventaire!M13:M90),0) -> 0 | H6: E | I6: Intérêts courus sur autres obligations | J6: OS/OR/CN
A8: =Sommaire!$C$1 -> 46022 | B8: OD-SITU | C8: 36800000 | E8: ="Valorisation au "&TEXT(Sommaire!$C$1,"jj/mm/aa") -> Valorisation au 31/12/25 | F8: =IF(SUMIF(Inventaire!B13:B90,"??PR*",Inventaire!M13:M90)+SUMIF(Inventaire!B13:B90,"??NO*",Inventaire!M13:M90)+SUMIF(Inventaire!B13:B90,"??CC*",Inventaire!M13:M90)>0,SUMIF(Inventaire!B13:B90,"??PR*",Inventaire!M13:M90)+SUMIF(Inventaire!B13:B90,"??NO*",Inventaire!M13:M90)+SUMIF(Inventaire!B13:B90,"??CC*",Inventaire!M13:M90),0) -> 0 | G8: =IF(SUMIF(Inventaire!B13:B90,"??PR*",Inventaire!M13:M90)+SUMIF(Inventaire!B13:B90,"??NO*",Inventaire!M13:M90)+SUMIF(Inventaire!B13:B90,"??CC*",Inventaire!M13:M90)<0,-SUMIF(Inventaire!B13:B90,"??PR*",Inventaire!M13:M90)+SUMIF(Inventaire!B13:B90,"??NO*",Inventaire!M13:M90)+SUMIF(Inventaire!B13:B90,"??CC*",Inventaire!M13:M90),0) -> 0 | H8: E | I8: intérêts courus sur Prêt
A9: =Sommaire!$C$1 -> 46022 | B9: OD-SITU | C9: 70600000 | E9: ="Valorisation au "&TEXT(Sommaire!$C$1,"jj/mm/aa") -> Valorisation au 31/12/25 | G9: =IF(SUMIF(Inventaire!B13:B90,"??PR*",Inventaire!M13:M90)+SUMIF(Inventaire!B13:B90,"??NO*",Inventaire!M13:M90)+SUMIF(Inventaire!B13:B90,"??CC*",Inventaire!M13:M90)>0,SUMIF(Inventaire!B13:B90,"??PR*",Inventaire!M13:M90)+SUMIF(Inventaire!B13:B90,"??NO*",Inventaire!M13:M90)+SUMIF(Inventaire!B13:B90,"??CC*",Inventaire!M13:M90),0) -> 0 | H9: E | I9: intérêts courus sur Prêt | J9: PR/CC/NO
A11: =Sommaire!$C$1 -> 46022 | B11: OD-SITU | C11: 36800000 | E11: ="Valorisation au "&TEXT(Sommaire!$C$1,"jj/mm/aa") -> Valorisation au 31/12/25 | F11: =IF(+SUMIF(Inventaire!B16:B93,"??CT*",Inventaire!M16:M93)>0,+SUMIF(Inventaire!B16:B93,"??CT*",Inventaire!M16:M93),0) -> 0 | G11: =IF(+SUMIF(Inventaire!B16:B93,"??CT*",Inventaire!M16:M93)<0,-SUMIF(Inventaire!B16:B93,"??CT*",Inventaire!M16:M93),0) -> 0 | H11: E | I11: intérêts courus sur dépôt
A12: =Sommaire!$C$1 -> 46022 | B12: OD-SITU | C12: 70600000 | E12: ="Valorisation au "&TEXT(Sommaire!$C$1,"jj/mm/aa") -> Valorisation au 31/12/25 | G12: =IF(+SUMIF(Inventaire!B16:B93,"??CT*",Inventaire!M16:M93)>0,+SUMIF(Inventaire!B16:B93,"??CT*",Inventaire!M16:M93),0) -> 0 | H12: E | I12: intérêts courus sur dépôt | J12: CT
A14: =Sommaire!$C$1 -> 46022 | B14: OD-SITU | C14: 36800000 | E14: ="Valorisation au "&TEXT(Sommaire!$C$1,"jj/mm/aa") -> Valorisation au 31/12/25 | F14: =IF(SUMIF(Inventaire!B13:B90,"??AC*",Inventaire!M13:M90)+SUMIF(Inventaire!B13:B90,"??AD*",Inventaire!M13:M90)+SUMIF(Inventaire!B13:B90,"??SA*",Inventaire!M13:M90)+SUMIF(Inventaire!B13:B90,"??BS*",Inventaire!M13:M90)>0,SUMIF(Inventaire!B13:B90,"??AC*",Inventaire!M13:M90)+SUMIF(Inventaire!B13:B90,"??AD*",Inventaire!M13:M90)+SUMIF(Inventaire!B13:B90,"??SA*",Inventaire!M13:M90)+SUMIF(Inventaire!B13:B90,"??BS*",Inventaire!M13:M90),0) -> 0 | G14: =IF(SUMIF(Inventaire!B13:B90,"??AC*",Inventaire!M13:M90)+SUMIF(Inventaire!B13:B90,"??AD*",Inventaire!M13:M90)+SUMIF(Inventaire!B13:B90,"??SA*",Inventaire!M13:M90)+SUMIF(Inventaire!B13:B90,"??BS*",Inventaire!M13:M90)<0,-SUMIF(Inventaire!B13:B90,"??AC*",Inventaire!M13:M90)+SUMIF(Inventaire!B13:B90,"??AD*",Inventaire!M13:M90)+SUMIF(Inventaire!B13:B90,"??SA*",Inventaire!M13:M90)+SUMIF(Inventaire!B13:B90,"??BS*",Inventaire!M13:M90),0) -> 0 | H14: E | I14: Intérêts courus sur actions
A15: =Sommaire!$C$1 -> 46022 | B15: OD-SITU | C15: 70000000 | E15: ="Valorisation au "&TEXT(Sommaire!$C$1,"jj/mm/aa") -> Valorisation au 31/12/25 | F15: =IF(SUMIF(Inventaire!B13:B90,"??AC*",Inventaire!M13:M90)+SUMIF(Inventaire!B13:B90,"??AD*",Inventaire!M13:M90)+SUMIF(Inventaire!B13:B90,"??SA*",Inventaire!M13:M90)+SUMIF(Inventaire!B13:B90,"??BS*",Inventaire!M13:M90)<0,-SUMIF(Inventaire!B13:B90,"??AC*",Inventaire!M13:M90)+SUMIF(Inventaire!B13:B90,"??AD*",Inventaire!M13:M90)+SUMIF(Inventaire!B13:B90,"??SA*",Inventaire!M13:M90)+SUMIF(Inventaire!B13:B90,"??BS*",Inventaire!M13:M90),0) -> 0 | G15: =IF(SUMIF(Inventaire!B13:B90,"??AC*",Inventaire!M13:M90)+SUMIF(Inventaire!B13:B90,"??AD*",Inventaire!M13:M90)+SUMIF(Inventaire!B13:B90,"??SA*",Inventaire!M13:M90)+SUMIF(Inventaire!B13:B90,"??BS*",Inventaire!M13:M90)>0,SUMIF(Inventaire!B13:B90,"??AC*",Inventaire!M13:M90)+SUMIF(Inventaire!B13:B90,"??AD*",Inventaire!M13:M90)+SUMIF(Inventaire!B13:B90,"??SA*",Inventaire!M13:M90)+SUMIF(Inventaire!B13:B90,"??BS*",Inventaire!M13:M90),0) -> 0 | H15: E | I15: Intérêts courus sur actions | J15: AC/AD/BS/SA
A17: =Sommaire!$C$1 -> 46022 | B17: OD-SITU | C17: 37000000 | E17: ="Valorisation au "&TEXT(Sommaire!$C$1,"jj/mm/aa") -> Valorisation au 31/12/25 | F17: =IF(SUMIF(Inventaire!B13:B90,"??AC*",Inventaire!L13:L90)+SUMIF(Inventaire!B13:B90,"??AD*",Inventaire!L13:L90)+SUMIF(Inventaire!B13:B90,"??SA*",Inventaire!L13:L90)+SUMIF(Inventaire!B13:B90,"??BS*",Inventaire!L13:L90)>0,(SUMIF(Inventaire!B13:B90,"??AC*",Inventaire!L13:L90)+SUMIF(Inventaire!B13:B90,"??AD*",Inventaire!L13:L90)+SUMIF(Inventaire!B13:B90,"??SA*",Inventaire!L13:L90)+SUMIF(Inventaire!B13:B90,"??BS*",Inventaire!L13:L90)),0) -> 0 | G17: =IF(SUMIF(Inventaire!B13:B90,"??AC*",Inventaire!L13:L90)+SUMIF(Inventaire!B13:B90,"??AD*",Inventaire!L13:L90)+SUMIF(Inventaire!B13:B90,"??SA*",Inventaire!L13:L90)+SUMIF(Inventaire!B13:B90,"??BS*",Inventaire!L13:L90)<0,-(SUMIF(Inventaire!B13:B90,"??AC*",Inventaire!L13:L90)+SUMIF(Inventaire!B13:B90,"??AD*",Inventaire!L13:L90)+SUMIF(Inventaire!B13:B90,"??SA*",Inventaire!L13:L90)+SUMIF(Inventaire!B13:B90,"??BS*",Inventaire!L13:L90)),0) -> 3633212.3 | H17: E | I17: PVMV latentes nettes s/actions
A18: =Sommaire!$C$1 -> 46022 | B18: OD-SITU | C18: 75500000 | E18: ="Valorisation au "&TEXT(Sommaire!$C$1,"jj/mm/aa") -> Valorisation au 31/12/25 | F18: =IF(SUMIF(Inventaire!B13:B90,"??AC*",Inventaire!L13:L90)+SUMIF(Inventaire!B13:B90,"??AD*",Inventaire!L13:L90)+SUMIF(Inventaire!B13:B90,"??SA*",Inventaire!L13:L90)+SUMIF(Inventaire!B13:B90,"??BS*",Inventaire!L13:L90)<0,-(SUMIF(Inventaire!B13:B90,"??AC*",Inventaire!L13:L90)+SUMIF(Inventaire!B13:B90,"??AD*",Inventaire!L13:L90)+SUMIF(Inventaire!B13:B90,"??SA*",Inventaire!L13:L90)+SUMIF(Inventaire!B13:B90,"??BS*",Inventaire!L13:L90)),0) -> 3633212.3 | G18: =IF(SUMIF(Inventaire!B13:B90,"??AC*",Inventaire!L13:L90)+SUMIF(Inventaire!B13:B90,"??AD*",Inventaire!L13:L90)+SUMIF(Inventaire!B13:B90,"??SA*",Inventaire!L13:L90)+SUMIF(Inventaire!B13:B90,"??BS*",Inventaire!L13:L90)>0,(SUMIF(Inventaire!B13:B90,"??AC*",Inventaire!L13:L90)+SUMIF(Inventaire!B13:B90,"??AD*",Inventaire!L13:L90)+SUMIF(Inventaire!B13:B90,"??SA*",Inventaire!L13:L90)+SUMIF(Inventaire!B13:B90,"??BS*",Inventaire!L13:L90)),0) -> 0 | H18: E | I18: PVMV latentes nettes s/actions
A20: =Sommaire!$C$1 -> 46022 | B20: OD-SITU | C20: 37100000 | E20: ="Valorisation au "&TEXT(Sommaire!$C$1,"jj/mm/aa") -> Valorisation au 31/12/25 | F20: =IF(SUMIF(Inventaire!B13:B90,"??OC*",Inventaire!L13:L90)>0,(SUMIF(Inventaire!B13:B90,"??OC*",Inventaire!L13:L90)),0) -> 0 | G20: =IF(SUMIF(Inventaire!B13:B90,"??OC*",Inventaire!L13:L90)<0,-(SUMIF(Inventaire!B13:B90,"??OC*",Inventaire!L13:L90)),0) -> 0 | H20: E | I20: PVMV latentes nettes s/obligations convertibles en actions
A21: =Sommaire!$C$1 -> 46022 | B21: OD-SITU | C21: 75512000 | E21: ="Valorisation au "&TEXT(Sommaire!$C$1,"jj/mm/aa") -> Valorisation au 31/12/25 | F21: =IF(SUMIF(Inventaire!B13:B90,"??OC*",Inventaire!L13:L90)<0,-(SUMIF(Inventaire!B13:B90,"??OC*",Inventaire!L13:L90)),0) -> 0 | G21: =IF(SUMIF(Inventaire!B13:B90,"??OC*",Inventaire!L13:L90)>0,(SUMIF(Inventaire!B13:B90,"??OC*",Inventaire!L13:L90)),0) -> 0 | H21: E | I21: PVMV latentes nettes s/obligations convertibles en actions
A23: =Sommaire!$C$1 -> 46022 | B23: OD-SITU | C23: 37100000 | E23: ="Valorisation au "&TEXT(Sommaire!$C$1,"jj/mm/aa") -> Valorisation au 31/12/25 | F23: =IF(SUMIF(Inventaire!B13:B90,"??OS*",Inventaire!L13:L90)+SUMIF(Inventaire!B13:B90,"??OR*",Inventaire!L13:L90)+SUMIF(Inventaire!B13:B90,"??CN*",Inventaire!L13:L90)>0,+(SUMIF(Inventaire!B13:B90,"??OS*",Inventaire!L13:L90)+SUMIF(Inventaire!B13:B90,"??OR*",Inventaire!L13:L90)+SUMIF(Inventaire!B13:B90,"??CN*",Inventaire!L13:L90)),0) -> 0 | G23: =IF(SUMIF(Inventaire!B13:B90,"??OS*",Inventaire!L13:L90)+SUMIF(Inventaire!B13:B90,"??OR*",Inventaire!L13:L90)+SUMIF(Inventaire!B13:B90,"??CN*",Inventaire!L13:L90)<0,-(SUMIF(Inventaire!B13:B90,"??OS*",Inventaire!L13:L90)+SUMIF(Inventaire!B13:B90,"??OR*",Inventaire!L13:L90)+SUMIF(Inventaire!B13:B90,"??CN*",Inventaire!L13:L90)),0) -> 0 | H23: E | I23: PVMV latentes nettes s/autres obligations
A24: =Sommaire!$C$1 -> 46022 | B24: OD-SITU | C24: 75515000 | E24: ="Valorisation au "&TEXT(Sommaire!$C$1,"jj/mm/aa") -> Valorisation au 31/12/25 | F24: =IF(SUMIF(Inventaire!B13:B90,"??OS*",Inventaire!L13:L90)+SUMIF(Inventaire!B13:B90,"??OR*",Inventaire!L13:L90)+SUMIF(Inventaire!B13:B90,"??CN*",Inventaire!L13:L90)<0,-(SUMIF(Inventaire!B13:B90,"??OS*",Inventaire!L13:L90)+SUMIF(Inventaire!B13:B90,"??OR*",Inventaire!L13:L90)+SUMIF(Inventaire!B13:B90,"??CN*",Inventaire!L13:L90)),0) -> 0 | G24: =IF(SUMIF(Inventaire!B13:B90,"??OS*",Inventaire!L13:L90)+SUMIF(Inventaire!B13:B90,"??OR*",Inventaire!L13:L90)+SUMIF(Inventaire!B13:B90,"??CN*",Inventaire!L13:L90)>0,+(SUMIF(Inventaire!B13:B90,"??OS*",Inventaire!L13:L90)+SUMIF(Inventaire!B13:B90,"??OR*",Inventaire!L13:L90)+SUMIF(Inventaire!B13:B90,"??CN*",Inventaire!L13:L90)),0) -> 0 | H24: E | I24: PVMV latentes nettes s/autres obligations
A26: =Sommaire!$C$1 -> 46022 | B26: OD-SITU | C26: 37600000 | E26: ="Valorisation au "&TEXT(Sommaire!$C$1,"jj/mm/aa") -> Valorisation au 31/12/25 | F26: =IF(SUMIF(Inventaire!B13:B90,"??PR*",Inventaire!L13:L90)+SUMIF(Inventaire!B13:B90,"??NO*",Inventaire!L13:L90)+SUMIF(Inventaire!B13:B90,"??CC*",Inventaire!L13:L90)+SUMIF(Inventaire!B13:B90,"??CT*",Inventaire!L13:L90)>0,+(SUMIF(Inventaire!B13:B90,"??PR*",Inventaire!L13:L90)+SUMIF(Inventaire!B13:B90,"??NO*",Inventaire!L13:L90)+SUMIF(Inventaire!B13:B90,"??CT*",Inventaire!L13:L90)+SUMIF(Inventaire!B13:B90,"??CC*",Inventaire!L13:L90)),0) -> 0 | G26: =IF(SUMIF(Inventaire!B13:B90,"??PR*",Inventaire!L13:L90)+SUMIF(Inventaire!B13:B90,"??NO*",Inventaire!L13:L90)+SUMIF(Inventaire!B13:B90,"??CC*",Inventaire!L13:L90)+SUMIF(Inventaire!B13:B90,"??CT*",Inventaire!L13:L90)<0,-(SUMIF(Inventaire!B13:B90,"??PR*",Inventaire!L13:L90)+SUMIF(Inventaire!B13:B90,"??NO*",Inventaire!L13:L90)+SUMIF(Inventaire!B13:B90,"??CT*",Inventaire!L13:L90)+SUMIF(Inventaire!B13:B90,"??CC*",Inventaire!L13:L90)),0) -> 0 | H26: E | I26: PVMV latentes nettes s/dépôt et autres investissements financiers
A27: =Sommaire!$C$1 -> 46022 | B27: OD-SITU | C27: 75561000 | E27: ="Valorisation au "&TEXT(Sommaire!$C$1,"jj/mm/aa") -> Valorisation au 31/12/25 | F27: =IF(SUMIF(Inventaire!B13:B90,"??PR*",Inventaire!L13:L90)+SUMIF(Inventaire!B13:B90,"??NO*",Inventaire!L13:L90)+SUMIF(Inventaire!B13:B90,"??CC*",Inventaire!L13:L90)+SUMIF(Inventaire!B13:B90,"??CT*",Inventaire!L13:L90)<0,-(SUMIF(Inventaire!B13:B90,"??PR*",Inventaire!L13:L90)+SUMIF(Inventaire!B13:B90,"??NO*",Inventaire!L13:L90)+SUMIF(Inventaire!B13:B90,"??CT*",Inventaire!L13:L90)+SUMIF(Inventaire!B13:B90,"??CC*",Inventaire!L13:L90)),0) -> 0 | G27: =IF(SUMIF(Inventaire!B13:B90,"??PR*",Inventaire!L13:L90)+SUMIF(Inventaire!B13:B90,"??NO*",Inventaire!L13:L90)+SUMIF(Inventaire!B13:B90,"??CC*",Inventaire!L13:L90)+SUMIF(Inventaire!B13:B90,"??CT*",Inventaire!L13:L90)>0,+(SUMIF(Inventaire!B13:B90,"??PR*",Inventaire!L13:L90)+SUMIF(Inventaire!B13:B90,"??NO*",Inventaire!L13:L90)+SUMIF(Inventaire!B13:B90,"??CT*",Inventaire!L13:L90)+SUMIF(Inventaire!B13:B90,"??CC*",Inventaire!L13:L90)),0) -> 0 | H27: E | I27: PVMV latentes nettes s/dépôt et autres investissements financiers
A29: =Sommaire!$C$1 -> 46022 | B29: OD-SITU | C29: 37300000 | E29: ="Valorisation au "&TEXT(Sommaire!$C$1,"jj/mm/aa") -> Valorisation au 31/12/25 | F29: =IF(SUMIF(Inventaire!C13:C90,"*sicav*",Inventaire!L13:L90)+SUMIF(Inventaire!C13:C90,"*FCP*",Inventaire!L13:L90)+SUMIF(Inventaire!C13:C90,"*FPCI*",Inventaire!L13:L90)+SUMIF(Inventaire!C13:C90,"*SLP*",Inventaire!L13:L90)+SUMIF(Inventaire!C13:C90,"*FIPS*",Inventaire!L13:L90)>0,(SUMIF(Inventaire!C13:C90,"*sicav*",Inventaire!L13:L90)+SUMIF(Inventaire!C13:C90,"*FCP*",Inventaire!L13:L90)+SUMIF(Inventaire!C13:C90,"*FPCI*",Inventaire!L13:L90)+SUMIF(Inventaire!C13:C90,"*SLP*",Inventaire!L13:L90)+SUMIF(Inventaire!C13:C90,"*FIPS*",Inventaire!L13:L90)),0) -> 0 | G29: =IF(SUMIF(Inventaire!C13:C90,"*sicav*",Inventaire!L13:L90)+SUMIF(Inventaire!C13:C90,"*FCP*",Inventaire!L13:L90)+SUMIF(Inventaire!C13:C90,"*FPCI*",Inventaire!L13:L90)+SUMIF(Inventaire!C13:C90,"*SLP*",Inventaire!L13:L90)+SUMIF(Inventaire!C13:C90,"*FIPS*",Inventaire!L13:L90)<0,-(SUMIF(Inventaire!C13:C90,"*sicav*",Inventaire!L13:L90)+SUMIF(Inventaire!C13:C90,"*FCP*",Inventaire!L13:L90)+SUMIF(Inventaire!C13:C90,"*FPCI*",Inventaire!L13:L90)+SUMIF(Inventaire!C13:C90,"*SLP*",Inventaire!L13:L90)+SUMIF(Inventaire!C13:C90,"*FIPS*",Inventaire!L13:L90)),0) -> 0 | H29: E | I29: PVMV latentes nettes s/OPC
A30: =Sommaire!$C$1 -> 46022 | B30: OD-SITU | C30: 75530000 | E30: ="Valorisation au "&TEXT(Sommaire!$C$1,"jj/mm/aa") -> Valorisation au 31/12/25 | F30: =IF(SUMIF(Inventaire!C13:C90,"*sicav*",Inventaire!L13:L90)+SUMIF(Inventaire!C13:C90,"*FCP*",Inventaire!L13:L90)+SUMIF(Inventaire!C13:C90,"*FPCI*",Inventaire!L13:L90)+SUMIF(Inventaire!C13:C90,"*SLP*",Inventaire!L13:L90)+SUMIF(Inventaire!C13:C90,"*FIPS*",Inventaire!L13:L90)<0,-(SUMIF(Inventaire!C13:C90,"*sicav*",Inventaire!L13:L90)+SUMIF(Inventaire!C13:C90,"*FCP*",Inventaire!L13:L90)+SUMIF(Inventaire!C13:C90,"*FPCI*",Inventaire!L13:L90)+SUMIF(Inventaire!C13:C90,"*SLP*",Inventaire!L13:L90)+SUMIF(Inventaire!C13:C90,"*FIPS*",Inventaire!L13:L90)),0) -> 0 | G30: =IF(SUMIF(Inventaire!C13:C90,"*sicav*",Inventaire!L13:L90)+SUMIF(Inventaire!C13:C90,"*FCP*",Inventaire!L13:L90)+SUMIF(Inventaire!C13:C90,"*FPCI*",Inventaire!L13:L90)+SUMIF(Inventaire!C13:C90,"*SLP*",Inventaire!L13:L90)+SUMIF(Inventaire!C13:C90,"*FIPS*",Inventaire!L13:L90)>0,(SUMIF(Inventaire!C13:C90,"*sicav*",Inventaire!L13:L90)+SUMIF(Inventaire!C13:C90,"*FCP*",Inventaire!L13:L90)+SUMIF(Inventaire!C13:C90,"*FPCI*",Inventaire!L13:L90)+SUMIF(Inventaire!C13:C90,"*SLP*",Inventaire!L13:L90)+SUMIF(Inventaire!C13:C90,"*FIPS*",Inventaire!L13:L90)),0) -> 0 | H30: E | I30: PVMV latentes nettes s/OPC | J30: Sicav/FCP/FPCI/SLP/FIPS
A33: =Sommaire!$C$1 -> 46022 | B33: OD-SITU | C33: 10410000 | E33: ="Valorisation au "&TEXT(Sommaire!$C$1,"jj/mm/aa") -> Valorisation au 31/12/25 | G33: 0 | H33: E | I33: Fund reserve
A34: =Sommaire!$C$1 -> 46022 | B34: OD-SITU | C34: 48700000 | E34: ="Valorisation au "&TEXT(Sommaire!$C$1,"jj/mm/aa") -> Valorisation au 31/12/25 | F34: 0 | G34: =F33 -> 0 | H34: E | I34: =+I33 -> Fund reserve
A36: =Sommaire!$C$1 -> 46022 | B36: OD-SITU | C36: 39800000 | E36: ="Valorisation au "&TEXT(Sommaire!$C$1,"jj/mm/aa") -> Valorisation au 31/12/25 | F36: 0 | G36: =Emprunt!K68 -> 0 | H36: E | I36: Intérêts sur emprunts
A37: =Sommaire!$C$1 -> 46022 | B37: OD-SITU | C37: 60500000 | E37: ="Valorisation au "&TEXT(Sommaire!$C$1,"jj/mm/aa") -> Valorisation au 31/12/25 | F37: =G36 -> 0 | G37: =F36 -> 0 | H37: E | I37: Intérêts sur emprunts
E41: Contrôle | F41: =SUM(F2:F40) -> 3633212.3 | G41: =SUM(G3:G40) -> 3633212.3
E42: écart | G42: =F41-G41 -> 0 | H42: ce contrôle toujours à zéro
G43: =IF(G42=0,"OK","ANOMALIE") -> OK
A47: à la clôture
A48: =A2 -> 46022 | B48: OD | C48: =C2 -> 31800000 | E48: =E2 -> Valorisation au 31/12/25 | F48: =F2 -> 0 | G48: =G2 -> 0 | H48: =H2 -> E | I48: =I2 -> Intérêts Courus sur OC
A49: =A3 -> 46022 | B49: OD | C49: =C3 -> 70110000 | E49: =E3 -> Valorisation au 31/12/25 | F49: =F3 -> 0 | G49: =G3 -> 0 | H49: =H3 -> E | I49: =I3 -> Intérêts courus sur OC
A51: =A5 -> 46022 | B51: OD | C51: =C5 -> 31800000 | E51: =E5 -> Valorisation au 31/12/25 | F51: =F5 -> 0 | G51: =G5 -> 0 | H51: =H5 -> E | I51: =I5 -> Intérêts courus sur autres obligations
A52: =A6 -> 46022 | B52: OD | C52: =C6 -> 70000000 | E52: =E6 -> Valorisation au 31/12/25 | F52: =F6 -> 0 | G52: =G6 -> 0 | H52: =H6 -> E | I52: =I6 -> Intérêts courus sur autres obligations
A54: =A8 -> 46022 | B54: OD | C54: =C8 -> 36800000 | E54: =E8 -> Valorisation au 31/12/25 | F54: =F8 -> 0 | G54: =G8 -> 0 | H54: =H8 -> E | I54: =I8 -> intérêts courus sur Prêt
A55: =A9 -> 46022 | B55: OD | C55: =C9 -> 70600000 | E55: =E9 -> Valorisation au 31/12/25 | F55: =F9 -> 0 | G55: =G9 -> 0 | H55: =H9 -> E | I55: =I9 -> intérêts courus sur Prêt
A57: =A14 -> 46022 | B57: OD | C57: =C14 -> 36800000 | E57: =E14 -> Valorisation au 31/12/25 | F57: =F14 -> 0 | G57: =G14 -> 0 | H57: =H14 -> E | I57: =I14 -> Intérêts courus sur actions
A58: =A15 -> 46022 | B58: OD | C58: =C15 -> 70000000 | E58: =E15 -> Valorisation au 31/12/25 | F58: =F15 -> 0 | G58: =G15 -> 0 | H58: =H15 -> E | I58: =I15 -> Intérêts courus sur actions
A60: =A17 -> 46022 | B60: OD | C60: =C17 -> 37000000 | E60: =E17 -> Valorisation au 31/12/25 | F60: =F17 -> 0 | G60: =G17 -> 3633212.3 | H60: =H17 -> E | I60: =I17 -> PVMV latentes nettes s/actions
A61: =A18 -> 46022 | B61: OD | C61: =C18 -> 75500000 | E61: =E18 -> Valorisation au 31/12/25 | F61: =F18 -> 3633212.3 | G61: =G18 -> 0 | H61: =H18 -> E | I61: =I18 -> PVMV latentes nettes s/actions
A63: =A20 -> 46022 | B63: OD | C63: =C20 -> 37100000 | E63: =E20 -> Valorisation au 31/12/25 | F63: =F20 -> 0 | G63: =G20 -> 0 | H63: =H20 -> E | I63: =I20 -> PVMV latentes nettes s/obligations convertibles en actions
A64: =A21 -> 46022 | B64: OD | C64: =C21 -> 75512000 | E64: =E21 -> Valorisation au 31/12/25 | F64: =F21 -> 0 | G64: =G21 -> 0 | H64: =H21 -> E | I64: =I21 -> PVMV latentes nettes s/obligations convertibles en actions
A66: =A23 -> 46022 | B66: OD | C66: =C23 -> 37100000 | E66: =E23 -> Valorisation au 31/12/25 | F66: =F23 -> 0 | G66: =G23 -> 0 | H66: =H23 -> E | I66: =I23 -> PVMV latentes nettes s/autres obligations
A67: =A24 -> 46022 | B67: OD | C67: =C24 -> 75515000 | E67: =E24 -> Valorisation au 31/12/25 | F67: =F24 -> 0 | G67: =G24 -> 0 | H67: =H24 -> E | I67: =I24 -> PVMV latentes nettes s/autres obligations
A69: =A26 -> 46022 | B69: OD | C69: =C26 -> 37600000 | E69: =E26 -> Valorisation au 31/12/25 | F69: =F26 -> 0 | G69: =G26 -> 0 | H69: =H26 -> E | I69: =I26 -> PVMV latentes nettes s/dépôt et autres investissements financiers
A70: =A27 -> 46022 | B70: OD | C70: =C27 -> 75561000 | E70: =E27 -> Valorisation au 31/12/25 | F70: =F27 -> 0 | G70: =G27 -> 0 | H70: =H27 -> E | I70: =I27 -> PVMV latentes nettes s/dépôt et autres investissements financiers
A72: =A29 -> 46022 | B72: OD | C72: =C29 -> 37300000 | E72: =E29 -> Valorisation au 31/12/25 | F72: =F29 -> 0 | G72: =G29 -> 0 | H72: =H29 -> E | I72: =I29 -> PVMV latentes nettes s/OPC
A73: =A30 -> 46022 | B73: OD | C73: =C30 -> 75530000 | E73: =E30 -> Valorisation au 31/12/25 | F73: =F30 -> 0 | G73: =G30 -> 0 | H73: =H30 -> E | I73: =I30 -> PVMV latentes nettes s/OPC
... A80: =A37 -> 46022 | B80: OD | C80: =C37 -> 60500000 | E80: =E37 -> Valorisation au 31/12/25 | F80: =F37 -> 0 | G80: =G37 -> 0 | H80: =H37 -> E | I80: =I37 -> Intérêts sur emprunts
F83: =F40 -> 0 | G83: =G40 -> 0
E84: =E41 -> Contrôle | F84: =SUM(F48:F83) -> 3633212.3 | G84: =SUM(G48:G83) -> 3633212.3
E85: =E42 -> écart | G85: =F84-G84 -> 0 | H85: =H42 -> ce contrôle toujours à zéro
G86: =IF(G85=0,"OK","ANOMALIE") -> OK
A88: Extourne de la clôture
A89: =A48+1 -> 46023 | B89: =B48 -> OD | C89: =C48 -> 31800000 | E89: =+"Extourne valorisation au "&TEXT(Sommaire!$C$1,"jj/mm/aaaa") -> Extourne valorisation au 31/12/2025 | F89: =G48 -> 0 | G89: =F48 -> 0 | H89: =H48 -> E | I89: =I48 -> Intérêts Courus sur OC
A90: =A49+1 -> 46023 | B90: =B49 -> OD | C90: 65100000 | E90: =+"Extourne valorisation au "&TEXT(Sommaire!$C$1,"jj/mm/aaaa") -> Extourne valorisation au 31/12/2025 | F90: =G49 -> 0 | G90: =F49 -> 0 | H90: =H49 -> E | I90: =I49 -> Intérêts courus sur OC
A92: =A51+1 -> 46023 | B92: =B51 -> OD | C92: =C51 -> 31800000 | E92: =+"Extourne valorisation au "&TEXT(Sommaire!$C$1,"jj/mm/aaaa") -> Extourne valorisation au 31/12/2025 | F92: =G51 -> 0 | G92: =F51 -> 0 | H92: =H51 -> E | I92: =I51 -> Intérêts courus sur autres obligations
A93: =A52+1 -> 46023 | B93: =B52 -> OD | C93: 65100000 | E93: =+"Extourne valorisation au "&TEXT(Sommaire!$C$1,"jj/mm/aaaa") -> Extourne valorisation au 31/12/2025 | F93: =G52 -> 0 | G93: =F52 -> 0 | H93: =H52 -> E | I93: =I52 -> Intérêts courus sur autres obligations
A95: =A54+1 -> 46023 | B95: =B54 -> OD | C95: =C54 -> 36800000 | E95: =+"Extourne valorisation au "&TEXT(Sommaire!$C$1,"jj/mm/aaaa") -> Extourne valorisation au 31/12/2025 | F95: =G54 -> 0 | G95: =F54 -> 0 | H95: =H54 -> E | I95: =I54 -> intérêts courus sur Prêt
A96: =A55+1 -> 46023 | B96: =B55 -> OD | C96: 65100000 | E96: =+"Extourne valorisation au "&TEXT(Sommaire!$C$1,"jj/mm/aaaa") -> Extourne valorisation au 31/12/2025 | F96: =G55 -> 0 | G96: =F55 -> 0 | H96: =H55 -> E | I96: =I55 -> intérêts courus sur Prêt
A98: =A57+1 -> 46023 | B98: =B57 -> OD | C98: =C57 -> 36800000 | E98: =+"Extourne valorisation au "&TEXT(Sommaire!$C$1,"jj/mm/aaaa") -> Extourne valorisation au 31/12/2025 | F98: =G57 -> 0 | G98: =F57 -> 0 | H98: =H57 -> E | I98: =I57 -> Intérêts courus sur actions
A99: =A58+1 -> 46023 | B99: =B58 -> OD | C99: 65100000 | E99: =+"Extourne valorisation au "&TEXT(Sommaire!$C$1,"jj/mm/aaaa") -> Extourne valorisation au 31/12/2025 | F99: =G58 -> 0 | G99: =F58 -> 0 | H99: =H58 -> E | I99: =I58 -> Intérêts courus sur actions
A101: =A60+1 -> 46023 | B101: =B60 -> OD | C101: =C60 -> 37000000 | E101: =+"Extourne valorisation au "&TEXT(Sommaire!$C$1,"jj/mm/aaaa") -> Extourne valorisation au 31/12/2025 | F101: =G60 -> 3633212.3 | G101: =F60 -> 0 | H101: =H60 -> E | I101: =I60 -> PVMV latentes nettes s/actions
A102: =A61+1 -> 46023 | B102: =B61 -> OD | C102: 65100000 | E102: =+"Extourne valorisation au "&TEXT(Sommaire!$C$1,"jj/mm/aaaa") -> Extourne valorisation au 31/12/2025 | F102: =G61 -> 0 | G102: =F61 -> 3633212.3 | H102: =H61 -> E | I102: =I61 -> PVMV latentes nettes s/actions
A104: =A63+1 -> 46023 | B104: =B63 -> OD | C104: =C63 -> 37100000 | E104: =+"Extourne valorisation au "&TEXT(Sommaire!$C$1,"jj/mm/aaaa") -> Extourne valorisation au 31/12/2025 | F104: =G63 -> 0 | G104: =F63 -> 0 | H104: =H63 -> E | I104: =I63 -> PVMV latentes nettes s/obligations convertibles en actions
A105: =A64+1 -> 46023 | B105: =B64 -> OD | C105: 65100000 | E105: =+"Extourne valorisation au "&TEXT(Sommaire!$C$1,"jj/mm/aaaa") -> Extourne valorisation au 31/12/2025 | F105: =G64 -> 0 | G105: =F64 -> 0 | H105: =H64 -> E | I105: =I64 -> PVMV latentes nettes s/obligations convertibles en actions
A107: =A66+1 -> 46023 | B107: =B66 -> OD | C107: =C66 -> 37100000 | E107: =+"Extourne valorisation au "&TEXT(Sommaire!$C$1,"jj/mm/aaaa") -> Extourne valorisation au 31/12/2025 | F107: =G66 -> 0 | G107: =F66 -> 0 | H107: =H66 -> E | I107: =I66 -> PVMV latentes nettes s/autres obligations
A108: =A67+1 -> 46023 | B108: =B67 -> OD | C108: 65100000 | E108: =+"Extourne valorisation au "&TEXT(Sommaire!$C$1,"jj/mm/aaaa") -> Extourne valorisation au 31/12/2025 | F108: =G67 -> 0 | G108: =F67 -> 0 | H108: =H67 -> E | I108: =I67 -> PVMV latentes nettes s/autres obligations
A110: =A69+1 -> 46023 | B110: =B69 -> OD | C110: =C69 -> 37600000 | E110: =+"Extourne valorisation au "&TEXT(Sommaire!$C$1,"jj/mm/aaaa") -> Extourne valorisation au 31/12/2025 | F110: =G69 -> 0 | G110: =F69 -> 0 | H110: =H69 -> E | I110: =I69 -> PVMV latentes nettes s/dépôt et autres investissements financiers
A111: =A70+1 -> 46023 | B111: =B70 -> OD | C111: 65100000 | E111: =+"Extourne valorisation au "&TEXT(Sommaire!$C$1,"jj/mm/aaaa") -> Extourne valorisation au 31/12/2025 | F111: =G70 -> 0 | G111: =F70 -> 0 | H111: =H70 -> E | I111: =I70 -> PVMV latentes nettes s/dépôt et autres investissements financiers
A113: =A72+1 -> 46023 | B113: =B72 -> OD | C113: =C72 -> 37300000 | E113: =+"Extourne valorisation au "&TEXT(Sommaire!$C$1,"jj/mm/aaaa") -> Extourne valorisation au 31/12/2025 | F113: =G72 -> 0 | G113: =F72 -> 0 | H113: =H72 -> E | I113: =I72 -> PVMV latentes nettes s/OPC
A114: =A73+1 -> 46023 | B114: =B73 -> OD | C114: 65100000 | E114: =+"Extourne valorisation au "&TEXT(Sommaire!$C$1,"jj/mm/aaaa") -> Extourne valorisation au 31/12/2025 | F114: =G73 -> 0 | G114: =F73 -> 0 | H114: =H73 -> E | I114: =I73 -> PVMV latentes nettes s/OPC
A117: =A76+1 -> 46023 | B117: =B76 -> OD | C117: =C76 -> 10410000 | E117: =+"Extourne valorisation au "&TEXT(Sommaire!$C$1,"jj/mm/aaaa") -> Extourne valorisation au 31/12/2025 | F117: =G76 -> 0 | G117: =F76 -> 0 | H117: =H76 -> E | I117: =I76 -> Fund reserve
A118: =A77+1 -> 46023 | B118: =B77 -> OD | C118: =C77 -> 48700000 | E118: =+"Extourne valorisation au "&TEXT(Sommaire!$C$1,"jj/mm/aaaa") -> Extourne valorisation au 31/12/2025 | F118: =G77 -> 0 | G118: =F77 -> 0 | H118: =H77 -> E | I118: =I77 -> Fund reserve
A120: =A79+1 -> 46023 | B120: =B79 -> OD | C120: =C79 -> 39800000 | E120: =+"Extourne valorisation au "&TEXT(Sommaire!$C$1,"jj/mm/aaaa") -> Extourne valorisation au 31/12/2025 | F120: =G79 -> 0 | G120: =F79 -> 0 | H120: =H79 -> E | I120: =I79 -> Intérêts sur emprunts
A121: =A80+1 -> 46023 | B121: =B80 -> OD | C121: =C80 -> 60500000 | E121: =+"Extourne valorisation au "&TEXT(Sommaire!$C$1,"jj/mm/aaaa") -> Extourne valorisation au 31/12/2025 | F121: =G80 -> 0 | G121: =F80 -> 0 | H121: =H80 -> E | I121: =I80 -> Intérêts sur emprunts
E125: =E84 -> Contrôle | F125: =SUM(F89:F124) -> 3633212.3 | G125: =SUM(G89:G124) -> 3633212.3
E126: =E85 -> écart | F126: =F125-G125 -> 0 | H126: =H85 -> ce contrôle toujours à zéro
G127: =IF(F126=0,"OK","ANOMALIE") -> OK

Sheet Rappro Titres & Parts
B1: =Inventaire!B1 -> SANCY - SLP | E1: Rapprochement Titres | J1: =Sommaire!C1 -> 46022
B4: Société et nature juridique | C4: Quantité | D4: Quantité | E4: Date | F4: Ecart | G4: Quantité | H4: Date relevé dépositaire | I4: Ecart | J4: Commentaires
B5: de l'instrument financier | C5: inventaire | D5: société | E5: attestation | F5: émetteur | G5: dépositaire | I5: dépositaire
B7: =Inventaire!C16 -> Heka Invest - Actions | C7: =Inventaire!D16 -> 14423076 | D7: 14423076 | E7: 45657 | F7: =C7-D7 -> 0 | G7: 14423076 | H7: 46022 | I7: =C7-G7 -> 0
F8: =C8-D8 -> 0 | I8: =C8-G8 -> 0
F9: =C9-D9 -> 0 | I9: =C9-G9 -> 0
F10: =C10-D10 -> 0 | I10: =C10-G10 -> 0
F11: =C11-D11 -> 0 | I11: =C11-G11 -> 0
C12: =SUM(C6:C11) -> 14423076 | D12: =SUM(D6:D11) -> 14423076 | F12: =SUM(F6:F11) -> 0 | G12: =SUM(G6:G11) -> 14423076 | I12: =SUM(I6:I11) -> 0
F13: =IF(ABS(F12)<0.01,"","Anomalie AIC") | I13: =IF(ABS(I12)<0.01,"","Anomalie dépositaire")
F15: Contrôle formule
E16: Contrôle | F16: =C12-D12 -> 0 | H16: Contrôle | I16: =C12-G12 -> 0
B17: Contrôle avec l'inventaire | C17: Nombre de lignes | E17: Ecart | F17: =F12-F16 -> 0 | H17: Ecart | I17: =I12-I16 -> 0
B18: Rapprochement titres | C18: =COUNT(C7:C11) -> 1 | F18: =IF(ABS(F17)>0.01,"ANOMALIE","OK") -> OK | I18: =IF(ABS(I17)>0.01,"ANOMALIE","OK") -> OK
B19: inventaire | C19: =COUNT(Inventaire!G15:G22) -> 1
C20: =IF(C18-C19<>0,"Rapprochement titres incomplet","OK") -> OK | E20: Rapprochement Parts
B23: Parts émises par | C23: Quantité | D23: Quantité | E23: Date | F23: ECART | G23: Commentaires
B24: le fonds | C24: Fonds | D24: Dépositaire | E24: attestation
B26: =+'Calcul VL'!B9 -> Parts A | C26: =+'Calcul VL'!C9 -> 15379.56 | D26: 15379.56 | E26: 46022 | F26: =C26-D26 -> 0
B27: =+'Calcul VL'!B10 -> Part de commandité | C27: =+'Calcul VL'!C10 -> 1 | D27: 1 | E27: 46022 | F27: =C27-D27 -> 0
C29: =SUM(C26:C28) -> 15380.56 | D29: =SUM(D26:D28) -> 15380.56 | F29: =SUM(F26:F28) -> 0

Sheet Hors bilan
B1: ='Calcul VL'!B1 -> SANCY - SLP | C1: HORS BILAN au | D1: =Sommaire!C1 -> 46022
D5: Exercice | E5: Exercice N-1 | F5: Exercice | G5: Exercice | H5: Exercice | I5: Exercice | J5: Exercice
B6: Autres engagements (par nature de produit) | D6: =+D1 -> 46022 | E6: 45657 | F6: 39447 | G6: 39082 | H6: 38717 | I6: 38352 | J6: 37986
B8: Garanties reçues | D8: =E34 -> 0 | E8: 0
B9: dont instruments financiers reçus en garantie et non inscrits au bilan
B11: Garanties données | D11: =D34 -> 0 | E11: 0
B12: dont instruments financiers donnés en garantie et maintenus dans leur poste d'origine
B14: Engagements de financement reçu mais non encore tirés | D14: =E38 -> 0 | E14: 0
B16: Engagements de financement donnés mais non encore tirés | D16: =D38 -> 0 | E16: 0
B18: Autres engagements hors bilan
C19: Donnés | D19: =D42 -> 0 | E19: 0
C20: reçus | D20: =E42 -> 0 | E20: 179291.18
B25: =+B1 -> SANCY - SLP | C25: DETAIL DES ENGAGEMENTS HORS-BILAN au | E25: =+D1 -> 46022
D28: Engagements hors bilan
D29: Engagements donnés | E29: Engagements reçus | F29: Commentaires
B30: Garanties
B34: Sous-total | D34: =SUM(D30:D33) -> 0 | E34: =SUM(E30:E33) -> 0
B35: Engagements de financement mais non encore tirés
B38: Sous-total | D38: =SUM(D35:D37) -> 0 | E38: =SUM(E35:E37) -> 0
B39: Autres engagements hors bilan | E39: ,
B42: Sous-total | D42: =SUM(D39:D41) -> 0 | E42: =SUM(E39:E41) -> 0

Sheet PVMV
B1: ='Rappro Titres & Parts'!B1 -> SANCY - SLP | G1: SUIVI DES ACHATS VENTES SUR TITRES : | K1: =Sommaire!C1 -> 46022 | Q1: AIFM Turn over | R1: =SUMIFS(J:J,D:D,">" & T1,D:D,"<=" & K1,C:C,"<>Récap")+SUMIFS(G:G,D:D,">" & T1,D:D,"<=" & K1,C:C,"<>Récap")-R2 -> 0 | T1: =DATE(YEAR(K1)+U1,MONTH(K1),DAY(K1)) -> 45657 | U1: -1
Q2: Collective Investment Undertakings | R2: =SUMIFS(J:J,D:D,">" & T1,D:D,"<=" & K1,C:C,"<>Récap",A:A,"x")+SUMIFS(G:G,D:D,">" & T1,D:D,"<=" & K1,C:C,"<>Récap",A:A,"x") -> 0
B3: Les instruments financiers sont comptabilisés "frais inclus". | E3: ACHATS | H3: VENTES | L3: SOLDES | O3: PLUS VALUES REALISEES | P3: MOINS VALUES REALISEES | Q3: Prix de vente- prix de revient (1) | R3: Sommes des plus ou moins values (2) | S3: Contrôle (1)-(2)
C4: LIBELLE | D4: DATE OPE | E4: QTE | F4: PR UNITAIRE | G4: PR OPERATION | H4: QTE | I4: PV UNITAIRE | J4: PV OPERATION | K4: PR OPERATION | L4: QUANTITE | M4: PR CUMULE | N4: PR UNIT. MOYEN | Q4: Plus ou moins values nettes | R4: Plus ou moins values nettes | S4: Contrôle
C5: Report | N5: =+IF(L5=0,0,M5/L5) -> 0 | O5: =IF(J5-K5>0,J5-K5,0) -> 0 | P5: =IF(J5-K5<0,J5-K5,0) -> 0 | Q5: =+J5-K5 -> 0 | R5: =+O5+P5 -> 0 | S5: =+Q5-R5 -> 0
B6: Heka Invest - Actions | C6: Reprise | D6: 45107 | E6: 14423076 | F6: =IF(E6=0,0,G6/E6) -> 1.04 | G6: 14999999 | I6: =IF(H6=0,0,J6/H6) -> 0 | K6: =+H6*N5 -> 0 | L6: =+L5+E6-H6 -> 14423076 | M6: =+M5+G6-K6 -> 14999999 | N6: =+IF(L6=0,0,M6/L6) -> 1.04 | O6: =IF(J6-K6>0,J6-K6,0) -> 0 | P6: =IF(J6-K6<0,J6-K6,0) -> 0 | Q6: =+J6-K6 -> 0 | R6: =+O6+P6 -> 0 | S6: =+Q6-R6 -> 0
B7: =B6 -> Heka Invest - Actions | F7: =IF(E7=0,0,G7/E7) -> 0 | I7: =IF(H7=0,0,J7/H7) -> 0 | K7: =+H7*N6 -> 0 | L7: =+L6+E7-H7 -> 14423076 | M7: =+M6+G7-K7 -> 14999999 | N7: =+IF(L7=0,0,M7/L7) -> 1.04 | O7: =IF(J7-K7>0,J7-K7,0) -> 0 | P7: =IF(J7-K7<0,J7-K7,0) -> 0 | Q7: =+J7-K7 -> 0 | R7: =+O7+P7 -> 0 | S7: =+Q7-R7 -> 0
B8: =B7 -> Heka Invest - Actions | F8: =IF(E8=0,0,G8/E8) -> 0 | I8: =IF(H8=0,0,J8/H8) -> 0 | K8: =+H8*N7 -> 0 | L8: =+L7+E8-H8 -> 14423076 | M8: =+M7+G8-K8 -> 14999999 | N8: =+IF(L8=0,0,M8/L8) -> 1.04 | O8: =IF(J8-K8>0,J8-K8,0) -> 0 | P8: =IF(J8-K8<0,J8-K8,0) -> 0 | Q8: =+J8-K8 -> 0 | R8: =+O8+P8 -> 0 | S8: =+Q8-R8 -> 0
B9: =B8 -> Heka Invest - Actions | F9: =IF(E9=0,0,G9/E9) -> 0 | I9: =IF(H9=0,0,J9/H9) -> 0 | K9: =+H9*N8 -> 0 | L9: =+L8+E9-H9 -> 14423076 | M9: =+M8+G9-K9 -> 14999999 | N9: =+IF(L9=0,0,M9/L9) -> 1.04 | O9: =IF(J9-K9>0,J9-K9,0) -> 0 | P9: =IF(J9-K9<0,J9-K9,0) -> 0 | Q9: =+J9-K9 -> 0 | R9: =+O9+P9 -> 0 | S9: =+Q9-R9 -> 0
B10: =B9 -> Heka Invest - Actions | F10: =IF(E10=0,0,G10/E10) -> 0 | I10: =IF(H10=0,0,J10/H10) -> 0 | K10: =+H10*N9 -> 0 | L10: =+L9+E10-H10 -> 14423076 | M10: =+M9+G10-K10 -> 14999999 | N10: =+IF(L10=0,0,M10/L10) -> 1.04 | O10: =IF(J10-K10>0,J10-K10,0) -> 0 | P10: =IF(J10-K10<0,J10-K10,0) -> 0 | Q10: =+J10-K10 -> 0 | R10: =+O10+P10 -> 0 | S10: =+Q10-R10 -> 0
B11: =B10 -> Heka Invest - Actions | F11: =IF(E11=0,0,G11/E11) -> 0 | I11: =IF(H11=0,0,J11/H11) -> 0 | K11: =+H11*N10 -> 0 | L11: =+L10+E11-H11 -> 14423076 | M11: =+M10+G11-K11 -> 14999999 | N11: =+IF(L11=0,0,M11/L11) -> 1.04 | O11: =IF(J11-K11>0,J11-K11,0) -> 0 | P11: =IF(J11-K11<0,J11-K11,0) -> 0 | Q11: =+J11-K11 -> 0 | R11: =+O11+P11 -> 0 | S11: =+Q11-R11 -> 0
B12: =B11 -> Heka Invest - Actions | F12: =IF(E12=0,0,G12/E12) -> 0 | I12: =IF(H12=0,0,J12/H12) -> 0 | K12: =+H12*N11 -> 0 | L12: =+L11+E12-H12 -> 14423076 | M12: =+M11+G12-K12 -> 14999999 | N12: =+IF(L12=0,0,M12/L12) -> 1.04 | O12: =IF(J12-K12>0,J12-K12,0) -> 0 | P12: =IF(J12-K12<0,J12-K12,0) -> 0 | Q12: =+J12-K12 -> 0 | R12: =+O12+P12 -> 0 | S12: =+Q12-R12 -> 0
B13: =B12 -> Heka Invest - Actions | F13: =IF(E13=0,0,G13/E13) -> 0 | I13: =IF(H13=0,0,J13/H13) -> 0 | K13: =+H13*N7 -> 0 | L13: =+L12+E13-H13 -> 14423076 | M13: =+M12+G13-K13 -> 14999999 | N13: =+IF(L13=0,0,M13/L13) -> 1.04 | O13: =IF(J13-K13>0,J13-K13,0) -> 0 | P13: =IF(J13-K13<0,J13-K13,0) -> 0 | Q13: =+J13-K13 -> 0 | R13: =+O13+P13 -> 0 | S13: =+Q13-R13 -> 0
B15: =B13 -> Heka Invest - Actions | C15: Récap | D15: =+$K$1 -> 46022 | E15: =SUM(E5:E13) -> 14423076 | F15: =+IF(E15=0,0,G15/E15) -> 1.04 | G15: =SUM(G5:G13) -> 14999999 | H15: =SUM(H5:H13) -> 0 | I15: =+IF(H15=0,0,J15/H15) -> 0 | J15: =SUM(J5:J13) -> 0 | K15: =SUM(K5:K13) -> 0 | L15: =L13 -> 14423076 | M15: =+M13 -> 14999999 | N15: =+IF(L15=0,0,M15/L15) -> 1.04 | O15: =SUM(O5:O13) -> 0 | P15: =SUM(P5:P13) -> 0 | Q15: =+J15-K15 -> 0 | R15: =+O15+P15 -> 0 | S15: =+Q15-R15 -> 0
C16: Report | N16: =+IF(L16=0,0,M16/L16) -> 0 | O16: =IF(J16-K16>0,J16-K16,0) -> 0 | P16: =IF(J16-K16<0,J16-K16,0) -> 0 | Q16: =+J16-K16 -> 0 | R16: =+O16+P16 -> 0 | S16: =+Q16-R16 -> 0
B17: XX | F17: =IF(E17=0,0,G17/E17) -> 0 | I17: =IF(H17=0,0,J17/H17) -> 0 | K17: =+H17*N16 -> 0 | L17: =+L16+E17-H17 -> 0 | M17: =+M16+G17-K17 -> 0 | N17: =+IF(L17=0,0,M17/L17) -> 0 | O17: =IF(J17-K17>0,J17-K17,0) -> 0 | P17: =IF(J17-K17<0,J17-K17,0) -> 0 | Q17: =+J17-K17 -> 0 | R17: =+O17+P17 -> 0 | S17: =+Q17-R17 -> 0
B18: =B17 -> XX | F18: =IF(E18=0,0,G18/E18) -> 0 | I18: =IF(H18=0,0,J18/H18) -> 0 | K18: =+H18*N17 -> 0 | L18: =+L17+E18-H18 -> 0 | M18: =+M17+G18-K18 -> 0 | N18: =+IF(L18=0,0,M18/L18) -> 0 | O18: =IF(J18-K18>0,J18-K18,0) -> 0 | P18: =IF(J18-K18<0,J18-K18,0) -> 0 | Q18: =+J18-K18 -> 0 | R18: =+O18+P18 -> 0 | S18: =+Q18-R18 -> 0
B19: =B18 -> XX | F19: =IF(E19=0,0,G19/E19) -> 0 | I19: =IF(H19=0,0,J19/H19) -> 0 | K19: =+H19*N18 -> 0 | L19: =+L18+E19-H19 -> 0 | M19: =+M18+G19-K19 -> 0 | N19: =+IF(L19=0,0,M19/L19) -> 0 | O19: =IF(J19-K19>0,J19-K19,0) -> 0 | P19: =IF(J19-K19<0,J19-K19,0) -> 0 | Q19: =+J19-K19 -> 0 | R19: =+O19+P19 -> 0 | S19: =+Q19-R19 -> 0
B20: =B19 -> XX | F20: =IF(E20=0,0,G20/E20) -> 0 | I20: =IF(H20=0,0,J20/H20) -> 0 | K20: =+H20*N19 -> 0 | L20: =+L19+E20-H20 -> 0 | M20: =+M19+G20-K20 -> 0 | N20: =+IF(L20=0,0,M20/L20) -> 0 | O20: =IF(J20-K20>0,J20-K20,0) -> 0 | P20: =IF(J20-K20<0,J20-K20,0) -> 0 | Q20: =+J20-K20 -> 0 | R20: =+O20+P20 -> 0 | S20: =+Q20-R20 -> 0
B21: =+B20 -> XX | C21: Récap | D21: =+$K$1 -> 46022 | E21: =SUM(E16:E20) -> 0 | F21: =+IF(E21=0,0,G21/E21) -> 0 | G21: =SUM(G16:G20) -> 0 | H21: =SUM(H16:H20) -> 0 | I21: =+IF(H21=0,0,J21/H21) -> 0 | J21: =SUM(J16:J20) -> 0 | K21: =SUM(K16:K20) -> 0 | L21: =+L20 -> 0 | M21: =+M20 -> 0 | N21: =+IF(L21=0,0,M21/L21) -> 0 | O21: =SUM(O16:O20) -> 0 | P21: =SUM(P16:P20) -> 0 | Q21: =+J21-K21 -> 0 | R21: =+O21+P21 -> 0 | S21: =+Q21-R21 -> 0
B22: TOTAL | C22: Récap | D22: =+$K$1 -> 46022 | E22: =+SUM(E5:E21)/2 -> 14423076 | G22: =+SUM(G5:G21)/2 -> 14999999 | J22: =SUM(J5:J15)/2 -> 0 | K22: =SUM(K5:K15)/2 -> 0 | L22: =L15+L21 -> 14423076 | M22: =M15+M21 -> 14999999 | N22: =N15+N21 -> 1.04 | O22: =SUM(O5:O21)/2 -> 0 | P22: =SUM(P5:P21)/2 -> 0 | Q22: =+J22-K22 -> 0 | R22: =+O22+P22 -> 0 | S22: =SUM(S5:S15) -> 0
H23: Contrôle de cohérence | J23: Total PR achat - Total PR Vente | M23: =+G22-K22 -> 14999999 | N23: Comptabilité | S23: =IF(ABS(S22)>0.01,"ANOMALIE","OK") -> OK
J24: Ecart | M24: =+M22-M23 -> 0 | N24: Reprise PV/MV
J25: Inventaire PR | M25: =Inventaire!H30 -> 14999999 | N25: Ecart | O25: =O22-O23+O24 -> 0 | P25: =P22-P23+P24 -> 0
J26: Ecart | M26: =+M22-M25 -> 0 | N26: Contrôle | O26: =IF(ABS(O25)>0.01,"ANOMALIE","OK") -> OK | P26: =IF(ABS(P25)>0.01,"ANOMALIE","OK") -> OK
N27: Frais de transaction antérieurs :
N28: Ecart | O28: =O22+P22-O23-P23-O27 -> 0
O29: =IF(ABS(O28)<0.01,"OK","ANOMALIE") -> OK

Sheet Emprunt
B1: =Sommaire!A1 -> SANCY - SLP | G1: EMPRUNT AU | I1: =Sommaire!C1 -> 46022
B3: Emprunt caisse d'épargne haut de France | F3: Montant tiré
B4: Date de début de période | C4: Date de fin de période | D4: Durée | E4: Base | F4: Intitulé | G4: Mouvements | H4: Solde progressif | I4: marge | J4: Taux Euribor | K4: Intérêts payés | L4: Intérêts courus
G16: =SUM(G5:G15) -> 0 | K16: =SUM(K6:K15) -> 0 | L16: =SUM(L6:L15) -> 0
B19: Emprunt caisse d'épargne haut de France | F19: Montant non tiré
B20: Date de début de période | C20: Date de fin de période | D20: Durée | E20: Base | F20: Intitulé | G20: Mouvements | H20: Solde progressif | I20: Taux appliqué | J20: Intérêts | K20: Intérêts courus
G65: =G54 -> 0 | H65: =+H26 -> 0 | J65: =SUM(J22:J64) -> 0 | K65: =SUM(K57:K64) -> 0
J68: Intérêts courus | K68: =+K65+L16 -> 0
J69: Emprunt | K69: =+G16 -> 0

Sheet Intérêts CC
B1: =PVMV!B1 -> SANCY - SLP | E1: Compte courant | K1: =+Sommaire!C1 -> 46022
B6: Date de début de période | C6: Date de fin de période | D6: Intitulé | E6: Durée | F6: Base | G6: Mouvements | H6: Solde progressif | I6: Taux appliqué | J6: Intérêts | K6: Intérêts courus | L6: Intérêts réglés
B8: 45008 | C8: 45107 | D8: Apport | E8: =+C8-B8 -> 99 | F8: 365 | H8: =+G8+H7 -> 0 | J8: =ROUND((H8)*I8*E8/F8,2) -> 0 | K8: =J8 -> 0
E9: =+C9-B9 -> 0 | F9: 365 | H9: =+G9+H8 -> 0 | J9: =ROUND((H9)*I9*E9/F9,2) -> 0 | K9: =J9 -> 0
E10: =+C10-B10 -> 0 | F10: 365 | H10: =+G10+H9 -> 0 | J10: =ROUND((H10)*I10*E10/F10,2) -> 0 | K10: =J10 -> 0
E11: =+C11-B11 -> 0 | F11: 365 | H11: =+G11+H10 -> 0 | J11: =ROUND((H11)*I11*E11/F11,2) -> 0 | K11: =J11 -> 0
E12: =+C12-B12 -> 0 | F12: 365 | H12: =+G12+H11 -> 0 | J12: =ROUND((H12)*I12*E12/F12,2) -> 0 | K12: =J12 -> 0
E13: =+C13-B13 -> 0 | F13: 365 | H13: =+G13+H12 -> 0 | J13: =ROUND((H13)*I13*E13/F13,2) -> 0 | K13: =J13 -> 0
H14: =+G14+H13 -> 0
E15: =SUM(E8:E12) -> 99 | G15: =+G11 -> 0 | H15: =H14 -> 0 | J15: =SUM(J8:J14) -> 0 | K15: =SUM(K8:K14) -> 0 | L15: =SUM(L8:L12) -> 0
H16: Provision intérêts | I16: 1 | J16: =-J15 -> 0 | K16: =-K15 -> 0
H17: Inventaire | J17: =J15+J16 -> 0 | K17: =K15+K16 -> 0
B18: Taux d'intérêts : 5%
B19: L'Avance en Compte Courant devra être remboursée par la Société aux Associés-Prêteurs à la date du dixième anniversaire de la Date de Mise à Disposition (l'Échéance).
B20: échéance : 07/11/2022
B21: Nouvel échéance : 07/11/2032

Sheet Intérêts OC
B1: ='Intérêts CC'!B1 -> SANCY - SLP | I1: Intérêts courus | M1: =Sommaire!C1 -> 46022
F3: Capitalisation des intérêts au 05/10
B4: Date de début de période | C4: Date d'arrêté | D4: Durée | E4: Base | F4: Nominal | G4: INTERETS capitalisés | I4: INTERETS CAPITALISES cumulés | J4: Taux appliqué | K4: INTERETS | L4: Intérêts courus sur nominal | M4: Intérêts courus sur intérêts capitalisés | N4: Contrôle PR unitaire (int. Compris)
D5: =C5-B5 -> 0 | E5: 360 | J5: 0.08 | K5: =ROUND((F5+I5)*J5*D5/E5,2) -> 0 | L5: =+F5*D5*J5/E5 -> 0
D6: =C6-B6 -> 0 | E6: 360 | F6: =F5 -> 0 | I6: =G6+I5 -> 0 | J6: 0.08 | K6: =ROUND((F6+I6)*J6*D6/E6,2) -> 0 | L6: =+F6*D6*J6/E6 -> 0
D7: =+C7-B7 -> 0 | E7: 360 | F7: =F6 -> 0 | I7: =G7+I6 -> 0 | J7: 0.08 | K7: =ROUND((F7+I7)*J7*D7/E7,2) -> 0 | L7: =+F7*D7*J7/E7 -> 0 | M7: =+I7*D7*J7/E7 -> 0
D8: =+C8-B8 -> 0 | E8: 360 | F8: =F7 -> 0 | I8: =G8+I7 -> 0 | J8: 0.08 | K8: =ROUND((F8+I8)*J8*D8/E8,2) -> 0 | L8: =+F8*D8*J8/E8 -> 0 | M8: =+I8*D8*J8/E8 -> 0
D9: =+C9-B9 -> 0 | E9: 360 | F9: =F8 -> 0 | I9: =G9+I8 -> 0 | J9: 0.08 | K9: =ROUND((F9+I9)*J9*D9/E9,2) -> 0 | L9: =+F9*D9*J9/E9 -> 0 | M9: =+I9*D9*J9/E9 -> 0
D10: =+C10-B10 -> 0 | E10: 360 | F10: =F9 -> 0 | I10: =G10+I9 -> 0 | J10: 0.08 | K10: =ROUND((F10+I10)*J10*D10/E10,2) -> 0 | L10: =+F10*D10*J10/E10 -> 0 | M10: =+I10*D10*J10/E10 -> 0
D11: =+C11-B11 -> 0 | E11: 360 | F11: =F10 -> 0 | I11: =G11+I10 -> 0 | K11: =ROUND((F11+I11)*J11*D11/E11,2) -> 0 | L11: =+F11*D11*J11/E11 -> 0 | M11: =+I11*D11*J11/E11 -> 0
D12: =+C12-B12 -> 0 | E12: 360 | F12: =F11 -> 0 | I12: =G12+I11 -> 0 | K12: =ROUND((F12+I12)*J12*D12/E12,2) -> 0 | L12: =+F12*D12*J12/E12 -> 0 | M12: =+I12*D12*J12/E12 -> 0
D13: =+C13-B13 -> 0 | E13: 360 | F13: =F12 -> 0 | I13: =G13+I12 -> 0 | K13: =ROUND((F13+I13)*J13*D13/E13,2) -> 0 | L13: =+F13*D13*J13/E13 -> 0 | M13: =+I13*D13*J13/E13 -> 0
E14: 360 | F14: =F13 -> 0 | I14: =I13 -> 0
B15: Total | F15: =F14 -> 0 | G15: =SUM(G5:G14) -> 0 | I15: =I14 -> 0 | K15: =SUM(K5:K14) -> 0 | L15: =SUM(L5:L14) -> 0 | M15: =SUM(M5:M14) -> 0 | P15: =K15-L15-M15-G15 -> 0
B16: Date d'échéance : | F16: Provision 0% | G16: 0 | J16: Provision intérêts courus | K16: 0 | L16: 0 | M16: =-M15 -> 0 | P16: =IF(ABS(ROUND((P15),2))<=0.01,"Contrôle OK","Erreur") -> Contrôle OK
G17: =SUM(G15:G16) -> 0 | J17: Intérêts courus nets | L17: =SUM(L15:L16) -> 0 | M17: =SUM(M15:M16) -> 0
K21: Inventaire | L21: Contrôle
E22: Total intérêts courus | I22: =L17+M17 -> 0 | K22: =Inventaire!M18 -> 0 | L22: =IF(ROUND(I22,2)=ROUND(K22,2),"OK","ERREUR") -> OK
E23: Total intérêts capitalisés | I23: =G17 -> 0 | K23: =Inventaire!I18 -> 0 | L23: =IF(ROUND(I23,2)=ROUND(K23,2),"OK","ERREUR") -> OK

Sheet Sous-Rachat
B1: ='Liste porteurs selon versement '!A1 -> SANCY - SLP | D1: Suivi des Porteurs | F1: =Sommaire!C1 -> 46022
B2: Euro
D4: Nature opération
B5: Parts A | C5: 1000 | D5: TP | E5: Transfert de Parts
B6: Parts commandité | C6: 1000 | D6: ADF | E6: Appel de fonds
D7: DD | E7: Distribution définitive
D8: DB | E8: Distribition Bloquée | K8: Date opération
D9: DP | E9: Distribution provisoire | K9: %ADF
D10: RD | E10: Rappel de distribution | K10: Nature opération
D11: ENG | E11: Engagement supplémentaire | M11: TP | N11: ADF | O11: ADF | P11: DD | Q11: DB | R11: DP | S11: RD
F12: 45657 | M12: Transfert de parts 1T2025 | U12: =F1 -> 46022
D13: Engagement en Euros | E13: montant libéré | F13: Nombre de parts à date de situation | G13: Total des versements à date de situation | H13: % libéré | I13: reste a appeler | J13: Distribution | K13: Distribution en % | L13: Engagement à date de situation | M13: Mouvements de parts 1T2025 | N13: Affectation ADF | O13: ADF Test | P13: Distribution définitive Test | Q13: Distribution Bloqué Test | R13: Distribution provisoire Test | S13: Rappel de distribution Test | U13: Nombre de parts | V13: Total des versements | W13: % libéré | X13: Montant non appelé | Y13: Distribution | Z13: Distribution en % | AA13: Engagement Total
B14: Parts A
B16: Pantheon Global Private Credit Gt Fund, L.P. | C16: A | D16: 2306930 | E16: 2280038.1 | F16: =+D16/1000 -> 2306.93 | G16: 2280038.1 | H16: =+G16/L16 -> 0.988343 | I16: =L16-G16 -> 26891.88 | K16: =J16/D16 -> 0 | L16: 2306930 | U16: =F16+SUMIF($M$11:$T$11,"TP",$M16:$T16) -> 2306.93 | V16: =G16+SUMIF($M$11:$T$11,"ADF",$M16:$T16) -> 2280038.1 | W16: =IFERROR(V16/AA16,0) -> 0.988343 | X16: =AA16-V16 -> 26891.88 | Y16: =J16+SUMIF($M$11:$T$11,"DD",$M16:$T16)+SUMIF($M$11:$T$11,"DB",$M16:$T16)+SUMIF($M$11:$T$11,"DP",$M16:$T16)-SUMIF($M$11:$T$11,"RD",$M16:$T16) -> 0 | Z16: =Y16/AA16 -> 0 | AA16: =$C$5*U16 -> 2306930
B17: Pantheon Global Private Credit Ho Fund, L.P. | C17: A | D17: 1537960 | E17: 1520032 | F17: =+D17/1000 -> 1537.96 | G17: 1520032 | H17: =+G17/L17 -> 0.988343 | I17: =L17-G17 -> 17928 | K17: =J17/D17 -> 0 | L17: 1537960 | U17: =F17+SUMIF($M$11:$T$11,"TP",$M17:$T17) -> 1537.96 | V17: =G17+SUMIF($M$11:$T$11,"ADF",$M17:$T17) -> 1520032 | W17: =IFERROR(V17/AA17,0) -> 0.988343 | X17: =AA17-V17 -> 17928 | Y17: =J17+SUMIF($M$11:$T$11,"DD",$M17:$T17)+SUMIF($M$11:$T$11,"DB",$M17:$T17)+SUMIF($M$11:$T$11,"DP",$M17:$T17)-SUMIF($M$11:$T$11,"RD",$M17:$T17) -> 0 | Z17: =Y17/AA17 -> 0 | AA17: =$C$5*U17 -> 1537960
B18: Abacus Private Credit | C18: A | D18: 1264740 | E18: 1249996.9 | F18: =+D18/1000 -> 1264.74 | G18: 1249996.9 | H18: =+G18/L18 -> 0.988343 | I18: =L18-G18 -> 14743.07 | K18: =J18/D18 -> 0 | L18: 1264740 | U18: =F18+SUMIF($M$11:$T$11,"TP",$M18:$T18) -> 1264.74 | V18: =G18+SUMIF($M$11:$T$11,"ADF",$M18:$T18) -> 1249996.9 | W18: =IFERROR(V18/AA18,0) -> 0.988343 | X18: =AA18-V18 -> 14743.07 | Y18: =J18+SUMIF($M$11:$T$11,"DD",$M18:$T18)+SUMIF($M$11:$T$11,"DB",$M18:$T18)+SUMIF($M$11:$T$11,"DP",$M18:$T18)-SUMIF($M$11:$T$11,"RD",$M18:$T18) -> 0 | Z18: =Y18/AA18 -> 0 | AA18: =$C$5*U18 -> 1264740
B19: Mw River | C19: A | D19: 1770640 | E19: 1749999.6 | F19: =+D19/1000 -> 1770.64 | G19: 1749999.6 | H19: =+G19/L19 -> 0.988343 | I19: =L19-G19 -> 20640.35 | K19: =J19/D19 -> 0 | L19: 1770640 | U19: =F19+SUMIF($M$11:$T$11,"TP",$M19:$T19) -> 1770.64 | V19: =G19+SUMIF($M$11:$T$11,"ADF",$M19:$T19) -> 1749999.6 | W19: =IFERROR(V19/AA19,0) -> 0.988343 | X19: =AA19-V19 -> 20640.35 | Y19: =J19+SUMIF($M$11:$T$11,"DD",$M19:$T19)+SUMIF($M$11:$T$11,"DB",$M19:$T19)+SUMIF($M$11:$T$11,"DP",$M19:$T19)-SUMIF($M$11:$T$11,"RD",$M19:$T19) -> 0 | Z19: =Y19/AA19 -> 0 | AA19: =$C$5*U19 -> 1770640
B20: Eiger | C20: A | D20: 8436050 | E20: 8337711 | F20: =+D20/1000 -> 8436.05 | G20: 8337711 | H20: =+G20/L20 -> 0.988343 | I20: =L20-G20 -> 98339.03 | K20: =J20/D20 -> 0 | L20: 8436050 | U20: =F20+SUMIF($M$11:$T$11,"TP",$M20:$T20) -> 8436.05 | V20: =G20+SUMIF($M$11:$T$11,"ADF",$M20:$T20) -> 8337711 | W20: =IFERROR(V20/AA20,0) -> 0.988343 | X20: =AA20-V20 -> 98339.03 | Y20: =J20+SUMIF($M$11:$T$11,"DD",$M20:$T20)+SUMIF($M$11:$T$11,"DB",$M20:$T20)+SUMIF($M$11:$T$11,"DP",$M20:$T20)-SUMIF($M$11:$T$11,"RD",$M20:$T20) -> 0 | Z20: =Y20/AA20 -> 0 | AA20: =$C$5*U20 -> 8436050
B21: VI Advisory | C21: A | D21: 12650 | E21: 12502.54 | F21: =+D21/1000 -> 12.65 | G21: 12502.54 | H21: =+G21/L21 -> 0.98834308 | I21: =L21-G21 -> 147.46 | K21: =J21/D21 -> 0 | L21: 12650 | U21: =F21+SUMIF($M$11:$T$11,"TP",$M21:$T21) -> 12.65 | V21: =G21+SUMIF($M$11:$T$11,"ADF",$M21:$T21) -> 12502.54 | W21: =IFERROR(V21/AA21,0) -> 0.98834308 | X21: =AA21-V21 -> 147.46 | Y21: =J21+SUMIF($M$11:$T$11,"DD",$M21:$T21)+SUMIF($M$11:$T$11,"DB",$M21:$T21)+SUMIF($M$11:$T$11,"DP",$M21:$T21)-SUMIF($M$11:$T$11,"RD",$M21:$T21) -> 0 | Z21: =Y21/AA21 -> 0 | AA21: =$C$5*U21 -> 12650
B22: AMER PARTNERS | C22: A | D22: 37940 | E22: 37497.73 | F22: =+D22/1000 -> 37.94 | G22: 37497.73 | H22: =+G22/L22 -> 0.98834291 | I22: =L22-G22 -> 442.27 | K22: =J22/D22 -> 0 | L22: 37940 | U22: =F22+SUMIF($M$11:$T$11,"TP",$M22:$T22) -> 37.94 | V22: =G22+SUMIF($M$11:$T$11,"ADF",$M22:$T22) -> 37497.73 | W22: =IFERROR(V22/AA22,0) -> 0.98834291 | X22: =AA22-V22 -> 442.27 | Y22: =J22+SUMIF($M$11:$T$11,"DD",$M22:$T22)+SUMIF($M$11:$T$11,"DB",$M22:$T22)+SUMIF($M$11:$T$11,"DP",$M22:$T22)-SUMIF($M$11:$T$11,"RD",$M22:$T22) -> 0 | Z22: =Y22/AA22 -> 0 | AA22: =$C$5*U22 -> 37940
B23: KTALYST INVESTMENTS | C23: A | D23: 12650 | E23: 12502.54 | F23: =+D23/1000 -> 12.65 | G23: 12502.54 | H23: =+G23/L23 -> 0.98834308 | I23: =L23-G23 -> 147.46 | K23: =J23/D23 -> 0 | L23: 12650 | U23: =F23+SUMIF($M$11:$T$11,"TP",$M23:$T23) -> 12.65 | V23: =G23+SUMIF($M$11:$T$11,"ADF",$M23:$T23) -> 12502.54 | W23: =IFERROR(V23/AA23,0) -> 0.98834308 | X23: =AA23-V23 -> 147.46 | Y23: =J23+SUMIF($M$11:$T$11,"DD",$M23:$T23)+SUMIF($M$11:$T$11,"DB",$M23:$T23)+SUMIF($M$11:$T$11,"DP",$M23:$T23)-SUMIF($M$11:$T$11,"RD",$M23:$T23) -> 0 | Z23: =Y23/AA23 -> 0 | AA23: =$C$5*U23 -> 12650
B24: TOTAL PARTS A | C24: A1 | D24: =SUM(D16:D23) -> 15379560 | E24: =SUM(E16:E23) -> 15200280 | F24: =SUM(F16:F23) -> 15379.56 | G24: =SUM(G16:G23) -> 15200280 | H24: =+G24/L24 -> 0.988343 | I24: =SUM(I16:I23) -> 179279.52 | J24: =SUM(J16:J23) -> 0 | K24: =J24/D24 -> 0 | L24: =SUM(L16:L23) -> 15379560 | U24: =SUM(U16:U23) -> 15379.56 | V24: =SUM(V16:V23) -> 15200280 | W24: =V24/AA24 -> 0.988343 | X24: =SUM(X16:X23) -> 179279.52 | Y24: =SUM(Y16:Y23) -> 0 | AA24: =SUM(AA16:AA23) -> 15379560
B28: Part de Commandité | C28: Commandité | D28: 1000 | E28: 988.34 | F28: 1 | G28: 988.34 | H28: =+G28/L28 -> 0.98834 | I28: =D28-G28 -> 11.66 | K28: =J28/D28 -> 0 | L28: =D28 -> 1000 | U28: =F28+SUMIF($M$11:$T$11,"TP",$M28:$T28) -> 1 | V28: =G28+SUMIF($M$11:$T$11,"ADF",$M28:$T28) -> 988.34 | W28: =IFERROR(V28/AA28,0) -> 0.98834 | X28: =AA28-V28 -> 11.66 | Y28: =J28+SUMIF($M$11:$T$11,"DD",$M28:$T28)+SUMIF($M$11:$T$11,"DB",$M28:$T28)+SUMIF($M$11:$T$11,"DP",$M28:$T28)-SUMIF($M$11:$T$11,"RD",$M28:$T28) -> 0 | Z28: =Y28/AA28 -> 0 | AA28: =$C$5*U28 -> 1000
B29: Total PARTS Commandité | D29: =D28 -> 1000 | E29: =SUM(E28) -> 988.34 | F29: =F28 -> 1 | G29: =G28 -> 988.34 | H29: =H28 -> 0.98834 | I29: =I28 -> 11.66 | J29: =J28 -> 0 | K29: =K28 -> 0 | L29: =L28 -> 1000 | U29: =U28 -> 1 | V29: =V28 -> 988.34 | W29: =IFERROR(V29/AA29,0) -> 0.98834 | X29: =X28 -> 11.66 | Y29: =Y28 -> 0 | Z29: =Y29/AA29 -> 0 | AA29: =AA28 -> 1000
B31: TOTAL PARTS | D31: =D24+D29 -> 15380560 | E31: =+E24+E29 -> 15201269 | F31: =+F29+F24 -> 15380.56 | G31: =+G29+G24 -> 15201269 | H31: =E31/D31 -> 0.988343 | I31: =+I29+I24 -> 179291.18 | J31: =+J29+J24 -> 0 | K31: =J31/D31 -> 0 | L31: =+L29+L24 -> 15380560 | U31: =U24+U29 -> 15380.56 | V31: =V24+V29 -> 15201269 | W31: =V31/AA31 -> 0.988343 | X31: =X24+X29 -> 179291.18 | Y31: =Y24+Y29 -> 0 | AA31: =AA24+AA29 -> 15380560

Sheet Liste porteurs selon versement 
A1: =Inventaire!B1 -> SANCY - SLP | C1: Liste des porteurs | E1: =Sommaire!C1 -> 46022
B4: Type de parts | C4: Nbre de parts | D4: VL
B5: A | C5: =Inventaire!F8 -> 15379.56 | D5: =Inventaire!F9 -> 745.47027
B6: Commandité | C6: =Inventaire!G8 -> 1 | D6: =Inventaire!G9 -> 745.47027
A9: Souscripteurs | B9: Type de parts | C9: Nb de parts soucrites | D9: Valeur unitaire | E9: Evaluation
A10: ='Sous-Rachat'!B16 -> Pantheon Global Private Credit Gt Fund, L.P. | B10: =VLOOKUP(A10,'Sous-Rachat'!$B$16:$C$24,2,FALSE) -> A | C10: =VLOOKUP(A10,'Sous-Rachat'!$B$16:$F$24,5,FALSE) -> 2306.93 | D10: =VLOOKUP(B10,$B$5:$D$6,3,FALSE) -> 745.47027 | E10: =C10*D10 -> 1719747.7
A11: Total Pantheon Global Private Credit Gt Fund, L.P. | E11: =SUBTOTAL(9,E10:E10) -> 1719747.7
A12: ='Sous-Rachat'!B17 -> Pantheon Global Private Credit Ho Fund, L.P. | B12: =VLOOKUP(A12,'Sous-Rachat'!$B$16:$C$24,2,FALSE) -> A | C12: =VLOOKUP(A12,'Sous-Rachat'!$B$16:$F$24,5,FALSE) -> 1537.96 | D12: =VLOOKUP(B12,$B$5:$D$6,3,FALSE) -> 745.47027 | E12: =C12*D12 -> 1146503.5
A13: Total Pantheon Global Private Credit Ho Fund, L.P. | E13: =SUBTOTAL(9,E12:E12) -> 1146503.5
A14: ='Sous-Rachat'!B18 -> Abacus Private Credit | B14: =VLOOKUP(A14,'Sous-Rachat'!$B$16:$C$24,2,FALSE) -> A | C14: =VLOOKUP(A14,'Sous-Rachat'!$B$16:$F$24,5,FALSE) -> 1264.74 | D14: =VLOOKUP(B14,$B$5:$D$6,3,FALSE) -> 745.47027 | E14: =C14*D14 -> 942826.07
A15: Total Abacus Private Credit | E15: =SUBTOTAL(9,E14:E14) -> 942826.07
A16: ='Sous-Rachat'!B19 -> Mw River | B16: =VLOOKUP(A16,'Sous-Rachat'!$B$16:$C$24,2,FALSE) -> A | C16: =VLOOKUP(A16,'Sous-Rachat'!$B$16:$F$24,5,FALSE) -> 1770.64 | D16: =VLOOKUP(B16,$B$5:$D$6,3,FALSE) -> 745.47027 | E16: =C16*D16 -> 1319959.5
A17: Total Bow River | E17: =SUBTOTAL(9,E16:E16) -> 1319959.5
A18: ='Sous-Rachat'!B20 -> Eiger | B18: =VLOOKUP(A18,'Sous-Rachat'!$B$16:$C$24,2,FALSE) -> A | C18: =VLOOKUP(A18,'Sous-Rachat'!$B$16:$F$24,5,FALSE) -> 8436.05 | D18: =VLOOKUP(B18,$B$5:$D$6,3,FALSE) -> 745.47027 | E18: =C18*D18 -> 6288824.5
A19: Total Eiger | E19: =SUBTOTAL(9,E18:E18) -> 6288824.5
A20: ='Sous-Rachat'!B21 -> VI Advisory | B20: =VLOOKUP(A20,'Sous-Rachat'!$B$16:$C$24,2,FALSE) -> A | C20: =VLOOKUP(A20,'Sous-Rachat'!$B$16:$F$24,5,FALSE) -> 12.65 | D20: =VLOOKUP(B20,$B$5:$D$6,3,FALSE) -> 745.47027 | E20: =C20*D20 -> 9430.1989
A21: Total VI Advisory | E21: =SUBTOTAL(9,E20:E20) -> 9430.1989
A22: ='Sous-Rachat'!B22 -> AMER PARTNERS | B22: =VLOOKUP(A22,'Sous-Rachat'!$B$16:$C$24,2,FALSE) -> A | C22: =VLOOKUP(A22,'Sous-Rachat'!$B$16:$F$24,5,FALSE) -> 37.94 | D22: =VLOOKUP(B22,$B$5:$D$6,3,FALSE) -> 745.47027 | E22: =C22*D22 -> 28283.142
A23: Total AMER PARTNERS | E23: =SUBTOTAL(9,E22:E22) -> 28283.142
A24: ='Sous-Rachat'!B23 -> KTALYST INVESTMENTS | B24: =VLOOKUP(A24,'Sous-Rachat'!$B$16:$C$24,2,FALSE) -> A | C24: =VLOOKUP(A24,'Sous-Rachat'!$B$16:$F$24,5,FALSE) -> 12.65 | D24: =VLOOKUP(B24,$B$5:$D$6,3,FALSE) -> 745.47027 | E24: =C24*D24 -> 9430.1989
A25: Total KTALYST INVESTMENTS | E25: =SUBTOTAL(9,E24:E24) -> 9430.1989
A26: ='Sous-Rachat'!B28 -> Part de Commandité | B26: =VLOOKUP(A26,'Sous-Rachat'!$B$28:$C$28,2,FALSE) -> Commandité | C26: =VLOOKUP(A26,'Sous-Rachat'!$B$28:$F$28,5,FALSE) -> 1 | D26: =VLOOKUP(B26,$B$5:$D$7,3,FALSE) -> 745.47027 | E26: =C26*D26 -> 745.47027
A27: Total Parts Commandité | E27: =SUBTOTAL(9,E26:E26) -> 745.47027
A28: Total général | E28: =SUBTOTAL(9,E10:E26) -> 11465750
D31: =C32-E36 -> 0
B32: Nombre de parts | C32: =SUM(C10:C26) -> 15380.56 | D32: =+IF(C32=E36,"OK","Anomalie") -> OK
C33: Actif net selon inventaire | E33: =Inventaire!C7 -> 11465750
C35: Actif net non affecté | E35: =+E33-E28 -> 0.01480992
C36: Nombre de parts | E36: =SUM(C5:C7) -> 15380.56
C37: Ecart/part | E37: =+E35/E36 -> 9.6289859e-07
C38: Conclusion | E38: =IF(ABS(E37)<0.01,"OK","Anomalie") -> OK

Sheet Frais de gestion
B1: =+Inventaire!B1 -> SANCY - SLP | F1: Frais de gestion | H1: =Sommaire!C1 -> 46022
B4: Frais de gestion de la société de gestion | H4: Charges
B5: Rémunération de la société de gestion
B13: Sous-total frais de gestion de la société de gestion | H13: =SUM(H5:H12) -> 0
B16: Autres frais de gestion | C16: Base de calcul | D16: Prorata temporis | E16: Taux | F16: TVA | G16: Calcul provisions | H16: Charges comptabilisés
B17: Honoraires CAC
B18: Budget 2025 3 660€ HT / an
B19: Provision 1T2025 | C19: 3435 | D19: 0.25 | F19: 1.2 | G19: =C19*D19*F19 -> 1030.5
B20: Provision 2T2025 | C20: =C19 -> 3435 | D20: 0.25 | F20: 1.2 | G20: =C20*D20*F20 -> 1030.5
B21: Provision 3T2025 | C21: =C20 -> 3435 | D21: 0.25 | F21: 1.2 | G21: =C21*D21*F21 -> 1030.5 | H21: =G21 -> 1030.5
B22: Provision 4T2025 | C22: 3660 | D22: 0.25 | F22: 1.2 | G22: =C22*D22*F22 -> 1098 | H22: =G22 -> 1098
B24: Facture 1S2025 | H24: 2151
B25: Provision complémentaire 1S2025 | H25: 112.5
H28: =SUM(H19:H27) -> 4392
B29: Honoraires comptables - Aplitec
B30: AIFM budget 2025 428€ HT /an
B31: Facture AIFM 1T2025 | C31: 424 | D31: 0.25 | E31: 0.3 | F31: N/A | G31: =C31*D31 -> 106 | H31: =G31 -> 106
B32: Facture AIFM 2T2025 | C32: 428 | D32: 0.25 | E32: 0.3 | F32: N/A | G32: =C32*D32 -> 107 | H32: =G32 -> 107
B33: Facture AIFM 3T2025 | C33: 428 | D33: 0.25 | E33: 0.3 | F33: N/A | G33: =C33*D33 -> 107 | H33: =G33 -> 107
B34: Provision AIFM 4T2025 | C34: 428 | D34: 0.25 | E34: 0.3 | F34: N/A | G34: =C34*D34 -> 107 | H34: 107
B35: Tenue Comptable budget 2025 5 440€ HT /an
B36: Facture VL 1T2025 | C36: 5400 | D36: 0.25 | F36: N/A | G36: =C36*D36 -> 1350 | H36: =G36 -> 1350
B37: Facture VL 2T2025 | C37: 5440 | D37: 0.25 | F37: N/A | G37: =C37*D37 -> 1360 | H37: =G37 -> 1360
B38: Facture VL 3T2025 | C38: 5440 | D38: 0.25 | F38: N/A | G38: =C38*D38 -> 1360 | H38: =G38 -> 1360
B39: Provision VL 4T2025 | C39: 5440 | D39: 0.25 | F39: N/A | G39: =C39*D39 -> 1360 | H39: 1360
B40: Déclaration BDF budget 2025 440€ HT /an
B41: Facture BDF 1T2025 | C41: 400 | D41: 0.25 | F41: N/A | G41: =C41*D41 -> 100 | H41: =G41 -> 100
B42: Facture BDF 2T2025 | C42: 440 | D42: 0.25 | F42: N/A | G42: =C42*D42 -> 110 | H42: =G42 -> 110
B43: Facture BDF 3T2025 | C43: 440 | D43: 0.25 | F43: N/A | G43: =C43*D43 -> 110 | H43: =G43 -> 110
B44: Provision BDF 4T2025 | C44: 440 | D44: 0.25 | F44: N/A | G44: =C44*D44 -> 110 | H44: 110
B45: Dépôt VL Base GECO Budget 2024 280€ HT /an
B46: Facture dépôt VL 1T2025 | C46: 280 | D46: 0.25 | G46: =C46*D46 -> 70 | H46: =+G46 -> 70
B47: Facture dépôt VL 2T2025 | C47: 280 | D47: 0.25 | G47: =C47*D47 -> 70 | H47: =+G47 -> 70
B48: Facture dépôt VL 3T2025 | C48: 280 | D48: 0.25 | G48: =C48*D48 -> 70 | H48: =+G48 -> 70
B49: Provision dépôt VL 4T2025 | C49: 280 | D49: 0.25 | G49: =C49*D49 -> 70 | H49: =+G49 -> 70
H52: =SUM(H31:H51) -> 6567
B53: Frais de dépositaire
B54: Budget minimum 10 000 HT par an | J54: Actif net
C55: 10000 | D55: 0.25 | F55: 1.2 | G55: =C55*D55*F55 -> 3000 | J55: =Inventaire!C7 -> 11465750
B56: Distribution (500€ HT par distribution) | C56: 500 | F56: 1.2 | G56: =C56*D56*F56 -> 0
B58: Facture dépositaire 1T2025 | G58: =+G55 -> 3000 | H58: 3000
B59: Facture dépositaire 2T2025 | G59: =+G55 -> 3000 | H59: 3000
B60: Provision dépositaire 3T2025 | G60: =+G55 -> 3000 | H60: 3000
B61: Provision dépositaire 4T2025 | G61: =+G55 -> 3000 | H61: 3000
B63: Facture tenue compte espèce 1T2025 | C63: 600 | D63: 0.25 | F63: 1.2 | G63: =C63*D63*F63 -> 180 | H63: =+G63 -> 180
B64: Facture tenue compte espèce 2T2025 | C64: 600 | D64: 0.25 | F64: 1.2 | G64: =C64*D64*F64 -> 180 | H64: =+G64 -> 180
B65: Provision tenue compte espèce 3T2025 | C65: 600 | D65: 0.25 | F65: 1.2 | G65: =C65*D65*F65 -> 180 | H65: =+G65 -> 180
B66: Provision tenue compte espèce 4T2025 | C66: 600 | D66: 0.25 | F66: 1.2 | G66: =C66*D66*F66 -> 180 | H66: 180
B68: Extourne Provision dépositaire 1S2024 | H68: -6000
B69: Facture 1S2024 | H69: 6360
B70: Extourne Provision dépositaire 2S2024 | H70: -6000
B71: Facture 2S2024 | H71: 6360
H79: =SUM(H58:H78) -> 13440
B80: Frais associé Commandité | J80: Facture 2024
B81: Rem GP Budget 2025 475,87€ HT /an | J81: 1188.73
B82: Provision 1T2025 | C82: =1188.73/1.2 -> 990.60833 | D82: 0.25 | F82: 1.2 | G82: =C82*D82*F82 -> 297.1825
B83: Provision 2T2025 | C83: =C82 -> 990.60833 | D83: 0.25 | F83: 1.2 | G83: =C83*D83*F83 -> 297.1825
B84: Provision 3T2025 | C84: =C83 -> 990.60833 | D84: 0.25 | F84: 1.2 | G84: =C84*D84*F84 -> 297.1825
B85: Provision 4T2025 | C85: 475.87 | D85: 0.25 | F85: 1.2 | G85: =C85*D85*F85 -> 142.761
B87: Facture 2025 | H87: 571.04
B88: Ajustement exercices antérieurs | H88: -400.32
H90: =SUM(H81:H88) -> 170.72
B95: Total frais de gestion | H95: =+H90+H79+H28+H52 -> 24569.72
F97: Balance | H97: ='Rappro Balance'!E11 -> 1653766.7
F98: Agios
F99: Remuneration Ebd | H99: 0
F100: Commission d'arrangement | H100: 0
F101: Commission d'engagement | H101: 0
F102: Frais d'étude et d'audit acquisition et cession | H102: 0
F103: Frais sur Deals réalisé
F104: Frais sur Deals non réalisé
F105: Frais AG
F106: Assistance juridique | H106: 305.58
F107: Autres frais de gestion courante | H107: 818.62
F108: Solde d’ouverture PVMV latentes nettes | H108: -1679460.6
F109: Moins-values réalisées de l'exercice
F111: Ecart | H111: =SUM(H95:H109) -> 0
H112: =IF(ABS(H111)>0.01,"ANOMALIE","OK") -> OK

Sheet Créances_&_dettes
B1: =+Inventaire!B1 -> SANCY - SLP | D1: Créances et dettes : | G1: =Sommaire!C1 -> 46022
B4: Créances | G4: =G1 -> 46022
B6: Refacturation EMZ
B9: Crédit vendeur
C10: Nominal crédit vendeur | G10: 0 | J10: Compte 46220010
C11: Intérêt crédit vendeur | G11: 0 | J11: Compte 46220011
B13: TOTAL | G13: =SUM(G6:G12) -> 0
B16: Dettes | G16: =G1 -> 46022
B18: EMZ Partners
F22: Solde | G22: =SUM(G19:G20) -> 0
B23: Honoraires CAC - Deloitte
B24: Provision 2T2025 - Solde | G24: 112.5
B25: Provision 3T2025 | G25: 1030.5
B26: Provision 4T2025 | G26: 1098
F28: Solde | G28: =SUM(G24:G27) -> 2241
B29: Honoraires comptables - Avant reprise
F34: Solde | G34: =SUM(G30:G33) -> 0
B35: Honoraires comptables - APLITEC
B36: Provision AIFM 4T2025 | G36: 107
B37: Provision VL 4T2025 | G37: 1360
B38: Provision BDF 4T2025 | G38: 110
B39: Provision dépôt VL 4T2025 | G39: 70
F41: =F28 -> Solde | G41: =SUM(G36:G40) -> 1647
B42: Honoraires dépositaire - CACEIS
B43: Provision 3T2025 | G43: 3000
B44: Provision tenue compte espèce 3T2025 | G44: 180
B45: Provision 4T2025 | G45: 3000
B46: Provision tenue compte espèce 4T2025 | G46: 180
F48: =F28 -> Solde | G48: =SUM(G43:G47) -> 6360
B49: Rémunération de l'associé commandité
F55: Solde | G55: =SUM(G50:G54) -> 0
B56: Refacturation EMZ
F58: Solde | G58: =SUM(G57:G57) -> 0
B59: TOTAL | G59: =SUM(G18:G58)/2 -> 10248

Sheet Bilan
B1: {=Résultat!B1:D1} -> SANCY - SLP | C1: 0 | D1: 0 | G1: Bilan au | I1: =Sommaire!C1 -> 46022
G2: en euros | L2: Texte de référence :
L3: article 421-1 Bilan actif du rglt ANC 2020-07
B4: ACTIF | L4: article 421-2 Bilan passif du rglt ANC 2020-07
I5: Exercice N | J5: Exercice N-1 | L5: annexe n°9 du guide d'implantation
I6: =I1 -> 46022 | J6: 45657 | L6: article L214-20 du Comofi
L7: Pas de comparatif la première année d'application
B8: TITRES FINANCIERS | I8: =+I10+I15+I20+I30+I38+I50 -> 11366787 | J8: =+J10+J15+J20+J30+J38+J50 -> 13320538
C10: Actions et valeurs assimilées (A) | I10: =SUM(I12:I13) -> 11366787 | J10: =SUM(J12:J13) -> 13320538
D12: - négociés sur un marché réglementé ou assimilé | I12: =SUMIFS(Inventaire!N13:N48,Inventaire!$A$13:$A$48,"*I*",Inventaire!C13:C48,"*Action*") -> 0 | L12: Actions
D13: - non négociés sur un marché réglementé ou assimilé | I13: =SUMIF(Inventaire!$B$13:$B$48,"??AC*",Inventaire!$N$13:$N$48)+SUMIF(Inventaire!B13:B48," ??AD*",Inventaire!N13:N48)+SUMIF(Inventaire!B13:B48," ??SA*",Inventaire!N13:N48)+SUMIF(Inventaire!B13:B48," ??BS*",Inventaire!N13:N48) -> 11366787 | J13: 13320538 | L13: AC/AD/SA/BS
C15: Obligations convertibles en actions (B) | I15: =SUM(I17:I18) -> 0 | J15: =SUM(J17:J18) -> 0
D17: - négociés sur un marché réglementé ou assimilé
D18: - non négociés sur un marché réglementé ou assimilé | I18: =SUMIF(Inventaire!$B$13:$B$48,"??OC*",Inventaire!$N$13:$N$48) -> 0 | J18: 0 | L18: OC
C20: Obligations et valeurs assimilées (C) | I20: =SUM(I22:I23) -> 0 | J20: =SUM(J22:J23) -> 0
D22: - négociés sur un marché réglementé ou assimilé
D23: - non négociés sur un marché réglementé ou assimilé | I23: =SUMIF(Inventaire!$B$13:$B$48,"??OS*",Inventaire!$N$13:$N$48)+SUMIF(Inventaire!$B$13:$B$48,"??OR*",Inventaire!$N$13:$N$48) -> 0 | J23: 0 | L23: OS/OR
C25: Titres de créances (D) | I25: =I27+I28 -> 0
D27: - négociés sur un marché réglementé ou assimilé
D28: - non négociés sur un marché réglementé ou assimilé
C30: Parts d'OPC et de fonds d'investissements (E) | I30: =SUM(I32:I34) -> 0 | J30: =SUM(J32:J34) -> 0
D32: - OPCVM | I32: =SUMIF(Inventaire!$C$49:$C$61,"*FCP*",Inventaire!$N$49:$N$61)+SUMIF(Inventaire!$C$49:$C$61,"*SICAV*",Inventaire!$N$49:$N$61) -> 0 | J32: 0 | L32: FCP/SICAV
D33: - FIA et équivalents d'autres Etats membres de l'Union Européenne | I33: =SUMIF(Inventaire!$C$13:$C$61,"*FPCI*",Inventaire!$N$13:$N$61)+SUMIF(Inventaire!$C$13:$C$61,"*SLP*",Inventaire!$N$13:$N$61)+SUMIF(Inventaire!$C$13:$C$61,"*FCPR*",Inventaire!$N$13:$N$61)+SUMIF(Inventaire!$C$13:$C$61,"*FCPI*",Inventaire!$N$13:$N$61) -> 0 | J33: 0 | L33: FCPR/FPCI/FCPI/SLP
D34: - Autres OPC et fonds d'investissement
C36: Dépôts (F) | I36: =SUMIF(Inventaire!$B$13:$B$48,"??CT*",Inventaire!$N$13:$N$48) -> 0 | L36: CT
C38: Instruments financiers à terme (G)
C40: Parts d'OPC et de fonds d'investissements (H) | I40: =SUM(I42:I46) -> 0
D42: - Créances représentatives de titres financiers reçus en pension
D43: - Créances représentatives de titres donnés en garantie
D44: - Créances représentatives de titres financiers prêtés
D45: - titres financiers donnés en pension
D46: - Autres opérations temporaires
C48: Prêts (I) | I48: =SUMIF(Inventaire!$B$13:$B$48,"??CC*",Inventaire!$N$13:$N$48)+SUMIF(Inventaire!$B$13:$B$48,"??PR*",Inventaire!$N$13:$MU$48) -> 0 | J48: 0 | L48: CC/PR/NO
C50: Autres actifs éligibles (J) | I50: 0 | J50: 0
B52: Sous-total actifs éligibles I = (A + B + C + D + E + F + G + H + I + J) | I52: =+I10+I15+I20+I30+I38+I50+I25+I36+I40+I48 -> 11366787 | J52: =+J10+J15+J20+J30+J38+J50 -> 13320538
B54: CREANCES ET COMPTES D'AJUSTEMENT ACTIFS | I54: =Inventaire!D38 -> 0 | J54: 0
B56: COMPTES FINANCIERS | I56: =Inventaire!D36 -> 109211.49 | J56: 140575.41
B58: Sous-total actifs autres que les actifs éligibles II | I58: =+I54+I56 -> 109211.49 | J58: =+J54+J56 -> 140575.41
B60: TOTAL DE L'ACTIF I + II | I60: =+I52+I58 -> 11475998 | J60: =+J52+J58 -> 13461114
B62: PASSIF
I63: =+I6 -> 46022 | J63: =+J6 -> 45657
B64: CAPITAUX PROPRES
C66: Capital (1) | I66: =+I77-I74-I72-I70-I68 -> 13445196 | J66: =+J77-J74-J72-J70-J68 -> 10752307
C68: Report à nouveau sur revenu net
C70: Report à nouveau des plus et moins-values latentes nettes
C72: Report à nouveau des plus et moins-values réalisées nettes
C74: Résultat net de l'exercice | I74: =Résultat!H188 -> -1979445.6 | J74: 2692888.4
B76: Sous-total capitaux propres I
D77: ( = montant représentatif de l'actif net ) | I77: =Inventaire!C7 -> 11465750 | J77: 13445196
B79: PASSIFS ELIGIBLES
C81: Instruments financiers
C83: Emprunts
C85: Autres passifs éligibles
B87: Sous-total passifs éligibles II | I87: =+I81+I83+I85 -> 0 | J87: =+J81+J83+J85 -> 0
B89: AUTRES PASSIFS
C91: Dettes et comptes d'ajustement passifs | I91: =-Inventaire!D40 -> 10248 | J91: 15918
C93: Concours bancaires
B95: Sous-total autres passifs III | I95: =+I91+I93 -> 10248 | J95: =+J91+J93 -> 15918
B97: TOTAL DU PASSIF : I + II + III | I97: =+I77+I87+I95 -> 11475998 | J97: =+J77+J87+J95 -> 13461114
B98: (1) capital sous déduction du capital souscrit non appelé et des répartitions d'actifs
I99: =I60-I97 -> 0 | J99: =J60-J97 -> 0
G100: Contrôle | I100: =IF(ABS((I97-I60))<0.01,"OK","ANOMALIE") -> OK | J100: =IF(ABS((J60-J97))<0.01,"OK","ANOMALIE") -> OK

Sheet Résultat
B1: ='Créances_&_dettes'!B1 -> SANCY - SLP | E1: Compte de résultat au | G1: =Sommaire!C1 -> 46022
B3: COMPTE DE RESULTAT
K4: Pas de comparatif la première année d'application
B5: EN EUROS
B6: Zone de saisie
B7: Commentaire : | D7: faire figurer le comparatif (toujours date clôture n-1)
I8: Exercice précédent
B9: Compte de résultat en | F9: =Sommaire!B32 -> Euro | H9: =G1 -> 46022 | I9: 45657
B12: REVENUS FINANCIERS NETS
B14: PRODUITS SUR OPERATIONS FINANCIERES (1)
C16: Produits sur instruments financiers de capital investissement
C17: 7000000 | D17: sur actions | H17: =SUMIF('Balance '!A:A,"700000*",'Balance '!F:F)-SUMIF('Balance '!A:A,"700000*",'Balance '!E:E) -> 0
C18: 7011000 | D18: sur des obligations convertibles en actions | H18: =SUMIF('Balance '!A:A,"701100*",'Balance '!F:F)-SUMIF('Balance '!A:A,"701100*",'Balance '!E:E) -> 0
C19: 7012000 | D19: sur autres obligations | H19: =SUMIF('Balance '!A:A,"701200*",'Balance '!F:F)-SUMIF('Balance '!A:A,"701200*",'Balance '!E:E) -> 0
C21: Produits sur instruments du marché monétaire
C22: 70210000 | D22: Sur titres de créances négociables | H22: =SUMIF('Balance '!A:A,"702100*",'Balance '!F:F)-SUMIF('Balance '!A:A,"702100*",'Balance '!E:E) -> 0
C23: 70220000 | D23: Sur autres titres de créances négociés sur un marché réglementé | H23: =SUMIF('Balance '!A:A,"702200*",'Balance '!F:F)-SUMIF('Balance '!A:A,"702200*",'Balance '!E:E) -> 0
C24: 70230000 | D24: Sur titres de créances non négociés sur un marché réglementé | H24: =SUMIF('Balance '!A:A,"702300*",'Balance '!F:F)-SUMIF('Balance '!A:A,"702300*",'Balance '!E:E) -> 0
C26: Produit sur les parts d'OPC
C27: 70300000 | D27: Produits sur parts d'OPC | H27: =SUMIF('Balance '!A:A,"703000*",'Balance '!F:F)-SUMIF('Balance '!A:A,"703000*",'Balance '!E:E) -> 0
C29: Produits sur instruments financiers à termes
C30: 7041000 | D30: sur opérations d'échange de taux | H30: =SUMIF('Balance '!A:A,"704100*",'Balance '!F:F)-SUMIF('Balance '!A:A,"704100*",'Balance '!E:E) -> 0
C31: 7042000 | D31: sur autres contrats financiers | H31: =SUMIF('Balance '!A:A,"704200*",'Balance '!F:F)-SUMIF('Balance '!A:A,"704200*",'Balance '!E:E) -> 0
C33: Produits sur opérations temporaires de titres
C34: 70500000 | D34: Produits sur opération temporaires de titres | H34: =SUMIF('Balance '!A:A,"705000*",'Balance '!F:F)-SUMIF('Balance '!A:A,"705000*",'Balance '!E:E) -> 0
C36: Produits sur prêts et créances
C37: 7066000 | D37: sur avance en compte courant | H37: =SUMIF('Balance '!A:A,"706600*",'Balance '!F:F)-SUMIF('Balance '!A:A,"706600*",'Balance '!E:E) -> 0
C39: Produits sur autres actifs et passifs éligibles
C40: 70710000 | D40: Sur dépôts | H40: =SUMIF('Balance '!A:A,"707100*",'Balance '!F:F)-SUMIF('Balance '!A:A,"707100*",'Balance '!E:E) -> 0
C41: 70760000 | D41: Fonds de capital investissement - sur avances en compte-courant | H41: =SUMIF('Balance '!A:A,"707600*",'Balance '!F:F)-SUMIF('Balance '!A:A,"707600*",'Balance '!E:E) -> 0
C42: 70770000 | D42: Sur autres instruments financiers | H42: =SUMIF('Balance '!A:A,"707700*",'Balance '!F:F)-SUMIF('Balance '!A:A,"707700*",'Balance '!E:E) -> 0
C44: Autres produits financiers
C45: 7083000 | D45: Intérêts comptes bancaires | H45: =SUMIF('Balance '!A:A,"708300*",'Balance '!F:F)-SUMIF('Balance '!A:A,"708300*",'Balance '!E:E) -> 0 | I45: 2939.06
B49: Sous-total produits sur opérations financières | H49: =+SUM(H16:H47) -> 0 | I49: =SUM(I16:I46) -> 2939.06
B51: CHARGES SUR OPERATIONS FINANCIERES
C53: Charges sur instruments finaciers à terme
C54: 6031000 | D54: sur opérations d'échange de taux | H54: =SUMIF('Balance '!A:A,"603100*",'Balance '!E:E)-SUMIF('Balance '!A:A,"603100*",'Balance '!F:F) -> 0
C55: 6032000 | D55: sur autres contrats financiers | H55: =SUMIF('Balance '!A:A,"603200*",'Balance '!E:E)-SUMIF('Balance '!A:A,"603200*",'Balance '!F:F) -> 0
C57: Charges sur emprunts
C58: 6050000 | D58: Charges sur emprunts | H58: =SUMIF('Balance '!A:A,"605000*",'Balance '!E:E)-SUMIF('Balance '!A:A,"605000*",'Balance '!F:F) -> 0
C59: Autres charges financières
C60: 6083000 | D60: Agios | H60: =SUMIF('Balance '!A:A,"608300*",'Balance '!E:E)-SUMIF('Balance '!A:A,"608300*",'Balance '!F:F) -> 0
B62: Sous-total charges sur opérations financières | H62: =SUM(H53:H59) -> 0 | I62: =SUM(I53:I59) -> 0
B64: TOTAL REVENUS FINANCIERS NETS (A) | H64: =H49-H62 -> 0 | I64: =I49-I62 -> 2939.06
B66: AUTRES PRODUITS
H67: =+SUM(H68:H71) -> 0 | I67: =+SUM(I68:I71) -> 0
C68: 7110000 | D68: Rétrocession des frais de gestion au bénéfice de l'OPC | H68: =SUMIF('Balance '!A:A,"711000*",'Balance '!F:F)-SUMIF('Balance '!A:A,"711000*",'Balance '!E:E) -> 0
C69: 7200000 | D69: Autres Produits | H69: =SUMIF('Balance '!A:A,"720000*",'Balance '!F:F)-SUMIF('Balance '!A:A,"720000*",'Balance '!E:E) -> 0
C70: 7210000 | D70: Versements en garantie de capital ou de performance | H70: =SUMIF('Balance '!A:A,"721000*",'Balance '!F:F)-SUMIF('Balance '!A:A,"721000*",'Balance '!E:E) -> 0
C71: 7240000 | D71: Produits sur autres actifs éligibles | H71: =SUMIF('Balance '!A:A,"724000*",'Balance '!F:F)-SUMIF('Balance '!A:A,"724000*",'Balance '!E:E) -> 0
B73: AUTRES CHARGES | H73: =+SUM(H75:H90) -> 25693.92 | I73: =+SUM(I75:I90) -> 13924.51
C75: 6111000 | D75: Frais de gestion de la société de gestion | H75: =SUMIF('Balance '!A:A,"611100*",'Balance '!E:E)-SUMIF('Balance '!A:A,"611100*",'Balance '!F:F) -> 0
C76: 6112100 | D76: Frais CAC | H76: =SUMIF('Balance '!A:A,"6112100*",'Balance '!E:E)-SUMIF('Balance '!A:A,"6112100*",'Balance '!F:F) -> 4392 | I76: 2562
C77: 6112200 | D77: Frais délégation comptable | H77: =SUMIF('Balance '!A:A,"6112200*",'Balance '!E:E)-SUMIF('Balance '!A:A,"6112200*",'Balance '!F:F) -> 6567 | I77: -226
C78: 6112300 | D78: Frais dépositaire | H78: =SUMIF('Balance '!A:A,"6112300*",'Balance '!E:E)-SUMIF('Balance '!A:A,"6112300*",'Balance '!F:F) -> 13440 | I78: 10239.78
C79: 6112400 | D79: Autres assurances | H79: =SUMIF('Balance '!A:A,"6112400*",'Balance '!E:E)-SUMIF('Balance '!A:A,"6112400*",'Balance '!F:F) -> 0
C80: 6112500 | D80: Assistance juridique | H80: =SUMIF('Balance '!A:A,"6112500*",'Balance '!E:E)-SUMIF('Balance '!A:A,"6112500*",'Balance '!F:F) -> 305.58
C81: 6112600 | D81: Rémunération GP | H81: =SUMIF('Balance '!A:A,"6112600*",'Balance '!E:E)-SUMIF('Balance '!A:A,"6112500*",'Balance '!F:F) -> 170.72 | I81: 1188.73
C83: 6120000 | D83: Frais d'audit et d'étude | H83: =SUMIF('Balance '!A:A,"6120000*",'Balance '!E:E)-SUMIF('Balance '!A:A,"6120000*",'Balance '!F:F) -> 0
C84: 6130000 | D84: Impôts, taxes et versements assimilés | H84: =SUMIF('Balance '!A:A,"6130000*",'Balance '!E:E)-SUMIF('Balance '!A:A,"6130000*",'Balance '!F:F) -> 0
C85: 6130001 | D85: Droit d'enregistrement | H85: =SUMIF('Balance '!A:A,"6130001*",'Balance '!E:E)-SUMIF('Balance '!A:A,"6130001*",'Balance '!F:F) -> 0
C86: 6150000 | D86: Autres charges de gestion courante | H86: =SUMIF('Balance '!A:A,"6150000*",'Balance '!E:E)-SUMIF('Balance '!A:A,"6150000*",'Balance '!F:F) -> 818.62 | I86: 160
C87: 6151000 | D87: Frais bancaires | H87: =SUMIF('Balance '!A:A,"6151000*",'Balance '!E:E)-SUMIF('Balance '!A:A,"6151000*",'Balance '!F:F) -> 0
C88: 6156000 | D88: Primes d'assurance | H88: =SUMIF('Balance '!A:A,"6156000*",'Balance '!E:E)-SUMIF('Balance '!A:A,"6156000*",'Balance '!F:F) -> 0
C89: 6160000 | D89: Autres charges | H89: =SUMIF('Balance '!A:A,"6160000*",'Balance '!E:E)-SUMIF('Balance '!A:A,"6160000*",'Balance '!F:F) -> 0
C90: 6190000 | D90: Rétrocessions de frais de gestion | H90: =SUMIF('Balance '!A:A,"6190000*",'Balance '!E:E)-SUMIF('Balance '!A:A,"6190000*",'Balance '!F:F) -> 0
B92: Sous-total autres produits et autres charges (B) | H92: =+H67+H73 -> 25693.92 | I92: =+I67+I73 -> 13924.51
B94: REVENUS NETS AVANT COMPTE DE REGULARISATION C = A - B | H94: =+H64-H92 -> -25693.92 | I94: =+I64-I92 -> -10985.45
C96: Régularisation des revenus nets de l'exercice (D) | H96: =SUMIF('Balance '!A:A,"771000*",'Balance '!F:F)-SUMIF('Balance '!A:A,"771000*",'Balance '!E:E) -> 0
B98: REVENUS NETS I = C + D | H98: =+H94+H96 -> -25693.92 | I98: =+I94+I96 -> -10985.45
B100: PLUS OU MOINS-VALUES REALISEES NETTES AVANT COMPTE DE REGULARISATIONS
C102: Plus et moins-values réalisées | K102: #64 + #74
C103: Dont Moins-values réalisées:
C104: 6440000 | D104: sur actions | H104: =-(SUMIF('Balance '!A:A,"6440000*",'Balance '!E:E)-SUMIF('Balance '!A:A,"6440000*",'Balance '!F:F)) -> 0
C105: 6441200 | D105: sur obligations convertibles en actions | H105: =-(SUMIF('Balance '!A:A,"6441200*",'Balance '!E:E)-SUMIF('Balance '!A:A,"6441200*",'Balance '!F:F)) -> 0
C106: 6441500 | D106: sur autres obligations | H106: =-(SUMIF('Balance '!A:A,"6441500*",'Balance '!E:E)-SUMIF('Balance '!A:A,"6441500*",'Balance '!F:F)) -> 0
C107: 6442000 | D107: sur titres de créances | H107: =-(SUMIF('Balance '!A:A,"6442000*",'Balance '!E:E)-SUMIF('Balance '!A:A,"6442000*",'Balance '!F:F)) -> 0
C108: 6443000 | D108: sur parts d’OPC | H108: =-(SUMIF('Balance '!A:A,"6443000*",'Balance '!E:E)-SUMIF('Balance '!A:A,"6443000*",'Balance '!F:F)) -> 0
C109: 6444000 | D109: sur opérations temporaires de titres financiers | H109: =-(SUMIF('Balance '!A:A,"6444000*",'Balance '!E:E)-SUMIF('Balance '!A:A,"6444000*",'Balance '!F:F)) -> 0
C110: 6445000 | D110: sur instruments financiers à terme (y compris change à terme) | H110: =-(SUMIF('Balance '!A:A,"6445000*",'Balance '!E:E)-SUMIF('Balance '!A:A,"6445000*",'Balance '!F:F)) -> 0
C111: 6446100 | D111: sur dépôts et autres instruments financiers | H111: =-(SUMIF('Balance '!A:A,"6446100*",'Balance '!E:E)-SUMIF('Balance '!A:A,"6446100*",'Balance '!F:F)) -> 0
C112: 6446200 | D112: sur autres actifs éligibles | H112: =-(SUMIF('Balance '!A:A,"6446200*",'Balance '!E:E)-SUMIF('Balance '!A:A,"6446200*",'Balance '!F:F)) -> 0
C113: 6447000 | D113: sur comptes financiers | H113: =-(SUMIF('Balance '!A:A,"6447000*",'Balance '!E:E)-SUMIF('Balance '!A:A,"6447000*",'Balance '!F:F)) -> 0
C114: 6448000 | D114: sur instruments financiers vendus à découvert | H114: =-(SUMIF('Balance '!A:A,"6448000*",'Balance '!E:E)-SUMIF('Balance '!A:A,"6448000*",'Balance '!F:F)) -> 0
C115: 6449000 | D115: sur les passifs de financement émis par l’OFS | H115: =-(SUMIF('Balance '!A:A,"6449000*",'Balance '!E:E)-SUMIF('Balance '!A:A,"6449000*",'Balance '!F:F)) -> 0
C117: Dont Plus-values réalisées:
C118: 7440000 | D118: sur actions | H118: =SUMIF('Balance '!A:A,"7440000*",'Balance '!F:F)-SUMIF('Balance '!A:A,"7440000*",'Balance '!E:E) -> 0
C119: 7441200 | D119: sur obligations convertibles en actions | H119: =SUMIF('Balance '!A:A,"7441200*",'Balance '!F:F)-SUMIF('Balance '!A:A,"7441200*",'Balance '!E:E) -> 0
C120: 7441500 | D120: sur autres obligations | H120: =SUMIF('Balance '!A:A,"7441500*",'Balance '!F:F)-SUMIF('Balance '!A:A,"7441500*",'Balance '!E:E) -> 0
C121: 7442000 | D121: sur titres de créances | H121: =SUMIF('Balance '!A:A,"7442000*",'Balance '!F:F)-SUMIF('Balance '!A:A,"7442000*",'Balance '!E:E) -> 0
C122: 7443000 | D122: sur parts d’OPC | H122: =SUMIF('Balance '!A:A,"7443000*",'Balance '!F:F)-SUMIF('Balance '!A:A,"7443000*",'Balance '!E:E) -> 0
C123: 7444000 | D123: sur opérations temporaires de titres financiers | H123: =SUMIF('Balance '!A:A,"7444000*",'Balance '!F:F)-SUMIF('Balance '!A:A,"7444000*",'Balance '!E:E) -> 0
C124: 7445000 | D124: sur instruments financiers à terme (y compris change à terme) | H124: =SUMIF('Balance '!A:A,"7445000*",'Balance '!F:F)-SUMIF('Balance '!A:A,"7445000*",'Balance '!E:E) -> 0
C125: 7446100 | D125: sur dépôts et autres instruments financiers | H125: =SUMIF('Balance '!A:A,"7446100*",'Balance '!F:F)-SUMIF('Balance '!A:A,"7446100*",'Balance '!E:E) -> 0
C126: 7446200 | D126: sur autres actifs éligibles | H126: =SUMIF('Balance '!A:A,"7446200*",'Balance '!F:F)-SUMIF('Balance '!A:A,"7446200*",'Balance '!E:E) -> 0
C127: 7447000 | D127: sur comptes financiers | H127: =SUMIF('Balance '!A:A,"7447000*",'Balance '!F:F)-SUMIF('Balance '!A:A,"7447000*",'Balance '!E:E) -> 0
C128: 7448000 | D128: sur instruments financiers vendus à découvert | H128: =SUMIF('Balance '!A:A,"7448000*",'Balance '!F:F)-SUMIF('Balance '!A:A,"7448000*",'Balance '!E:E) -> 0
C129: 7460000 | D129: Différences de change réalisées sur comptes financiers | H129: =SUMIF('Balance '!A:A,"7460000*",'Balance '!F:F)-SUMIF('Balance '!A:A,"7460000*",'Balance '!E:E) -> 0
C130: 7471000 | D130: Indemnités d’assurances perçues | H130: =SUMIF('Balance '!A:A,"7471000*",'Balance '!F:F)-SUMIF('Balance '!A:A,"7471000*",'Balance '!E:E) -> 0
C131: 7479000 | D131: Versements reçus en garantie de performance | H131: =SUMIF('Balance '!A:A,"7479000*",'Balance '!F:F)-SUMIF('Balance '!A:A,"7479000*",'Balance '!E:E) -> 0
...

Sheet Capitaux propres
B1: ='Créances_&_dettes'!B1 -> SANCY - SLP | D1: Evolution des capitaux propres | F1: =Sommaire!C1 -> 46022
B4: Libellé | D4: =F1 -> 46022 | E4: 45657 | F4: Variation | H4: Texte de référence : article 433-2
B5: Apports | C5: + | D5: =+D6+D7 -> 15201269 | E5: =SUM(E6:E7) -> 15201269 | F5: =D5-E5 -> 0 | H5: Reconstitution de la ligne "capitaux propres" des fonds de capital investissement et autres véhicules
B6: Capital souscrit | C6: + | D6: =SUMIF('Balance '!A:A,"1011*",'Balance '!F:F)-SUMIF('Balance '!A:A,"1011*",'Balance '!E:E) -> 15380560 | E6: 15380560 | F6: =D6-E6 -> 0
B7: Capital non appelé | C7: - | D7: =-(SUMIF('Balance '!A:A,"1019*",'Balance '!E:E)+SUMIF('Balance '!A:A,"1021*",'Balance '!E:E)-SUMIF('Balance '!A:A,"1019*",'Balance '!F:F)-SUMIF('Balance '!A:A,"1021*",'Balance '!F:F)) -> -179291.18 | E7: -179291.18 | F7: =D7-E7 -> 0
B8: Emission de passifs de financement (ne concerne que les OFS) | C8: +
B9: Résultat de gestion | C9: +/- | D9: =SUM(D10:D11) -> -81306.29 | E9: =SUM(E10:E11) -> -55612.37 | F9: =+D9-E9 -> -25693.92 | H9: Pas de comparatif la première année d'application
B10: Revenus nets de l'exercice | C10: +/- | D10: =Résultat!H98 -> -25693.92 | E10: -10985.45 | F10: =D10-E10 -> -14708.47
B11: Cumul des revenus nets des exercices précédents | C11: +/- | D11: =+E11+E10 -> -55612.37 | E11: -44626.92 | F11: =D11-E11 -> -10985.45
B12: Plus ou moins-values réalisées nettes | D12: =SUM(D13:D14) -> 0 | E12: =SUM(E13:E14) -> 0 | F12: =D12-E12 -> 0
B13: Plus ou moins-values réalisées nettes de l'exercice | C13: +/- | D13: =Résultat!H145 -> 0 | F13: =D13-E13 -> 0
B14: Cumul plus ou moins-values réalisées nettes des exercices précédents | C14: +/- | D14: =E13+E14 -> 0 | F14: =D14-E14 -> 0
B15: Variation des plus ou moins-values latentes nettes | D15: =SUM(D16:D17) -> -3633212.3 | E15: =SUM(E16:E17) -> -1679460.6 | F15: =D15-E15 -> -1953751.7
B16: Plus ou moins-values latentes nettes de l'exercice | C16: +/- | D16: =+Résultat!H175 -> -1953751.7 | E16: 2703873.8 | F16: =D16-E16 -> -4657625.6
B17: Cumul plus ou moins-values latentes nettes des exercices précédents | C17: +/- | D17: =+E17+E16 -> -1679460.6 | E17: -4383334.4 | F17: =D17-E17 -> 2703873.8
B18: Boni de liquidation | C18: +/- | F18: =D18-E18 -> 0
B19: Rachats et répartitions d'actifs | C19: - | D19: =SUM(D20:D23) -> 0 | E19: =SUM(E20:E23) -> 0 | F19: =D19-E19 -> 0
B20: Rachats | C20: - | F20: =D20-E20 -> 0
B21: Répartition d'actifs | C21: - | F21: =D21-E21 -> 0
B22: Distribution de résultats nets | C22: - | F22: =D22-E22 -> 0
B23: Distribution de plus et moins-values réalisées nettes | C23: - | F23: =D23-E23 -> 0
B24: Remboursement de passifs de financement (ne concerne que les OFS) | C24: +/- | F24: =D24-E24 -> 0
B25: Autres éléments | C25: +/- | D25: =SUM(D30,D31) -> -21000 | E25: -21000 | F25: =D25-E25 -> 0
B26: Capitaux propres en fin d'exercice | C26: = | D26: =D25+D19+D9+D5+D12+D15+D18 -> 11465750 | E26: =E25+E9+E19+E5+E15 -> 13445196 | F26: =D26-E26 -> -1979445.7
B29: Autres éléments :
B30: Frais de constitution | D30: =SUMIF('Balance '!A:A,"13*",'Balance '!F:F)-SUMIF('Balance '!A:A,"13*",'Balance '!E:E) -> -21000
B31: Prime de souscription | D31: =SUMIF('Balance '!A:A,"1031*",'Balance '!F:F)-SUMIF('Balance '!A:A,"1031*",'Balance '!E:E) -> 0
B34: Contrôle de l'actif net selon l'inventaire : | D34: =Inventaire!C7 -> 11465750 | E34: 13445196 | F34: =+D34-E34 -> -1979445.7
B35: Ecart | D35: =D26-D34 -> 0 | E35: =E26-E34 -> 0 | F35: =ROUND(F26-F34,2) -> 0
B36: Conclusion après valorisation | D36: =+IF(ABS(D35)<0.01,"OK","ANOMALIE") -> OK | E36: =+IF(ABS(E35)<0.01,"OK","ANOMALIE") -> OK | F36: =+IF(ABS(F35)<0.01,"OK","ANOMALIE") -> OK
B38: Ecart | D38: =+D35+Inventaire!L30 -> -3633212.3
B39: Conclusion avant valorisation | D39: =IF(D36="OK","OK",+IF(D38<0.0000001,"OK","ANOMALIE")) -> OK

Sheet Rappro Banque
B1: =+Inventaire!B1 -> SANCY - SLP | D1: Rapprochement bancaire au | F1: 46022
B5: CACEIS compte 00500242947
C6: OPC | F6: DEPOSITAIRE
B7: Libellé | C7: Montant | D7: Date de régularisation | E7: Libellé | F7: Montant | G7: Date de régularisation
B9: Solde comptable | C9: =SUMIF('Balance '!A:A,"51111100*",'Balance '!E:E)-SUMIF('Balance '!A:A,"5111110*",'Balance '!F:F) -> 109211.49 | E9: Solde bancaire | F9: 109211.49
B11: TOTAL | C11: =SUM(C9) -> 109211.49 | E11: TOTAL | F11: =SUM(F9:F10) -> 109211.49
B12: Ecart pour contrôle | C12: =F11-C11 -> 0
C13: =IF(C12=0,"OK","ANOMALIE") -> OK
B17: TOTAL DISPONIBILITES | C17: =C11 -> 109211.49

Sheet Rappro Balance
B1: =+Inventaire!B1 -> SANCY - SLP | D1: Rapprochement Portefeuille/ balance : | G1: =Résultat!G1 -> 46022
B4: Classe | C4: Comptes débiteurs/créditeurs | D4: Soldes balance | E4: Solde net | F4: Calcul VL | G4: Différence | H4: Contrôle
B6: Classe 1 | C6: comptes débiteurs | D6: =SUMIF('Balance '!A:A,"1*",'Balance '!E:E) -> 1935364.2
C7: comptes créditeurs | D7: =SUMIF('Balance '!A:A,"1*",'Balance '!F:F) -> 15380560
C8: Sous total | E8: =D7-D6 -> 13445196
B9: Classe 6 | C9: comptes débiteurs | D9: =SUMIF('Balance '!A:A,"6*",'Balance '!E:E) -> 25693.92
C10: comptes créditeurs | D10: =SUMIF('Balance '!A:A,"6*",'Balance '!F:F) -> 1679460.6
C11: Sous total | E11: =D10-D9 -> 1653766.7
B12: Classe 7 | C12: comptes débiteurs | D12: =SUMIF('Balance '!A:A,"7*",'Balance '!E:E) -> 3633212.3
C13: comptes créditeurs | D13: =SUMIF('Balance '!A:A,"7*",'Balance '!F:F) -> 0
C14: Sous total | E14: =D13-D12 -> -3633212.3
C15: Résultat | D15: =E14+E11 -> -1979445.6
B16: Actif net | E16: =SUM(E8:E15) -> 11465750 | F16: =+Inventaire!D44 -> 11465750 | G16: =E16-F16 -> 0 | H16: =IF(ABS(G16)<0.01,"OK","ANOMALIE") -> OK
B18: Classe | C18: Comptes débiteurs/créditeurs | D18: Soldes balance | E18: Solde net | F18: Calcul VL | G18: Différence
B20: Classe 3 | C20: comptes débiteurs | D20: =SUMIF('Balance '!A:A,"3*",'Balance '!E:E) -> 14999999 | I20: Contrôle avant valorisation
C21: comptes créditeurs | D21: =SUMIF('Balance '!A:A,"3*",'Balance '!F:F) -> 3633212.3 | I21: valo | J21: écart
C22: Sous total | E22: =D20-D21 -> 11366787 | F22: =Inventaire!D34 -> 11366787 | G22: =E22-F22 -> 0 | I22: =+Inventaire!L27+Inventaire!M27 -> -3633212.3 | J22: =G22+I22 -> -3633212.3 | K22: =IF(ABS(J22)<>0.01,"OK","ANOMALIE") -> OK
B23: Classe 4 | C23: comptes débiteurs | D23: =SUMIF('Balance '!A:A,"4*",'Balance '!E:E) -> 0
C24: comptes créditeurs | D24: =SUMIF('Balance '!A:A,"4*",'Balance '!F:F) -> 10248
C25: Sous total | E25: =D23-D24 -> -10248 | F25: =Inventaire!D38+Inventaire!D40 -> -10248 | G25: =F25-E25 -> 0
B26: Classe 5 | C26: comptes débiteurs | D26: =SUMIF('Balance '!A:A,"5*",'Balance '!E:E) -> 109211.49
C27: comptes créditeurs | D27: =SUMIF('Balance '!A:A,"5*",'Balance '!F:F) -> 0
C28: Sous total | E28: =+D26-D27 -> 109211.49 | F28: =+Inventaire!D36 -> 109211.49 | G28: =F28-E28 -> 0
B30: Actif net | E30: =SUM(E22:E29) -> 11465750 | F30: =SUM(F20:F29) -> 11465750 | G30: =F30-E30 -> 0 | H30: =IF(ABS(G30)<0.01,"OK","ANOMALIE") -> OK
E32: =E16-E30 -> 0 | F32: CONTRÔLE | G32: =G16+G30 -> 0
E33: =IF(ABS(E32)<0.01,"OK","ANOMALIE") -> OK | F33: Conclusion | G33: =IF(ABS(G32)<0.01,"OK","ANOMALIE") -> OK

Sheet Balance 
A1: SANCY SLP
A3: BALANCE GENERALE
A4: Période du 01/01/2025 au 31/12/2025 | B4: Exporté le02/01/2026
A5: Compte | B5: Libellé | C5: Débit | D5: Crédit | E5: Solde Débit | F5: Solde Crédit
A6: 10111000 | B6: Capital souscrit parts A | C6: 0 | D6: 15379560 | E6: 0 | F6: 15379560
A7: 10111220 | B7: Capital souscrit parts commandité | C7: 0 | D7: 1000 | E7: 0 | F7: 1000
A8: 10150010 | B8: Revenu net capitalisé s/ex. préc. | C8: 55612.37 | D8: 0 | E8: 55612.37 | F8: 0
A9: 10150030 | B9: PVMV latentes nettes cap. s/ex. préc. | C9: 4383334.4 | D9: 2703873.8 | E9: 1679460.6 | F9: 0
A10: 10191100 | B10: Parts A souscrites non appelées | C10: 179279.52 | D10: 0 | E10: 179279.52 | F10: 0
A11: 10191400 | B11: Capital Souscrit Non Appele Parts Gp | C11: 11.66 | D11: 0 | E11: 11.66 | F11: 0
A12: 12000000 | B12: Résultat de l'exercice (solde créditeur) | C12: 2703873.8 | D12: 2703873.8 | E12: 0 | F12: 0
A13: 13011100 | B13: Frais De Constit. Fusion Appor | C13: 21000 | D13: 0 | E13: 21000 | F13: 0
A14: 30261100 | B14: Heka Invest - AO | C14: 14999999 | D14: 0 | E14: 14999999 | F14: 0
A15: 37000000 | B15: Différence d'estimation sur actions | C15: 2901643.4 | D15: 6534855.7 | E15: 0 | F15: 3633212.3
A16: 37021100 | B16: Var.Dif.Est Heka Invest - AO | C16: 6223005.9 | D16: 6223005.9 | E16: 0 | F16: 0
A17: 46310000 | B17: Honoraires Commissaire aux comptes | C17: 6645 | D17: 8886 | E17: 0 | F17: 2241
... A30: 75500000 | B30: PVMV latentes nettes s/actions | C30: 11078401 | D30: 7445188.7 | E30: 3633212.3 | F30: 0
