Workbook
Name _zz8: #REF!
Name _zz8: #REF!
Name _zz8: #REF!
Name ABCcostPerLine: [3]Assump!$O$77
Name ABCcostPerLine: #REF!
Name ABCcostPerLine: #REF!
Name ABCcostPerLine: #REF!
Name ABClinesMax: [3]Assump!$L$77
Name ABClinesMax: #REF!
Name ABClinesMax: #REF!
Name ABClinesMax: #REF!
Name ABClinesMin: [3]Assump!$M$77
Name ABClinesMin: #REF!
Name ABClinesMin: #REF!
Name ABClinesMin: #REF!
Name ABCterminalCost: [3]Assump!$O$79
Name ABCterminalCost: #REF!
Name ABCterminalCost: #REF!
Name ABCterminalCost: #REF!
Name ABCutil: [3]Assump!$N$77
Name ABCutil: #REF!
Name ABCutil: #REF!
Name ABCutil: #REF!
Name AccessNodeSize: [3]Assump!$L$103
Name AccessNodeSize: #REF!
Name AccessNodeSize: #REF!
Name AccessNodeSize: #REF!
Name ActCabinetTelcoCost: [3]Assump!$N$106
Name ActCabinetTelcoCost: #REF!
Name ActCabinetTelcoCost: #REF!
Name ActCabinetTelcoCost: #REF!
Name ActCabinetVideoCost: [3]Assump!$N$107
Name ActCabinetVideoCost: #REF!
Name ActCabinetVideoCost: #REF!
Name ActCabinetVideoCost: #REF!
Name ActiveLines: [3]Assump!$L$106
Name ActiveLines: #REF!
Name ActiveLines: #REF!
Name ActiveLines: #REF!
Name ActiveUtil: [3]Assump!$M$106
Name ActiveUtil: #REF!
Name ActiveUtil: #REF!
Name ActiveUtil: #REF!
Name AN0: 'Frais de gestion'!$H$144
Name AreaPerEmployee: [3]Assump!$L$69
Name AreaPerEmployee: #REF!
Name AreaPerEmployee: #REF!
Name AreaPerEmployee: #REF!
Name AreaPerHeadend: [3]Assump!$L$71
Name AreaPerHeadend: #REF!
Name AreaPerHeadend: #REF!
Name AreaPerHeadend: #REF!
Name AreaPerSwitch: [3]Assump!$L$70
Name AreaPerSwitch: #REF!
Name AreaPerSwitch: #REF!
Name AreaPerSwitch: #REF!
Name ArialCoaxLabor: [3]Assump!$M$134
Name ArialCoaxLabor: #REF!
Name ArialCoaxLabor: #REF!
Name ArialCoaxLabor: #REF!

Sheet Sommaire
A1: BOLZEN - SLP | C1: 46022
A3: Code AMF | B3: FDS104360
A5: Méthode de comptabilisation des intérêts | B5: Coupon couru
A7: Particularités de la SLP
A9: Fonds investi | B9: Le Fonds interviendra dans des opérations conformes à la politique d'investissement d'EMZ 11 et à titre principal au titre de toute opération de financement obligataire ou unitranche, pouvant prendre des formes multiples, dont notamment des obligations à bons de souscription d'actions, des obligations convertibles, des obligations remboursables en actions, des obligations simples, ou tout autre type d'obligations. | D9: Article 2.6
A11: Périodicité de la VL | B11: Trimestrielle, au 31 mars, 30 juin, 30 septembre et 31 décembre. | D11: Article 14
A13: Date de clôture du premier exercice comptable | B13: 46022 | D13: Article 21
A15: Type de parts
A16: Parts A1 | B16: Investisseurs avertis
A17: Parts A2 | B17: Investisseurs avertis
A18: Parts de Commandité | B18: Parts associés commandités
A20: Frais de gestion | B20: La société de Gestion ne recevra pas de commission de la part du Fonds | D20: Article 20.1.1
A22: Dépositaire | B22: Caceis
A24: CAC | B24: Deloitte
A28: Evaluation des OPC | B28: dernière VL connue
A30: Devise de comptabilisation | B30: Euro
A33: Zone de saisie
A38: Onglets | B38: Synthèse contrôles
A39: Inventaire | B39: =Inventaire!F12
A40: Calcul VL | B40: ='Calcul VL'!G6 -> OK
A41: OD Rééval | B41: =IF(AND('O.D Rééval'!G38="OK",'O.D Rééval'!G80="OK",'O.D Rééval'!G107="OK"),"OK","Anomalies") -> OK
A42: Rappro titres | B42: ='Rappro Titres & Parts'!C25 -> OK
B43: ='Rappro Titres & Parts'!F21 -> OK
B44: ='Rappro Titres & Parts'!I21 -> OK
A45: Intérêts OC | B45: ='Intérêts Obligations'!J105 -> OK
B46: ='Intérêts Obligations'!J106 -> OK
A47: PVMV | B47: =PVMV!M167 -> OK
A48: PV | B48: =PVMV!O165 -> OK
A49: MV | B49: =PVMV!P165 -> OK
B50: =PVMV!S163 -> OK
B51: =PVMV!O173 -> OK
A52: Liste porteurs selon versement | B52: ='Liste porteurs selon versement '!F25 -> OK
B53: ='Liste porteurs selon versement '!E18 -> OK
A54: Frais de gestion | B54: ='Frais de gestion'!J126 -> OK
A55: Résultat | B55: =Résultat!H194 -> OK
A56: N-1 | B56: =Résultat!I194 -> OK
A57: Bilan | B57: =Bilan!I101 -> OK
A58: N-1 | B58: =Bilan!J101 -> OK
A59: Variation actif net après valorisation | B59: =IF(B39="",'Capitaux propres'!D37,"") -> OK
A60: N-1 | B60: ='Capitaux propres'!E37 -> OK
A61: Variation actif net avant valorisation | B61: =IF(B39="","",'Capitaux propres'!D40)
A62: Rappro banque | B62: ='Rappro Banque'!C23 -> OK
A63: rapprobalance classe 1-6-7 | B63: =IF(B39="",'Rappro Balance'!H16,"") -> OK
A64: rapprobalance classe 3-4-5 | B64: =IF(B39="",'Rappro Balance'!H30,"") -> OK
A65: rapprobalance classe 3 avant valorisation | B65: =IF(B39="","",'Rappro Balance'!K22)
A66: Actif /passif | B66: ='Rappro Balance'!E33 -> OK
A67: Actif /passif | B67: ='Rappro Balance'!G33 -> OK
A69: Délaration BDF
A70: Inventaire: BDF : complément Composition de l'actif net | B70: =IF(Inventaire!F82="OK","VRAI","FAUX") -> VRAI

Sheet Inventaire
B1: =Sommaire!A1 -> BOLZEN - SLP | G1: Inventaire au : | H1: =Sommaire!C1 -> 46022
B2: Code ISIN parts A1 | C2: ='Calcul VL'!A8 -> FR001400XME8
B3: Code ISIN parts A2 | C3: ='Calcul VL'!A9 -> FR001400XMF5
B4: Code ISIN parts Commandité | C4: ='Calcul VL'!A10 -> FR001400XMG3
B7: Actif net : | C7: =ROUNDDOWN(D74,2) -> 90063591 | D7: Type de parts : | E7: Total | F7: A1 | G7: A2 | H7: Part de Commandité
B8: Actif net fonds général : | C8: =+D74 -> 90063591 | D8: Nbre de parts : | E8: =SUM(F8:H8) -> 943269.7 | F8: ='Calcul VL'!C8 -> 943268.7 | G8: ='Calcul VL'!C9 -> 0 | H8: ='Calcul VL'!C10 -> 1
D9: valeur liquidative : | F9: ='Calcul VL'!F8 -> 95.480211 | G9: ='Calcul VL'!F9 -> 0 | H9: ='Calcul VL'!F10 -> 95.480211
A11: G ou I | B11: Code Titre | C11: Libellé | D11: Quantité | E11: Prix de revient unitaire | F11: Cours | G11: Date de valorisation | H11: Prix de revient | I11: Intérêt ou dividendes capitalisés Prime de non conversion | J11: Prix de revient global | K11: Valeur d'estimation hors coupons | L11: +/- value potentielle | M11: Coupon couru / Dividende | N11: Valeur d'estimation coupon inclus | O11: % actif net | Q11: Valo Aplitec au 31/12/2025 | R11: Valo SG au 31/12/2025 | S11: écart | T11: Cours unitaire de valorisation
B12: FONDS GENERAL | F12: =IF('Rappro Balance'!G22=0,"","Anomalie de valorisation")
B13: Instruments financiers de capital Investissement
A15: G | B15: FROREUR02773 | C15: =PVMV!B35 -> Inflexion BIDCO - ORADP 1 | D15: =PVMV!L35 -> 10080000 | E15: =PVMV!F35 -> 1 | F15: 1 | G15: =G16 -> 46022 | H15: =PVMV!M35 -> 10080000 | J15: =H15+I15 -> 10080000 | K15: =ROUND(F15*D15,2) -> 10080000 | L15: =ROUND(+K15-J15,2) -> 0 | N15: =K15+M15 -> 10080000 | O15: =+N15/$D$74*100 -> 11.192092 | Q15: =N15 -> 10080000 | R15: 10080000 | S15: =Q15-R15 -> 0 | T15: =(R15-M15)/D15 -> 1
A16: G | B16: FROCEUR02774 | C16: =PVMV!B20 -> Inflexion BIDCO - OCADP 2 | D16: =PVMV!L20 -> 40320000 | E16: =PVMV!F20 -> 1 | F16: 1 | G16: =H1 -> 46022 | H16: =PVMV!M20 -> 40320000 | I16: ='Intérêts Obligations'!G21 -> 0 | J16: =H16+I16 -> 40320000 | K16: =ROUND(F16*D16,2) -> 40320000 | L16: =ROUND(+K16-J16,2) -> 0 | M16: ='Intérêts Obligations'!L23 -> 1712219.2 | N16: =K16+M16 -> 42032219 | O16: =+N16/$D$74*100 -> 46.669491 | Q16: =N16 -> 42032219 | R16: 42032219 | S16: =Q16-R16 -> 0 | T16: =(R16-M16)/D16 -> 1
A18: G | B18: DEADEUR03287 | C18: =PVMV!B40 -> Koenig solutions - ADP B | D18: =PVMV!L40 -> 87200 | E18: =PVMV!F40 -> 100 | F18: 100.77917 | G18: =G16 -> 46022 | H18: =PVMV!M40 -> 8720000 | I18: ='Intérêts Obligations'!G44 -> 0 | J18: =H18+I18 -> 8720000 | K18: =ROUND(F18*D18,2) -> 8787943.3 | L18: =ROUND(+K18-J18,2) -> 67943.33 | M18: ='Intérêts Obligations'!L46 -> 90591.11 | N18: =K18+M18 -> 8878534.4 | O18: =+N18/$D$74*100 -> 9.8580729 | Q18: =N18 -> 8878534.4 | R18: 8878534.4 | S18: =Q18-R18 -> 0 | T18: =(R18-M18)/D18 -> 100.77917
A19: G | B19: DEOCEUR03288 | C19: =PVMV!B45 -> Koenig solutions - OC (SHL) | D19: =PVMV!L45 -> 3200 | E19: =PVMV!F45 -> 8175 | F19: 8238.6969 | G19: =G18 -> 46022 | H19: =PVMV!M45 -> 26160000 | I19: ='Intérêts Obligations'!G60 -> 0 | J19: =H19+I19 -> 26160000 | K19: =ROUND(F19*D19,2) -> 26363830 | L19: =ROUND(+K19-J19,2) -> 203830 | M19: ='Intérêts Obligations'!L62 -> 0 | N19: =K19+M19 -> 26363830 | O19: =+N19/$D$74*100 -> 29.272462 | Q19: =N19 -> 26363830 | R19: 26363830 | S19: =Q19-R19 -> 0 | T19: =(R19-M19)/D19 -> 8238.6969
A20: G | B20: DEOCEUR03289 | C20: =PVMV!B51 -> Koenig solutions - OC (Warehouse II - ADP A) | D20: =PVMV!L51 -> 500 | E20: =PVMV!F51 -> 1000 | F20: 1046.0204 | G20: =G19 -> 46022 | H20: =PVMV!M51 -> 500000 | I20: ='Intérêts Obligations'!G75 -> 0 | J20: =H20+I20 -> 500000 | K20: =ROUND(F20*D20,2) -> 523010.18 | L20: =ROUND(+K20-J20,2) -> 23010.18 | M20: ='Intérêts Obligations'!L77 -> 0 | N20: =K20+M20 -> 523010.18 | O20: =+N20/$D$74*100 -> 0.58071211 | Q20: =N20 -> 523010.18 | R20: 523010.18 | S20: =Q20-R20 -> 0 | T20: =(R20-M20)/D20 -> 1046.0204
A22: G | B22: FROSEUR03290 | C22: =PVMV!B56 -> SNIC Technologies Group - OBSA | D22: =PVMV!L56 -> 63750000 | E22: =PVMV!F56 -> 1 | F22: 1 | G22: =G20 -> 46022 | H22: =PVMV!M56 -> 63750000 | I22: ='Intérêts Obligations'!G98 -> 0 | J22: =H22+I22 -> 63750000 | K22: =ROUND(F22*D22,2) -> 63750000 | L22: =ROUND(+K22-J22,2) -> 0 | M22: ='Intérêts Obligations'!L100 -> 247916.67 | N22: =K22+M22 -> 63997917 | O22: =+N22/$D$74*100 -> 71.058589 | Q22: =N22 -> 63997917 | R22: 63997917 | S22: =Q22-R22 -> 0 | T22: =(R22-M22)/D22 -> 1
C25: Total | H25: =SUM(H14:H24) -> 149530000 | I25: =SUM(I14:I24) -> 0 | J25: =SUM(J14:J24) -> 149530000 | K25: =SUM(K14:K24) -> 1.4982478e+08 | L25: =SUM(L14:L24) -> 294783.51 | M25: =SUM(M14:M24) -> 2050727 | N25: =SUM(N14:N24) -> 1.5187551e+08 | O25: =SUM(O15:O24) -> 168.63142 | Q25: =SUM(Q15:Q24) -> 1.5187551e+08 | R25: =SUM(R15:R24) -> 1.5187551e+08 | S25: =SUM(S15:S24) -> 0 | T25: Total
B26: Autres instruments financiers
C29: Total | I29: =SUM(I26:I28) -> 0 | K29: =SUM(K26:K28) -> 0 | L29: =SUM(L26:L28) -> 0 | M29: =SUM(M26:M28) -> 0 | N29: =SUM(N26:N28) -> 0 | O29: =SUM(O26:O28) -> 0
C31: Total fonds général | H31: =+H25+H29 -> 149530000 | I31: =+I25+I29 -> 0 | J31: =+J25+J29 -> 149530000 | K31: =+K25+K29 -> 1.4982478e+08 | L31: =+L25+L29 -> 294783.51 | M31: =+M25+M29 -> 2050727 | N31: =+N25+N29 -> 1.5187551e+08 | O31: =+O25+O29 -> 168.63142
B34: Total inventaire : | H34: =H31 -> 149530000 | I34: =I31 -> 0 | J34: =J31 -> 149530000 | K34: =K31 -> 1.4982478e+08 | L34: =L31 -> 294783.51 | M34: =M31 -> 2050727 | N34: =N31 -> 1.5187551e+08 | O34: =+O31 -> 168.63142
B39: Composition de l'actif net | D39: Fonds général | E39: %
B41: Inventaire | D41: =N34 -> 1.5187551e+08 | E41: =+D41/$D$74 -> 1.6863142
B43: Disponibilités | D43: ='Rappro Banque'!C30 -> 2114169.8 | E43: =+D43/$D$74 -> 0.023474189
B45: Créances | D45: =+'Créances_&_dettes'!G35 -> 0 | E45: =+D45/$D$74 -> 0
B47: Dettes | D47: =-'Créances_&_dettes'!G103+'Créances_&_dettes'!G105-'Créances_&_dettes'!G106 -> -63484.78 | E47: =+D47/$D$74 -> -0.0007048884
B49: Dettes financières | D49: =-(Emprunt!K186+Emprunt!K187) -> -63862605 | E49: =+D49/$D$74 -> -0.70908348
B51: Actif net | D51: =ROUND(SUM(D41:D50),2) -> 90063591 | E51: =SUM(E40:E50) -> 1
B62: Composition de l'actif net (2) | D62: Fonds général | E62: Reemploi/Compte bloqué/Clawback | F62: Reinvestissement | G62: Total | H62: %
B64: Inventaire BDF | D64: =D41 -> 1.5187551e+08 | G64: =D64+E64+F64 -> 1.5187551e+08 | H64: =+G64/$G$74 -> 1.6863142 | AH64: Nombre de ligne Portefeuille | AI64: =COUNT(N27:N28)+COUNT(N14:N15) -> 1
AH65: Nombre de rang AIFM | AI65: =COUNTA(AF14:AF32) -> 0
B66: Disponibilité BDF | D66: =D43 -> 2114169.8 | G66: =D66+E66+F66 -> 2114169.8 | H66: =+G66/$G$74 -> 0.023474189 | AH66: Contrôle | AI66: =AI65=AI64 -> FALSE
AI67: =IF(AF67="","",#REF!)
B68: Créances BDF | D68: =D45 -> 0 | G68: =D68+E68+F68 -> 0 | H68: =+G68/$G$74 -> 0 | AH68: =SUM(AL14:AL15) -> 0 | AI68: Total
AH69: =N34 -> 1.5187551e+08 | AI69: Inventaire
B70: Dettes BDF | D70: =D47 -> -63484.78 | G70: =D70+E70+F70 -> -63484.78 | H70: =+G70/$G$74 -> -0.0007048884 | AH70: =AH68-AH69 -> -1.5187551e+08
AH71: =IF(ABS(AH70)<1,"OK","Anomalie") -> Anomalie
B72: Dettes financières BDF | D72: =D49 -> -63862605 | G72: =D72+E72+F72 -> -63862605 | H72: =+G72/$G$74 -> -0.70908348
B74: Actif net BDF | D74: =ROUND(SUM(D64:D73),2) -> 90063591 | E74: =ROUNDDOWN(SUM(E63:E73),2) -> 0 | F74: =SUM(F63:F73) -> 0 | G74: =ROUND(SUM(G64:G73),2) -> 90063591 | H74: =SUM(H63:H73) -> 1
E82: Contrôle: | F82: =IF((D51-G74)=0,"OK","Anomalies") -> OK

Sheet Calcul VL
B1: =Sommaire!A1 -> BOLZEN - SLP | D1: Calcul des valeurs liquidatives : | F1: =Sommaire!C1 -> 46022
B4: Actif net | F4: =Inventaire!C7 -> 90063591
D6: Au prorata des parts pour le 30/09/25 | G6: =IF(G7=0,"OK","Anomalies") -> OK
B7: Type de parts | C7: nombre de parts | D7: Montant libéré | E7: Actif net réparti | F7: Valeur de la parts | G7: =E12-F4 -> 0 | J7: Valeur liquidative recalculée | K7: Ecart non affectable | L7: Vérification | M7: SI l'écart divisé par le nombre de parts est inférieur à 0,01= OK
A8: FR001400XME8 | B8: Parts A1 | C8: 943268.7 | D8: 88886445 | E8: =$F$4*C8/$C$12 -> 90063495 | F8: =ROUNDDOWN(E8/C8,6) -> 95.480211 | J8: =F8*C8 -> 90063495 | K8: =E8-J8 -> 0.80409248 | L8: =+K8/C8/100 -> 8.5245326e-09 | M8: =IF(L8>0.01,"'ANOMALIE","'OK") -> 'OK
A9: FR001400XMF5 | B9: Parts A2 | C9: 0 | D9: 0 | E9: =$F$4*D9/$D$12 -> 0 | F9: =IF(C9=0,0,ROUNDDOWN(E9/C9,6)) -> 0 | J9: =F9*C9 -> 0 | K9: =E9-J9 -> 0 | L9: =+K9/C9/100 -> #DIV/0! | M9: =IF(L9>0.01,"'ANOMALIE","'OK") -> #DIV/0!
A10: FR001400XMG3 | B10: Part de Commandité | C10: 1 | D10: 94.23 | E10: =$F$4*C10/$C$12 -> 95.480212 | F10: =ROUNDDOWN(E10/C10,6) -> 95.480211 | J10: =F10*C10 -> 95.480211 | K10: =E10-J10 -> 8.5245324e-07 | L10: =+K10/C10/100 -> 8.5245324e-09 | M10: =IF(L10>0.01,"'ANOMALIE","'OK") -> 'OK
B12: Total | C12: =SUM(C8:C11) -> 943269.7 | D12: =SUM(D8:D11) -> 88886539 | E12: =SUM(E8:E11) -> 90063591 | J12: =SUM(J8:J11) -> 90063590 | K12: =SUM(K8:K11) -> 0.80409333 | L12: =+K12/C12/100 -> 8.5245326e-09 | M12: =IF(L12>0.01,"'ANOMALIE","'OK") -> 'OK
B13: Article 10

Sheet O.D Rééval
A1: Date | B1: journal | C1: Compte | D1: N° Piéces | E1: Libellé | F1: Debit | G1: Credit | H1: Monnaie
A2: =Sommaire!$C$1 -> 46022 | B2: ODSITU | C2: 31800000 | E2: ="Valorisation au "&TEXT(Sommaire!$C$1,"jj/mm/aa") -> Valorisation au 31/12/25 | F2: =IF(SUMIF(Inventaire!B12:B79,"??OC*",Inventaire!M12:M79)>0,SUMIF(Inventaire!B12:B79,"??OC*",Inventaire!M12:M79),0) -> 1712219.2 | G2: =IF(SUMIF(Inventaire!B12:B79,"??OC*",Inventaire!M12:M79)<0,-SUMIF(Inventaire!B12:B79,"??OC*",Inventaire!M12:M79),0) -> 0 | H2: E | I2: Intérêts Courus sur OC
A3: =Sommaire!$C$1 -> 46022 | B3: ODSITU | C3: 70110000 | E3: ="Valorisation au "&TEXT(Sommaire!$C$1,"jj/mm/aa") -> Valorisation au 31/12/25 | G3: =IF(SUMIF(Inventaire!B12:B79,"??OC*",Inventaire!M12:M79)>0,SUMIF(Inventaire!B12:B79,"??OC*",Inventaire!M12:M79),0) -> 1712219.2 | H3: E | I3: Intérêts courus sur OC | J3: OC
A5: =Sommaire!$C$1 -> 46022 | B5: ODSITU | C5: 31800000 | E5: ="Valorisation au "&TEXT(Sommaire!$C$1,"jj/mm/aa") -> Valorisation au 31/12/25 | F5: =IF(SUMIF(Inventaire!B12:B79,"??OS*",Inventaire!M12:M79)+SUMIF(Inventaire!B12:B79,"??OR*",Inventaire!M12:M79)+SUMIF(Inventaire!B12:B79,"??CN*",Inventaire!M12:M79)>0,SUMIF(Inventaire!B12:B79,"??OS*",Inventaire!M12:M79)+SUMIF(Inventaire!B12:B79,"??OR*",Inventaire!M12:M79)+SUMIF(Inventaire!B12:B79,"??CN*",Inventaire!M12:M79),0) -> 247916.67 | G5: =IF(SUMIF(Inventaire!B12:B79,"??OS*",Inventaire!M12:M79)+SUMIF(Inventaire!B12:B79,"??OR*",Inventaire!M12:M79)+SUMIF(Inventaire!B12:B79,"??CN*",Inventaire!M12:M79)<0,-(SUMIF(Inventaire!B12:B79,"??OS*",Inventaire!M12:M79)+SUMIF(Inventaire!B12:B79,"??OR*",Inventaire!M12:M79)+SUMIF(Inventaire!B12:B79,"??CN*",Inventaire!M12:M79)),0) -> 0 | H5: E | I5: Intérêts courus sur autres obligations
A6: =Sommaire!$C$1 -> 46022 | B6: ODSITU | C6: 70120000 | E6: ="Valorisation au "&TEXT(Sommaire!$C$1,"jj/mm/aa") -> Valorisation au 31/12/25 | G6: =IF(SUMIF(Inventaire!B12:B79,"??OS*",Inventaire!M12:M79)+SUMIF(Inventaire!B12:B79,"??OR*",Inventaire!M12:M79)+SUMIF(Inventaire!B12:B79,"??CN*",Inventaire!M12:M79)>0,SUMIF(Inventaire!B12:B79,"??OS*",Inventaire!M12:M79)+SUMIF(Inventaire!B12:B79,"??OR*",Inventaire!M12:M79)+SUMIF(Inventaire!B12:B79,"??CN*",Inventaire!M12:M79),0) -> 247916.67 | H6: E | I6: Intérêts courus sur autres obligations | J6: OS/OR/CN
A8: =Sommaire!$C$1 -> 46022 | B8: ODSITU | C8: 36800000 | E8: ="Valorisation au "&TEXT(Sommaire!$C$1,"jj/mm/aa") -> Valorisation au 31/12/25 | F8: =IF(SUMIF(Inventaire!B12:B79,"??PR*",Inventaire!M12:M79)+SUMIF(Inventaire!B12:B79,"??NO*",Inventaire!M12:M79)+SUMIF(Inventaire!B12:B79,"??CC*",Inventaire!M12:M79)>0,SUMIF(Inventaire!B12:B79,"??PR*",Inventaire!M12:M79)+SUMIF(Inventaire!B12:B79,"??NO*",Inventaire!M12:M79)+SUMIF(Inventaire!B12:B79,"??CC*",Inventaire!M12:M79),0) -> 0 | G8: =IF(SUMIF(Inventaire!B12:B79,"??PR*",Inventaire!M12:M79)+SUMIF(Inventaire!B12:B79,"??NO*",Inventaire!M12:M79)+SUMIF(Inventaire!B12:B79,"??CC*",Inventaire!M12:M79)<0,-SUMIF(Inventaire!B12:B79,"??PR*",Inventaire!M12:M79)+SUMIF(Inventaire!B12:B79,"??NO*",Inventaire!M12:M79)+SUMIF(Inventaire!B12:B79,"??CC*",Inventaire!M12:M79),0) -> 0 | H8: E | I8: intérêts courus sur Prêt
A9: =Sommaire!$C$1 -> 46022 | B9: ODSITU | C9: 70760000 | E9: ="Valorisation au "&TEXT(Sommaire!$C$1,"jj/mm/aa") -> Valorisation au 31/12/25 | G9: =IF(SUMIF(Inventaire!B12:B79,"??PR*",Inventaire!M12:M79)+SUMIF(Inventaire!B12:B79,"??NO*",Inventaire!M12:M79)+SUMIF(Inventaire!B12:B79,"??CC*",Inventaire!M12:M79)>0,SUMIF(Inventaire!B12:B79,"??PR*",Inventaire!M12:M79)+SUMIF(Inventaire!B12:B79,"??NO*",Inventaire!M12:M79)+SUMIF(Inventaire!B12:B79,"??CC*",Inventaire!M12:M79),0) -> 0 | H9: E | I9: intérêts courus sur Prêt | J9: PR/CC/NO
A11: =Sommaire!$C$1 -> 46022 | B11: ODSITU | C11: 31800000 | E11: ="Valorisation au "&TEXT(Sommaire!$C$1,"jj/mm/aa") -> Valorisation au 31/12/25 | F11: =IF(SUMIF(Inventaire!B12:B79,"??AC*",Inventaire!M12:M79)+SUMIF(Inventaire!B12:B79,"??AD*",Inventaire!M12:M79)+SUMIF(Inventaire!B12:B79,"??SA*",Inventaire!M12:M79)+SUMIF(Inventaire!B12:B79,"??BS*",Inventaire!M12:M79)>0,SUMIF(Inventaire!B12:B79,"??AC*",Inventaire!M12:M79)+SUMIF(Inventaire!B12:B79,"??AD*",Inventaire!M12:M79)+SUMIF(Inventaire!B12:B79,"??SA*",Inventaire!M12:M79)+SUMIF(Inventaire!B12:B79,"??BS*",Inventaire!M12:M79),0) -> 90591.11 | G11: =IF(SUMIF(Inventaire!B12:B79,"??AC*",Inventaire!M12:M79)+SUMIF(Inventaire!B12:B79,"??AD*",Inventaire!M12:M79)+SUMIF(Inventaire!B12:B79,"??SA*",Inventaire!M12:M79)+SUMIF(Inventaire!B12:B79,"??BS*",Inventaire!M12:M79)<0,-SUMIF(Inventaire!B12:B79,"??AC*",Inventaire!M12:M79)+SUMIF(Inventaire!B12:B79,"??AD*",Inventaire!M12:M79)+SUMIF(Inventaire!B12:B79,"??SA*",Inventaire!M12:M79)+SUMIF(Inventaire!B12:B79,"??BS*",Inventaire!M12:M79),0) -> 0 | H11: E | I11: Intérêts courus sur actions
A12: =Sommaire!$C$1 -> 46022 | B12: ODSITU | C12: 70000000 | E12: ="Valorisation au "&TEXT(Sommaire!$C$1,"jj/mm/aa") -> Valorisation au 31/12/25 | F12: =IF(SUMIF(Inventaire!B12:B79,"??AC*",Inventaire!M12:M79)+SUMIF(Inventaire!B12:B79,"??AD*",Inventaire!M12:M79)+SUMIF(Inventaire!B12:B79,"??SA*",Inventaire!M12:M79)+SUMIF(Inventaire!B12:B79,"??BS*",Inventaire!M12:M79)<0,-SUMIF(Inventaire!B12:B79,"??AC*",Inventaire!M12:M79)+SUMIF(Inventaire!B12:B79,"??AD*",Inventaire!M12:M79)+SUMIF(Inventaire!B12:B79,"??SA*",Inventaire!M12:M79)+SUMIF(Inventaire!B12:B79,"??BS*",Inventaire!M12:M79),0) -> 0 | G12: =IF(SUMIF(Inventaire!B12:B79,"??AC*",Inventaire!M12:M79)+SUMIF(Inventaire!B12:B79,"??AD*",Inventaire!M12:M79)+SUMIF(Inventaire!B12:B79,"??SA*",Inventaire!M12:M79)+SUMIF(Inventaire!B12:B79,"??BS*",Inventaire!M12:M79)>0,SUMIF(Inventaire!B12:B79,"??AC*",Inventaire!M12:M79)+SUMIF(Inventaire!B12:B79,"??AD*",Inventaire!M12:M79)+SUMIF(Inventaire!B12:B79,"??SA*",Inventaire!M12:M79)+SUMIF(Inventaire!B12:B79,"??BS*",Inventaire!M12:M79),0) -> 90591.11 | H12: E | I12: Intérêts courus sur actions | J12: AC/AD/BS/SA
A14: =Sommaire!$C$1 -> 46022 | B14: ODSITU | C14: 37000000 | E14: ="Valorisation au "&TEXT(Sommaire!$C$1,"jj/mm/aa") -> Valorisation au 31/12/25 | F14: =IF(SUMIF(Inventaire!B12:B79,"??AC*",Inventaire!L12:L79)+SUMIF(Inventaire!B12:B79,"??AD*",Inventaire!L12:L79)+SUMIF(Inventaire!B12:B79,"??SA*",Inventaire!L12:L79)+SUMIF(Inventaire!B12:B79,"??BS*",Inventaire!L12:L79)>0,(SUMIF(Inventaire!B12:B79,"??AC*",Inventaire!L12:L79)+SUMIF(Inventaire!B12:B79,"??AD*",Inventaire!L12:L79)+SUMIF(Inventaire!B12:B79,"??SA*",Inventaire!L12:L79)+SUMIF(Inventaire!B12:B79,"??BS*",Inventaire!L12:L79)),0) -> 67943.33 | G14: =IF(SUMIF(Inventaire!B12:B79,"??AC*",Inventaire!L12:L79)+SUMIF(Inventaire!B12:B79,"??AD*",Inventaire!L12:L79)+SUMIF(Inventaire!B12:B79,"??SA*",Inventaire!L12:L79)+SUMIF(Inventaire!B12:B79,"??BS*",Inventaire!L12:L79)<0,-(SUMIF(Inventaire!B12:B79,"??AC*",Inventaire!L12:L79)+SUMIF(Inventaire!B12:B79,"??AD*",Inventaire!L12:L79)+SUMIF(Inventaire!B12:B79,"??SA*",Inventaire!L12:L79)+SUMIF(Inventaire!B12:B79,"??BS*",Inventaire!L12:L79)),0) -> 0 | H14: E | I14: PVMV latentes nettes s/actions
A15: =Sommaire!$C$1 -> 46022 | B15: ODSITU | C15: 75500000 | E15: ="Valorisation au "&TEXT(Sommaire!$C$1,"jj/mm/aa") -> Valorisation au 31/12/25 | F15: =IF(SUMIF(Inventaire!B12:B79,"??AC*",Inventaire!L12:L79)+SUMIF(Inventaire!B12:B79,"??AD*",Inventaire!L12:L79)+SUMIF(Inventaire!B12:B79,"??SA*",Inventaire!L12:L79)+SUMIF(Inventaire!B12:B79,"??BS*",Inventaire!L12:L79)<0,-(SUMIF(Inventaire!B12:B79,"??AC*",Inventaire!L12:L79)+SUMIF(Inventaire!B12:B79,"??AD*",Inventaire!L12:L79)+SUMIF(Inventaire!B12:B79,"??SA*",Inventaire!L12:L79)+SUMIF(Inventaire!B12:B79,"??BS*",Inventaire!L12:L79)),0) -> 0 | G15: =IF(SUMIF(Inventaire!B12:B79,"??AC*",Inventaire!L12:L79)+SUMIF(Inventaire!B12:B79,"??AD*",Inventaire!L12:L79)+SUMIF(Inventaire!B12:B79,"??SA*",Inventaire!L12:L79)+SUMIF(Inventaire!B12:B79,"??BS*",Inventaire!L12:L79)>0,(SUMIF(Inventaire!B12:B79,"??AC*",Inventaire!L12:L79)+SUMIF(Inventaire!B12:B79,"??AD*",Inventaire!L12:L79)+SUMIF(Inventaire!B12:B79,"??SA*",Inventaire!L12:L79)+SUMIF(Inventaire!B12:B79,"??BS*",Inventaire!L12:L79)),0) -> 67943.33 | H15: E | I15: PVMV latentes nettes s/actions
A17: =Sommaire!$C$1 -> 46022 | B17: ODSITU | C17: 37100000 | E17: ="Valorisation au "&TEXT(Sommaire!$C$1,"jj/mm/aa") -> Valorisation au 31/12/25 | F17: =IF(SUMIF(Inventaire!B12:B79,"??OC*",Inventaire!L12:L79)>0,(SUMIF(Inventaire!B12:B79,"??OC*",Inventaire!L12:L79)),0) -> 226840.18 | G17: =IF(SUMIF(Inventaire!B12:B79,"??OC*",Inventaire!L12:L79)<0,-(SUMIF(Inventaire!B12:B79,"??OC*",Inventaire!L12:L79)),0) -> 0 | H17: E | I17: PVMV latentes nettes s/obligations convertibles en actions
A18: =Sommaire!$C$1 -> 46022 | B18: ODSITU | C18: 75512000 | E18: ="Valorisation au "&TEXT(Sommaire!$C$1,"jj/mm/aa") -> Valorisation au 31/12/25 | F18: =IF(SUMIF(Inventaire!B12:B79,"??OC*",Inventaire!L12:L79)<0,-(SUMIF(Inventaire!B12:B79,"??OC*",Inventaire!L12:L79)),0) -> 0 | G18: =IF(SUMIF(Inventaire!B12:B79,"??OC*",Inventaire!L12:L79)>0,(SUMIF(Inventaire!B12:B79,"??OC*",Inventaire!L12:L79)),0) -> 226840.18 | H18: E | I18: PVMV latentes nettes s/obligations convertibles en actions
A20: =Sommaire!$C$1 -> 46022 | B20: ODSITU | C20: 37100000 | E20: ="Valorisation au "&TEXT(Sommaire!$C$1,"jj/mm/aa") -> Valorisation au 31/12/25 | F20: =IF(SUMIF(Inventaire!B12:B79,"??OS*",Inventaire!L12:L79)+SUMIF(Inventaire!B12:B79,"??OR*",Inventaire!L12:L79)+SUMIF(Inventaire!B12:B79,"??CN*",Inventaire!L12:L79)>0,+(SUMIF(Inventaire!B12:B79,"??OS*",Inventaire!L12:L79)+SUMIF(Inventaire!B12:B79,"??OR*",Inventaire!L12:L79)+SUMIF(Inventaire!B12:B79,"??CN*",Inventaire!L12:L79)),0) -> 0 | G20: =IF(SUMIF(Inventaire!B12:B79,"??OS*",Inventaire!L12:L79)+SUMIF(Inventaire!B12:B79,"??OR*",Inventaire!L12:L79)+SUMIF(Inventaire!B12:B79,"??CN*",Inventaire!L12:L79)<0,-(SUMIF(Inventaire!B12:B79,"??OS*",Inventaire!L12:L79)+SUMIF(Inventaire!B12:B79,"??OR*",Inventaire!L12:L79)+SUMIF(Inventaire!B12:B79,"??CN*",Inventaire!L12:L79)),0) -> 0 | H20: E | I20: PVMV latentes nettes s/autres obligations
A21: =Sommaire!$C$1 -> 46022 | B21: ODSITU | C21: 75515000 | E21: ="Valorisation au "&TEXT(Sommaire!$C$1,"jj/mm/aa") -> Valorisation au 31/12/25 | F21: =IF(SUMIF(Inventaire!B12:B79,"??OS*",Inventaire!L12:L79)+SUMIF(Inventaire!B12:B79,"??OR*",Inventaire!L12:L79)+SUMIF(Inventaire!B12:B79,"??CN*",Inventaire!L12:L79)<0,-(SUMIF(Inventaire!B12:B79,"??OS*",Inventaire!L12:L79)+SUMIF(Inventaire!B12:B79,"??OR*",Inventaire!L12:L79)+SUMIF(Inventaire!B12:B79,"??CN*",Inventaire!L12:L79)),0) -> 0 | G21: =IF(SUMIF(Inventaire!B12:B79,"??OS*",Inventaire!L12:L79)+SUMIF(Inventaire!B12:B79,"??OR*",Inventaire!L12:L79)+SUMIF(Inventaire!B12:B79,"??CN*",Inventaire!L12:L79)>0,+(SUMIF(Inventaire!B12:B79,"??OS*",Inventaire!L12:L79)+SUMIF(Inventaire!B12:B79,"??OR*",Inventaire!L12:L79)+SUMIF(Inventaire!B12:B79,"??CN*",Inventaire!L12:L79)),0) -> 0 | H21: E | I21: PVMV latentes nettes s/autres obligations
A23: =Sommaire!$C$1 -> 46022 | B23: ODSITU | C23: 37600000 | E23: ="Valorisation au "&TEXT(Sommaire!$C$1,"jj/mm/aa") -> Valorisation au 31/12/25 | F23: =IF(SUMIF(Inventaire!B12:B79,"??PR*",Inventaire!L12:L79)+SUMIF(Inventaire!B12:B79,"??NO*",Inventaire!L12:L79)+SUMIF(Inventaire!B12:B79,"??CC*",Inventaire!L12:L79)+SUMIF(Inventaire!B12:B79,"??CT*",Inventaire!L12:L79)>0,+(SUMIF(Inventaire!B12:B79,"??PR*",Inventaire!L12:L79)+SUMIF(Inventaire!B12:B79,"??NO*",Inventaire!L12:L79)+SUMIF(Inventaire!B12:B79,"??CT*",Inventaire!L12:L79)+SUMIF(Inventaire!B12:B79,"??CC*",Inventaire!L12:L79)),0) -> 0 | G23: =IF(SUMIF(Inventaire!B12:B79,"??PR*",Inventaire!L12:L79)+SUMIF(Inventaire!B12:B79,"??NO*",Inventaire!L12:L79)+SUMIF(Inventaire!B12:B79,"??CC*",Inventaire!L12:L79)+SUMIF(Inventaire!B12:B79,"??CT*",Inventaire!L12:L79)<0,-(SUMIF(Inventaire!B12:B79,"??PR*",Inventaire!L12:L79)+SUMIF(Inventaire!B12:B79,"??NO*",Inventaire!L12:L79)+SUMIF(Inventaire!B12:B79,"??CT*",Inventaire!L12:L79)+SUMIF(Inventaire!B12:B79,"??CC*",Inventaire!L12:L79)),0) -> 0 | H23: E | I23: PVMV latentes nettes s/dépôt et autres investissements financiers
A24: =Sommaire!$C$1 -> 46022 | B24: ODSITU | C24: 75560000 | E24: ="Valorisation au "&TEXT(Sommaire!$C$1,"jj/mm/aa") -> Valorisation au 31/12/25 | F24: =IF(SUMIF(Inventaire!B12:B79,"??PR*",Inventaire!L12:L79)+SUMIF(Inventaire!B12:B79,"??NO*",Inventaire!L12:L79)+SUMIF(Inventaire!B12:B79,"??CC*",Inventaire!L12:L79)+SUMIF(Inventaire!B12:B79,"??CT*",Inventaire!L12:L79)<0,-(SUMIF(Inventaire!B12:B79,"??PR*",Inventaire!L12:L79)+SUMIF(Inventaire!B12:B79,"??NO*",Inventaire!L12:L79)+SUMIF(Inventaire!B12:B79,"??CT*",Inventaire!L12:L79)+SUMIF(Inventaire!B12:B79,"??CC*",Inventaire!L12:L79)),0) -> 0 | G24: =IF(SUMIF(Inventaire!B12:B79,"??PR*",Inventaire!L12:L79)+SUMIF(Inventaire!B12:B79,"??NO*",Inventaire!L12:L79)+SUMIF(Inventaire!B12:B79,"??CC*",Inventaire!L12:L79)+SUMIF(Inventaire!B12:B79,"??CT*",Inventaire!L12:L79)>0,+(SUMIF(Inventaire!B12:B79,"??PR*",Inventaire!L12:L79)+SUMIF(Inventaire!B12:B79,"??NO*",Inventaire!L12:L79)+SUMIF(Inventaire!B12:B79,"??CT*",Inventaire!L12:L79)+SUMIF(Inventaire!B12:B79,"??CC*",Inventaire!L12:L79)),0) -> 0 | H24: E | I24: PVMV latentes nettes s/dépôt et autres investissements financiers | J24: PR
A26: =Sommaire!$C$1 -> 46022 | B26: ODSITU | C26: 37300000 | E26: ="Valorisation au "&TEXT(Sommaire!$C$1,"jj/mm/aa") -> Valorisation au 31/12/25 | F26: =IF(SUMIF(Inventaire!C12:C79,"*sicav*",Inventaire!L12:L79)+SUMIF(Inventaire!C12:C79,"*FCP*",Inventaire!L12:L79)+SUMIF(Inventaire!C12:C79,"*FPCI*",Inventaire!L12:L79)+SUMIF(Inventaire!C12:C79,"*SLP*",Inventaire!L12:L79)+SUMIF(Inventaire!C12:C79,"*FIPS*",Inventaire!L12:L79)>0,(SUMIF(Inventaire!C12:C79,"*sicav*",Inventaire!L12:L79)+SUMIF(Inventaire!C12:C79,"*FCP*",Inventaire!L12:L79)+SUMIF(Inventaire!C12:C79,"*FPCI*",Inventaire!L12:L79)+SUMIF(Inventaire!C12:C79,"*SLP*",Inventaire!L12:L79)+SUMIF(Inventaire!C12:C79,"*FIPS*",Inventaire!L12:L79)),0) -> 0 | G26: =IF(SUMIF(Inventaire!C12:C79,"*sicav*",Inventaire!L12:L79)+SUMIF(Inventaire!C12:C79,"*FCP*",Inventaire!L12:L79)+SUMIF(Inventaire!C12:C79,"*FPCI*",Inventaire!L12:L79)+SUMIF(Inventaire!C12:C79,"*SLP*",Inventaire!L12:L79)+SUMIF(Inventaire!C12:C79,"*FIPS*",Inventaire!L12:L79)<0,-(SUMIF(Inventaire!C12:C79,"*sicav*",Inventaire!L12:L79)+SUMIF(Inventaire!C12:C79,"*FCP*",Inventaire!L12:L79)+SUMIF(Inventaire!C12:C79,"*FPCI*",Inventaire!L12:L79)+SUMIF(Inventaire!C12:C79,"*SLP*",Inventaire!L12:L79)+SUMIF(Inventaire!C12:C79,"*FIPS*",Inventaire!L12:L79)),0) -> 0 | H26: E | I26: PVMV latentes nettes s/OPC
A27: =Sommaire!$C$1 -> 46022 | B27: ODSITU | C27: 75530000 | E27: ="Valorisation au "&TEXT(Sommaire!$C$1,"jj/mm/aa") -> Valorisation au 31/12/25 | F27: =IF(SUMIF(Inventaire!C12:C79,"*sicav*",Inventaire!L12:L79)+SUMIF(Inventaire!C12:C79,"*FCP*",Inventaire!L12:L79)+SUMIF(Inventaire!C12:C79,"*FPCI*",Inventaire!L12:L79)+SUMIF(Inventaire!C12:C79,"*SLP*",Inventaire!L12:L79)+SUMIF(Inventaire!C12:C79,"*FIPS*",Inventaire!L12:L79)<0,-(SUMIF(Inventaire!C12:C79,"*sicav*",Inventaire!L12:L79)+SUMIF(Inventaire!C12:C79,"*FCP*",Inventaire!L12:L79)+SUMIF(Inventaire!C12:C79,"*FPCI*",Inventaire!L12:L79)+SUMIF(Inventaire!C12:C79,"*SLP*",Inventaire!L12:L79)+SUMIF(Inventaire!C12:C79,"*FIPS*",Inventaire!L12:L79)),0) -> 0 | G27: =IF(SUMIF(Inventaire!C12:C79,"*sicav*",Inventaire!L12:L79)+SUMIF(Inventaire!C12:C79,"*FCP*",Inventaire!L12:L79)+SUMIF(Inventaire!C12:C79,"*FPCI*",Inventaire!L12:L79)+SUMIF(Inventaire!C12:C79,"*SLP*",Inventaire!L12:L79)+SUMIF(Inventaire!C12:C79,"*FIPS*",Inventaire!L12:L79)>0,(SUMIF(Inventaire!C12:C79,"*sicav*",Inventaire!L12:L79)+SUMIF(Inventaire!C12:C79,"*FCP*",Inventaire!L12:L79)+SUMIF(Inventaire!C12:C79,"*FPCI*",Inventaire!L12:L79)+SUMIF(Inventaire!C12:C79,"*SLP*",Inventaire!L12:L79)+SUMIF(Inventaire!C12:C79,"*FIPS*",Inventaire!L12:L79)),0) -> 0 | H27: E | I27: PVMV latentes nettes s/OPC | J27: Sicav/FCP/FPCI/SLP/FIPS
A30: =Sommaire!$C$1 -> 46022 | B30: ODSITU | C30: 10410000 | E30: ="Valorisation au "&TEXT(Sommaire!$C$1,"jj/mm/aa") -> Valorisation au 31/12/25 | F30: =+'Créances_&_dettes'!G105 -> 0 | G30: 0 | H30: E | I30: Fund reserve
A31: =Sommaire!$C$1 -> 46022 | B31: ODSITU | C31: 48700000 | E31: ="Valorisation au "&TEXT(Sommaire!$C$1,"jj/mm/aa") -> Valorisation au 31/12/25 | F31: 0 | G31: =F30 -> 0 | H31: E | I31: =+I30 -> Fund reserve
A33: =Sommaire!$C$1 -> 46022 | B33: ODSITU | C33: 39800000 | E33: ="Valorisation au "&TEXT(Sommaire!$C$1,"jj/mm/aa") -> Valorisation au 31/12/25 | G33: =Emprunt!K186 -> 112604.67 | H33: E | I33: Intérêts sur emprunts
A34: =Sommaire!$C$1 -> 46022 | B34: ODSITU | C34: 60500000 | E34: ="Valorisation au "&TEXT(Sommaire!$C$1,"jj/mm/aa") -> Valorisation au 31/12/25 | F34: =G33 -> 112604.67 | H34: E | I34: Intérêts sur emprunts
E36: Contrôle | F36: =SUM(F2:F35) -> 2458115.1 | G36: =SUM(G3:G35) -> 2458115.1
E37: écart | G37: =F36-G36 -> 0 | H37: ce contrôle toujours à zéro
G38: =IF(G37=0,"OK","ANOMALIE") -> OK
B41: Ne pas modifier la présentation de cette OD
A42: à la clôture
A43: =A2 -> 46022 | B43: OD | C43: =C2 -> 31800000 | E43: =E2 -> Valorisation au 31/12/25 | F43: =F2 -> 1712219.2 | G43: =G2 -> 0 | H43: =H2 -> E | I43: =I2 -> Intérêts Courus sur OC
A44: =A3 -> 46022 | B44: OD | C44: =C3 -> 70110000 | E44: =E3 -> Valorisation au 31/12/25 | F44: =F3 -> 0 | G44: =G3 -> 1712219.2 | H44: =H3 -> E | I44: =I3 -> Intérêts courus sur OC
A46: =A5 -> 46022 | B46: OD | C46: =C5 -> 31800000 | E46: =E5 -> Valorisation au 31/12/25 | F46: =F5 -> 247916.67 | G46: =G5 -> 0 | H46: =H5 -> E | I46: =I5 -> Intérêts courus sur autres obligations
A47: =A6 -> 46022 | B47: OD | C47: =C6 -> 70120000 | E47: =E6 -> Valorisation au 31/12/25 | F47: =F6 -> 0 | G47: =G6 -> 247916.67 | H47: =H6 -> E | I47: =I6 -> Intérêts courus sur autres obligations
A49: =A8 -> 46022 | B49: OD | C49: =C8 -> 36800000 | E49: =E8 -> Valorisation au 31/12/25 | F49: =F8 -> 0 | G49: =G8 -> 0 | H49: =H8 -> E | I49: =I8 -> intérêts courus sur Prêt
A50: =A9 -> 46022 | B50: OD | C50: =C9 -> 70760000 | E50: =E9 -> Valorisation au 31/12/25 | F50: =F9 -> 0 | G50: =G9 -> 0 | H50: =H9 -> E | I50: =I9 -> intérêts courus sur Prêt
A52: =A11 -> 46022 | B52: OD | C52: =C11 -> 31800000 | E52: =E11 -> Valorisation au 31/12/25 | F52: =F11 -> 90591.11 | G52: =G11 -> 0 | H52: =H11 -> E | I52: =I11 -> Intérêts courus sur actions
A53: =A12 -> 46022 | B53: OD | C53: =C12 -> 70000000 | E53: =E12 -> Valorisation au 31/12/25 | F53: =F12 -> 0 | G53: =G12 -> 90591.11 | H53: =H12 -> E | I53: =I12 -> Intérêts courus sur actions
A55: =A14 -> 46022 | B55: OD | C55: =C14 -> 37000000 | E55: =E14 -> Valorisation au 31/12/25 | F55: =F14 -> 67943.33 | G55: =G14 -> 0 | H55: =H14 -> E | I55: =I14 -> PVMV latentes nettes s/actions
A56: =A15 -> 46022 | B56: OD | C56: =C15 -> 75500000 | E56: =E15 -> Valorisation au 31/12/25 | F56: =F15 -> 0 | G56: =G15 -> 67943.33 | H56: =H15 -> E | I56: =I15 -> PVMV latentes nettes s/actions
A58: =A17 -> 46022 | B58: OD | C58: =C17 -> 37100000 | E58: =E17 -> Valorisation au 31/12/25 | F58: =F17 -> 226840.18 | G58: =G17 -> 0 | H58: =H17 -> E | I58: =I17 -> PVMV latentes nettes s/obligations convertibles en actions
A59: =A18 -> 46022 | B59: OD | C59: =C18 -> 75512000 | E59: =E18 -> Valorisation au 31/12/25 | F59: =F18 -> 0 | G59: =G18 -> 226840.18 | H59: =H18 -> E | I59: =I18 -> PVMV latentes nettes s/obligations convertibles en actions
... A75: =A34 -> 46022 | B75: OD | C75: =C34 -> 60500000 | E75: =E34 -> Valorisation au 31/12/25 | F75: =F34 -> 112604.67 | G75: =G34 -> 0 | H75: =H34 -> E | I75: =I34 -> Intérêts sur emprunts
F77: =F35 -> 0 | G77: =G35 -> 0
E78: =E36 -> Contrôle | F78: =SUM(F43:F77) -> 2458115.1 | G78: =SUM(G43:G77) -> 2458115.1
E79: =E37 -> écart | G79: =F78-G78 -> 0 | H79: =H37 -> ce contrôle toujours à zéro
G80: =IF(G79=0,"OK","ANOMALIE") -> OK
B81: Ne pas modifier la présentation de cette OD
A82: Extourne de la clôture
A83: =A55+1 -> 46023 | B83: =B55 -> OD | C83: =C55 -> 37000000 | E83: =+"Extourne valorisation au "&TEXT(Sommaire!$C$1,"jj/mm/aaaa") -> Extourne valorisation au 31/12/2025 | F83: =G55 -> 0 | G83: =F55 -> 67943.33 | H83: =H55 -> E | I83: =I55 -> PVMV latentes nettes s/actions
A84: =A56+1 -> 46023 | B84: =B56 -> OD | C84: 65100000 | E84: =+"Extourne valorisation au "&TEXT(Sommaire!$C$1,"jj/mm/aaaa") -> Extourne valorisation au 31/12/2025 | F84: =G56 -> 67943.33 | G84: =F56 -> 0 | H84: =H56 -> E | I84: =I56 -> PVMV latentes nettes s/actions
A86: =A58+1 -> 46023 | B86: =B58 -> OD | C86: =C58 -> 37100000 | E86: =+"Extourne valorisation au "&TEXT(Sommaire!$C$1,"jj/mm/aaaa") -> Extourne valorisation au 31/12/2025 | F86: =G58 -> 0 | G86: =F58 -> 226840.18 | H86: =H58 -> E | I86: =I58 -> PVMV latentes nettes s/obligations convertibles en actions
A87: =A59+1 -> 46023 | B87: =B59 -> OD | C87: 65100000 | E87: =+"Extourne valorisation au "&TEXT(Sommaire!$C$1,"jj/mm/aaaa") -> Extourne valorisation au 31/12/2025 | F87: =G59 -> 226840.18 | G87: =F59 -> 0 | H87: =H59 -> E | I87: =I59 -> PVMV latentes nettes s/obligations convertibles en actions
A89: =A61+1 -> 46023 | B89: =B61 -> OD | C89: =C61 -> 37100000 | E89: =+"Extourne valorisation au "&TEXT(Sommaire!$C$1,"jj/mm/aaaa") -> Extourne valorisation au 31/12/2025 | F89: =G61 -> 0 | G89: =F61 -> 0 | H89: =H61 -> E | I89: =I61 -> PVMV latentes nettes s/autres obligations
A90: =A62+1 -> 46023 | B90: =B62 -> OD | C90: 65100000 | E90: =+"Extourne valorisation au "&TEXT(Sommaire!$C$1,"jj/mm/aaaa") -> Extourne valorisation au 31/12/2025 | F90: =G62 -> 0 | G90: =F62 -> 0 | H90: =H62 -> E | I90: =I62 -> PVMV latentes nettes s/autres obligations
A92: =A64+1 -> 46023 | B92: =B64 -> OD | C92: =C64 -> 37600000 | E92: =+"Extourne valorisation au "&TEXT(Sommaire!$C$1,"jj/mm/aaaa") -> Extourne valorisation au 31/12/2025 | F92: =G64 -> 0 | G92: =F64 -> 0 | H92: =H64 -> E | I92: =I64 -> PVMV latentes nettes s/dépôt et autres investissements financiers
A93: =A65+1 -> 46023 | B93: =B65 -> OD | C93: 65100000 | E93: =+"Extourne valorisation au "&TEXT(Sommaire!$C$1,"jj/mm/aaaa") -> Extourne valorisation au 31/12/2025 | F93: =G65 -> 0 | G93: =F65 -> 0 | H93: =H65 -> E | I93: =I65 -> PVMV latentes nettes s/dépôt et autres investissements financiers
A95: =A67+1 -> 46023 | B95: =B67 -> OD | C95: =C67 -> 37300000 | E95: =+"Extourne valorisation au "&TEXT(Sommaire!$C$1,"jj/mm/aaaa") -> Extourne valorisation au 31/12/2025 | F95: =G67 -> 0 | G95: =F67 -> 0 | H95: =H67 -> E | I95: =I67 -> PVMV latentes nettes s/OPC
A96: =A68+1 -> 46023 | B96: =B68 -> OD | C96: 65100000 | E96: =+"Extourne valorisation au "&TEXT(Sommaire!$C$1,"jj/mm/aaaa") -> Extourne valorisation au 31/12/2025 | F96: =G68 -> 0 | G96: =F68 -> 0 | H96: =H68 -> E | I96: =I68 -> PVMV latentes nettes s/OPC
A99: =A71+1 -> 46023 | B99: =B71 -> OD | C99: =C71 -> 10410000 | E99: =+"Extourne valorisation au "&TEXT(Sommaire!$C$1,"jj/mm/aaaa") -> Extourne valorisation au 31/12/2025 | F99: =G71 -> 0 | G99: =F71 -> 0 | H99: =H71 -> E | I99: =I71 -> Fund reserve
A100: =A72+1 -> 46023 | B100: =B72 -> OD | C100: =C72 -> 48700000 | E100: =+"Extourne valorisation au "&TEXT(Sommaire!$C$1,"jj/mm/aaaa") -> Extourne valorisation au 31/12/2025 | F100: =G72 -> 0 | G100: =F72 -> 0 | H100: =H72 -> E | I100: =I72 -> Fund reserve
A102: =A74+1 -> 46023 | B102: =B74 -> OD | C102: =C74 -> 39800000 | E102: =+"Extourne valorisation au "&TEXT(Sommaire!$C$1,"jj/mm/aaaa") -> Extourne valorisation au 31/12/2025 | F102: =G74 -> 112604.67 | G102: =F74 -> 0 | H102: =H74 -> E | I102: =I74 -> Intérêts sur emprunts
A103: =A75+1 -> 46023 | B103: =B75 -> OD | C103: =C75 -> 60500000 | E103: =+"Extourne valorisation au "&TEXT(Sommaire!$C$1,"jj/mm/aaaa") -> Extourne valorisation au 31/12/2025 | F103: =G75 -> 0 | G103: =F75 -> 112604.67 | H103: =H75 -> E | I103: =I75 -> Intérêts sur emprunts
E105: =E78 -> Contrôle | F105: =SUM(F83:F104) -> 407388.18 | G105: =SUM(G83:G104) -> 407388.18
E106: =E79 -> écart | F106: =F105-G105 -> 0 | H106: =H79 -> ce contrôle toujours à zéro
G107: =IF(F106=0,"OK","ANOMALIE") -> OK

Sheet Rappro Titres & Parts
B1: =Inventaire!B1 -> BOLZEN - SLP | F1: Rapprochement Titres | J1: =Inventaire!H1 -> 46022
B4: Société et nature juridique | C4: Quantité | D4: Quantité | E4: Date | F4: ECART | G4: Quantité | H4: Date | I4: ECART | J4: Commentaires
B5: de l'instrument financier | C5: inventaire | D5: société | E5: attestation | G5: dépositaire | H5: relevé
B7: =Inventaire!C15 -> Inflexion BIDCO - ORADP 1 | C7: =Inventaire!D15 -> 10080000 | F7: =C7-D7 -> 10080000 | I7: =C7-G7 -> 10080000 | J7: Souscription 25/07/2025
B8: =Inventaire!C16 -> Inflexion BIDCO - OCADP 2 | C8: =Inventaire!D16 -> 40320000 | F8: =C8-D8 -> 40320000 | I8: =C8-G8 -> 40320000 | J8: Souscription 25/07/2025
B10: =Inventaire!C18 -> Koenig solutions - ADP B | C10: =Inventaire!D18 -> 87200 | F10: =C10-D10 -> 87200 | G10: 87200 | H10: 46022 | I10: =C10-G10 -> 0
B11: =Inventaire!C19 -> Koenig solutions - OC (SHL) | C11: =Inventaire!D19 -> 3200 | F11: =C11-D11 -> 3200 | I11: =C11-G11 -> 3200 | J11: Souscription 25/11/2025
B12: =Inventaire!C20 -> Koenig solutions - OC (Warehouse II - ADP A) | C12: =Inventaire!D20 -> 500 | F12: =C12-D12 -> 500 | I12: =C12-G12 -> 500 | J12: Souscription 25/11/2025
B14: =Inventaire!C22 -> SNIC Technologies Group - OBSA | C14: =Inventaire!D22 -> 63750000 | F14: =C14-D14 -> 63750000 | I14: =C14-G14 -> 63750000 | J14: Souscription 16/12/2025
F16: =C16-D16 -> 0 | I16: =C16-G16 -> 0
C17: =ROUND(SUM(C6:C16),2) -> 114240900 | D17: =SUM(D6:D7) -> 0 | F17: =SUM(F6:F16) -> 114240900 | G17: =SUM(G6:G16) -> 87200 | I17: =ROUND(SUM(I6:I16),2) -> 114153700
E19: Contrôle | F19: =C17-D17 -> 114240900 | I19: =C17-G17 -> 114153700
F20: =F17-F19 -> 0 | I20: =ROUND(I17-I19,2) -> 0
F21: =IF(F20=0,"OK","ANOMALIE") -> OK | I21: =IF(I20=0,"OK","ANOMALIE") -> OK
B22: Contrôle avec l'inventaire | C22: Nombre de ligne
B23: Rapprochement titres | C23: =COUNT(C7:C16) -> 6
B24: inventaire | C24: =COUNT(Inventaire!G12:G30) -> 6
C25: =IF(C23-C24<>0,"Rapprochement titres incomplet","OK") -> OK
F27: Rapprochement Parts
B29: Type de parts | C29: Quantité souscription / rachat | D29: Quantité dépositaire | E29: Date relevé | F29: ECART | G29: Commentaires
B31: Parts A1 | C31: =Inventaire!F8 -> 943268.7 | D31: 943268.7 | E31: 46022 | F31: =C31-D31 -> 0
B32: Parts A2 | C32: =Inventaire!G8 -> 0 | D32: 0 | E32: 46022 | F32: =C32-D32 -> 0
B33: Part commandité | C33: =Inventaire!H8 -> 1 | D33: 1 | E33: 46022 | F33: =C33-D33 -> 0
F34: =C34-D34 -> 0
C36: =SUM(C26:C35) -> 943269.7 | D36: =SUM(D26:D35) -> 943269.7 | F36: =SUM(F26:F35) -> 0

Sheet Hors bilan
B1: =Sommaire!A1 -> BOLZEN - SLP | C1: HORS BILAN au | E1: =Sommaire!C1 -> 46022
D5: Exercice | E5: Exercice
B6: Autres engagements (par nature de produit) | D6: =+E1 -> 46022
B8: Garanties reçues | D8: =E34 -> 0
B9: dont instruments financiers reçus en garantie et non inscrits au bilan
B11: Garanties données | D11: =D34 -> 0
B12: dont instruments financiers donnés en garantie et maintenus dans leur poste d'origine
B14: Engagements de financement reçu mais non encore tirés | D14: =E38 -> 0
B16: Engagements de financement donnés mais non encore tirés | D16: =D38 -> 0
B18: Autres engagements hors bilan
C19: Donnés | D19: =D43 -> 0 | E19: 0
C20: reçus | D20: =E43 -> 8.5438316e+08
B25: =+B1 -> BOLZEN - SLP | C25: DETAIL DES ENGAGEMENTS HORS-BILAN au | E25: =+E1 -> 46022
D28: Engagements hors bilan
D29: Engagements donnés | E29: Engagements reçus
B30: Garanties
B34: Sous-total | D34: =SUM(D30:D33) -> 0 | E34: =SUM(E30:E33) -> 0
B35: Engagements de financement mais non encore tirés
B38: Sous-total | D38: =SUM(D35:D37) -> 0 | E38: =SUM(E35:E37) -> 0
B39: Autres engagements hors bilan
B40: Engagement reçus non libérés | C40: Parts A1 | E40: 8.5438225e+08
B41: Engagement reçus non libérés | C41: Parts A2 | E41: 0 | H41: Ne jamais renseigner le non libéré des parts
B42: Engagement reçus non libérés | C42: Parts de Commandité | E42: 905.77
B43: Sous-total | D43: =SUM(D39:D42) -> 0 | E43: =SUM(E39:E42) -> 8.5438316e+08 | G43: =+IF(E43+'Capitaux propres'!D7=0,"OK","Anomalie") -> OK

Sheet PVMV
B1: =Sommaire!A1 -> BOLZEN - SLP | F1: SUIVI DES ACHATS VENTES SUR TITRES : | K1: =Sommaire!C1 -> 46022 | Q1: AIFM Turnover (T3B1) | S1: =DATE(YEAR($K$1),MONTH($K$1)-3,DAY($K$1)+1) -> 45932
Q2: Unlisted equities | R2: =+ABS(SUMIFS($J$14:$J$1057,$A$14:$A$1057,"UE",$D$14:$D$1057,">="&$S$1,$D$14:$D$1057,"<="&$K$1,$C$14:$C$1057,"<>Récap"))+ABS(SUMIFS($G$14:$G$1057,$A$14:$A$1057,"UE",$D$14:$D$1057,">="&$S$1,$D$14:$D$1057,"<="&$K$1,$C$14:$C$1057,"<>Récap")) -> 99130000
Q3: Corporate bonds not issued by financial institutions | R3: =+ABS(SUMIFS($J$14:$J$1057,$A$14:$A$1057,"OS",$D$14:$D$1057,">="&$S$1,$D$14:$D$1057,"<="&$K$1,$C$14:$C$1057,"<>Récap"))+ABS(SUMIFS($G$14:$G$1057,$A$14:$A$1057,"OS",$D$14:$D$1057,">="&$S$1,$D$14:$D$1057,"<="&$K$1,$C$14:$C$1057,"<>Récap")) -> 0
Q4: Loans | R4: =+ABS(SUMIFS($J$14:$J$1057,$A$14:$A$1057,"L",$D$14:$D$1057,">="&$S$1,$D$14:$D$1057,"<="&$K$1,$C$14:$C$1057,"<>Récap"))+ABS(SUMIFS($G$14:$G$1057,$A$14:$A$1057,"L",$D$14:$D$1057,">="&$S$1,$D$14:$D$1057,"<="&$K$1,$C$14:$C$1057,"<>Récap")) -> 0
Q5: Collective Investment Undertakings | R5: =+ABS(SUMIFS($J$14:$J$1057,$A$14:$A$1057,"CIU",$D$14:$D$1057,">="&$S$1,$D$14:$D$1057,"<="&$K$1,$C$14:$C$1057,"<>Récap"))+ABS(SUMIFS($G$14:$G$1057,$A$14:$A$1057,"CIU",$D$14:$D$1057,">="&$S$1,$D$14:$D$1057,"<="&$K$1,$C$14:$C$1057,"<>Récap")) -> 0
Q6: Convertible bonds not issued by financial institutionsNon-investment grade | R6: =+ABS(SUMIFS($J$14:$J$1057,$A$14:$A$1057,"OC",$D$14:$D$1057,">="&$S$1,$D$14:$D$1057,"<="&$K$1,$C$14:$C$1057,"<>Récap"))+ABS(SUMIFS($G$14:$G$1057,$A$14:$A$1057,"OC",$D$14:$D$1057,">="&$S$1,$D$14:$D$1057,"<="&$K$1,$C$14:$C$1057,"<>Récap")) -> 0
B10: Les instruments financiers sont comptabilisés "frais exclus"; les droits d'enregistrement
B11: sont à comptabiliser en charges | E11: ACHATS | H11: VENTES | L11: SOLDES | O11: PLUS VALUES REALISEES | P11: MOINS VALUES REALISEES | Q11: Prix de vente- prix de revient (2) | R11: Sommes des plus ou moins values (1) | S11: Contrôle (2)-(1)
B12: TITRE | C12: LIBELLE | D12: DATE OPE | E12: QTE | F12: PR UNITAIRE | G12: PR OPERATION | H12: QTE | I12: PV UNITAIRE | J12: PV OPERATION | K12: PR OPERATION | L12: QUANTITE | M12: PR CUMULE | N12: PR UNIT. MOYEN | Q12: Plus ou moins values nettes | R12: Plus ou moins values nettes | S12: Contrôle
C13: Report | N13: =+IF(L13=0,0,M13/L13) -> 0 | O13: =IF(J13-K13>0,J13-K13,0) -> 0 | P13: =IF(J13-K13<0,J13-K13,0) -> 0 | Q13: =+J13-K13 -> 0 | R13: =+O13+P13 -> 0 | S13: =+Q13-R13 -> 0
A14: UE | B14: Inflexion BIDCO - OCADP 2 | C14: Souscription | D14: 45863 | E14: 40320000 | F14: =IF(E14=0,0,G14/E14) -> 1 | G14: 40320000 | I14: =IF(H14=0,0,J14/H14) -> 0 | K14: =+H14*N13 -> 0 | L14: =+L13+E14-H14 -> 40320000 | M14: =+M13+G14-K14 -> 40320000 | N14: =+ROUND(IF(L14=0,0,M14/L14),2) -> 1 | O14: =IF(J14-K14>0,J14-K14,0) -> 0 | P14: =IF(J14-K14<0,J14-K14,0) -> 0 | Q14: =+J14-K14 -> 0 | R14: =+O14+P14 -> 0 | S14: =+Q14-R14 -> 0
A15: UE | B15: Inflexion BIDCO - OCADP 2 | F15: =IF(E15=0,0,G15/E15) -> 0 | I15: =IF(H15=0,0,J15/H15) -> 0 | K15: =+H15*N14 -> 0 | L15: =+L14+E15-H15 -> 40320000 | M15: =+M14+G15-K15 -> 40320000 | N15: =+ROUND(IF(L15=0,0,M15/L15),2) -> 1 | O15: =IF(J15-K15>0,J15-K15,0) -> 0 | P15: =IF(J15-K15<0,J15-K15,0) -> 0 | Q15: =+J15-K15 -> 0 | R15: =+O15+P15 -> 0 | S15: =+Q15-R15 -> 0
A16: UE | B16: Inflexion BIDCO - OCADP 2 | F16: =IF(E16=0,0,G16/E16) -> 0 | I16: =IF(H16=0,0,J16/H16) -> 0 | K16: =+H16*N15 -> 0 | L16: =+L15+E16-H16 -> 40320000 | M16: =+M15+G16-K16 -> 40320000 | N16: =+ROUND(IF(L16=0,0,M16/L16),2) -> 1 | O16: =IF(J16-K16>0,J16-K16,0) -> 0 | P16: =IF(J16-K16<0,J16-K16,0) -> 0 | Q16: =+J16-K16 -> 0 | R16: =+O16+P16 -> 0 | S16: =+Q16-R16 -> 0
A17: UE | B17: Inflexion BIDCO - OCADP 2 | F17: =IF(E17=0,0,G17/E17) -> 0 | I17: =IF(H17=0,0,J17/H17) -> 0 | K17: =+H17*N16 -> 0 | L17: =+L16+E17-H17 -> 40320000 | M17: =+M16+G17-K17 -> 40320000 | N17: =+ROUND(IF(L17=0,0,M17/L17),2) -> 1 | O17: =IF(J17-K17>0,J17-K17,0) -> 0 | P17: =IF(J17-K17<0,J17-K17,0) -> 0 | Q17: =+J17-K17 -> 0 | R17: =+O17+P17 -> 0 | S17: =+Q17-R17 -> 0
A18: UE | B18: Inflexion BIDCO - OCADP 2 | F18: =IF(E18=0,0,G18/E18) -> 0 | I18: =IF(H18=0,0,J18/H18) -> 0 | K18: =+H18*N17 -> 0 | L18: =+L17+E18-H18 -> 40320000 | M18: =+M17+G18-K18 -> 40320000 | N18: =+ROUND(IF(L18=0,0,M18/L18),2) -> 1 | O18: =IF(J18-K18>0,J18-K18,0) -> 0 | P18: =IF(J18-K18<0,J18-K18,0) -> 0 | Q18: =+J18-K18 -> 0 | R18: =+O18+P18 -> 0 | S18: =+Q18-R18 -> 0
A19: UE | B19: Inflexion BIDCO - OCADP 2 | F19: =IF(E19=0,0,G19/E19) -> 0 | I19: =IF(H19=0,0,J19/H19) -> 0 | K19: =+H19*N18 -> 0 | L19: =+L18+E19-H19 -> 40320000 | M19: =+M18+G19-K19 -> 40320000 | N19: =+ROUND(IF(L19=0,0,M19/L19),2) -> 1 | O19: =IF(J19-K19>0,J19-K19,0) -> 0 | P19: =IF(J19-K19<0,J19-K19,0) -> 0 | Q19: =+J19-K19 -> 0 | R19: =+O19+P19 -> 0 | S19: =+Q19-R19 -> 0
A20: UE | B20: =B19 -> Inflexion BIDCO - OCADP 2 | C20: Récap | D20: =+$K$1 -> 46022 | E20: =SUM(E14:E19) -> 40320000 | F20: =+IF(E20=0,0,G20/E20) -> 1 | G20: =SUM(G13:G19) -> 40320000 | H20: =SUM(H13:H19) -> 0 | I20: =+IF(H20=0,0,J20/H20) -> 0 | J20: =SUM(J13:J19) -> 0 | K20: =SUM(K13:K19) -> 0 | L20: =+L19 -> 40320000 | M20: =+M19 -> 40320000 | N20: =+IF(L20=0,0,M20/L20) -> 1 | O20: =SUM(O13:O16) -> 0 | P20: =SUM(P13:P16) -> 0 | Q20: =+J20-K20 -> 0 | R20: =+O20+P20 -> 0 | S20: =+Q20-R20 -> 0
A21: UE | C21: Report | Q21: =+J21-K21 -> 0 | R21: =+O21+P21 -> 0 | S21: =+Q21-R21 -> 0
A22: UE | B22: Inflexion BIDCO - ORADP 1 | C22: Souscription | D22: 45863 | E22: 10080000 | F22: =IF(E22=0,0,G22/E22) -> 1 | G22: 10080000 | I22: =IF(H22=0,0,J22/H22) -> 0 | K22: =+H22*N21 -> 0 | L22: =+L21+E22-H22 -> 10080000 | M22: =+M21+G22-K22 -> 10080000 | N22: =+IF(L22=0,0,M22/L22) -> 1 | O22: =IF(J22-K22>0,J22-K22,0) -> 0 | P22: =IF(J22-K22<0,J22-K22,0) -> 0 | Q22: =+J22-K22 -> 0 | R22: =+O22+P22 -> 0 | S22: =+Q22-R22 -> 0
A23: UE | B23: =B22 -> Inflexion BIDCO - ORADP 1 | F23: =IF(E23=0,0,G23/E23) -> 0 | I23: =IF(H23=0,0,J23/H23) -> 0 | K23: =+H23*N22 -> 0 | L23: =+L22+E23-H23 -> 10080000 | M23: =+M22+G23-K23 -> 10080000 | N23: =+IF(L23=0,0,M23/L23) -> 1 | O23: =IF(J23-K23>0,J23-K23,0) -> 0 | P23: =IF(J23-K23<0,J23-K23,0) -> 0 | Q23: =+J23-K23 -> 0 | R23: =+O23+P23 -> 0 | S23: =+Q23-R23 -> 0
A24: UE | B24: =B23 -> Inflexion BIDCO - ORADP 1 | F24: =IF(E24=0,0,G24/E24) -> 0 | I24: =IF(H24=0,0,J24/H24) -> 0 | K24: =+H24*N23 -> 0 | L24: =+L23+E24-H24 -> 10080000 | M24: =+M23+G24-K24 -> 10080000 | N24: =+IF(L24=0,0,M24/L24) -> 1 | O24: =IF(J24-K24>0,J24-K24,0) -> 0 | P24: =IF(J24-K24<0,J24-K24,0) -> 0 | Q24: =+J24-K24 -> 0 | R24: =+O24+P24 -> 0 | S24: =+Q24-R24 -> 0
A25: UE | B25: =B24 -> Inflexion BIDCO - ORADP 1 | F25: =IF(E25=0,0,G25/E25) -> 0 | I25: =IF(H25=0,0,J25/H25) -> 0 | K25: =+H25*N24 -> 0 | L25: =+L24+E25-H25 -> 10080000 | M25: =+M24+G25-K25 -> 10080000 | N25: =+IF(L25=0,0,M25/L25) -> 1 | O25: =IF(J25-K25>0,J25-K25,0) -> 0 | P25: =IF(J25-K25<0,J25-K25,0) -> 0 | Q25: =+J25-K25 -> 0 | R25: =+O25+P25 -> 0 | S25: =+Q25-R25 -> 0
A26: UE | B26: =B25 -> Inflexion BIDCO - ORADP 1 | F26: =IF(E26=0,0,G26/E26) -> 0 | I26: =IF(H26=0,0,J26/H26) -> 0 | K26: =+H26*N25 -> 0 | L26: =+L25+E26-H26 -> 10080000 | M26: =+M25+G26-K26 -> 10080000 | N26: =+IF(L26=0,0,M26/L26) -> 1 | O26: =IF(J26-K26>0,J26-K26,0) -> 0 | P26: =IF(J26-K26<0,J26-K26,0) -> 0 | Q26: =+J26-K26 -> 0 | R26: =+O26+P26 -> 0 | S26: =+Q26-R26 -> 0
A27: UE | B27: =B26 -> Inflexion BIDCO - ORADP 1 | F27: =IF(E27=0,0,G27/E27) -> 0 | I27: =IF(H27=0,0,J27/H27) -> 0 | K27: =+H27*N26 -> 0 | L27: =+L26+E27-H27 -> 10080000 | M27: =+M26+G27-K27 -> 10080000 | N27: =+IF(L27=0,0,M27/L27) -> 1 | O27: =IF(J27-K27>0,J27-K27,0) -> 0 | P27: =IF(J27-K27<0,J27-K27,0) -> 0 | Q27: =+J27-K27 -> 0 | R27: =+O27+P27 -> 0 | S27: =+Q27-R27 -> 0
A28: UE | B28: =B27 -> Inflexion BIDCO - ORADP 1 | F28: =IF(E28=0,0,G28/E28) -> 0 | I28: =IF(H28=0,0,J28/H28) -> 0 | K28: =+H28*N27 -> 0 | L28: =+L27+E28-H28 -> 10080000 | M28: =+M27+G28-K28 -> 10080000 | N28: =+IF(L28=0,0,M28/L28) -> 1 | O28: =IF(J28-K28>0,J28-K28,0) -> 0 | P28: =IF(J28-K28<0,J28-K28,0) -> 0 | Q28: =+J28-K28 -> 0 | R28: =+O28+P28 -> 0 | S28: =+Q28-R28 -> 0
A29: UE | B29: =B28 -> Inflexion BIDCO - ORADP 1 | F29: =IF(E29=0,0,G29/E29) -> 0 | I29: =IF(H29=0,0,J29/H29) -> 0 | K29: =+H29*N28 -> 0 | L29: =+L28+E29-H29 -> 10080000 | M29: =+M28+G29-K29 -> 10080000 | N29: =+IF(L29=0,0,M29/L29) -> 1 | O29: =IF(J29-K29>0,J29-K29,0) -> 0 | P29: =IF(J29-K29<0,J29-K29,0) -> 0 | Q29: =+J29-K29 -> 0 | R29: =+O29+P29 -> 0 | S29: =+Q29-R29 -> 0
A30: UE | B30: =B29 -> Inflexion BIDCO - ORADP 1 | F30: =IF(E30=0,0,G30/E30) -> 0 | I30: =IF(H30=0,0,J30/H30) -> 0 | K30: =+H30*N29 -> 0 | L30: =+L29+E30-H30 -> 10080000 | M30: =+M29+G30-K30 -> 10080000 | N30: =+IF(L30=0,0,M30/L30) -> 1 | O30: =IF(J30-K30>0,J30-K30,0) -> 0 | P30: =IF(J30-K30<0,J30-K30,0) -> 0 | Q30: =+J30-K30 -> 0 | R30: =+O30+P30 -> 0 | S30: =+Q30-R30 -> 0
A31: UE | B31: =B30 -> Inflexion BIDCO - ORADP 1 | F31: =IF(E31=0,0,G31/E31) -> 0 | I31: =IF(H31=0,0,J31/H31) -> 0 | K31: =+H31*N30 -> 0 | L31: =+L30+E31-H31 -> 10080000 | M31: =+M30+G31-K31 -> 10080000 | N31: =+IF(L31=0,0,M31/L31) -> 1 | O31: =IF(J31-K31>0,J31-K31,0) -> 0 | P31: =IF(J31-K31<0,J31-K31,0) -> 0 | Q31: =+J31-K31 -> 0 | R31: =+O31+P31 -> 0 | S31: =+Q31-R31 -> 0
A32: UE | B32: =B31 -> Inflexion BIDCO - ORADP 1 | F32: =IF(E32=0,0,G32/E32) -> 0 | I32: =IF(H32=0,0,J32/H32) -> 0 | K32: =+H32*N31 -> 0 | L32: =+L31+E32-H32 -> 10080000 | M32: =+M31+G32-K32 -> 10080000 | N32: =+IF(L32=0,0,M32/L32) -> 1 | O32: =IF(J32-K32>0,J32-K32,0) -> 0 | P32: =IF(J32-K32<0,J32-K32,0) -> 0 | Q32: =+J32-K32 -> 0 | R32: =+O32+P32 -> 0 | S32: =+Q32-R32 -> 0
A33: UE | B33: =B32 -> Inflexion BIDCO - ORADP 1 | F33: =IF(E33=0,0,G33/E33) -> 0 | I33: =IF(H33=0,0,J33/H33) -> 0 | K33: =+H33*N32 -> 0 | L33: =+L32+E33-H33 -> 10080000 | M33: =+M32+G33-K33 -> 10080000 | N33: =+IF(L33=0,0,M33/L33) -> 1 | O33: =IF(J33-K33>0,J33-K33,0) -> 0 | P33: =IF(J33-K33<0,J33-K33,0) -> 0 | Q33: =+J33-K33 -> 0 | R33: =+O33+P33 -> 0 | S33: =+Q33-R33 -> 0
A34: UE | B34: =B33 -> Inflexion BIDCO - ORADP 1 | F34: =IF(E34=0,0,G34/E34) -> 0 | I34: =IF(H34=0,0,J34/H34) -> 0 | K34: =+H34*N33 -> 0 | L34: =+L33+E34-H34 -> 10080000 | M34: =+M33+G34-K34 -> 10080000 | N34: =+IF(L34=0,0,M34/L34) -> 1 | O34: =IF(J34-K34>0,J34-K34,0) -> 0 | P34: =IF(J34-K34<0,J34-K34,0) -> 0 | Q34: =+J34-K34 -> 0 | R34: =+O34+P34 -> 0 | S34: =+Q34-R34 -> 0
A35: UE | B35: =B34 -> Inflexion BIDCO - ORADP 1 | C35: Récap | D35: =+$K$1 -> 46022 | E35: =SUM(E22:E34) -> 10080000 | F35: =+IF(E35=0,0,G35/E35) -> 1 | G35: =SUM(G22:G34) -> 10080000 | H35: =SUM(H22:H34) -> 0 | I35: =+IF(H35=0,0,J35/H35) -> 0 | J35: =SUM(J22:J34) -> 0 | K35: =SUM(K21:K34) -> 0 | L35: =+L34 -> 10080000 | M35: =+M34 -> 10080000 | N35: =+IF(L35=0,0,M35/L35) -> 1 | O35: =SUM(O21:O34) -> 0 | P35: =SUM(P21:P34) -> 0 | Q35: =+J35-K35 -> 0 | R35: =+O35+P35 -> 0 | S35: =+Q35-R35 -> 0
A36: UE | C36: Report | Q36: =+J36-K36 -> 0 | R36: =+O36+P36 -> 0 | S36: =+Q36-R36 -> 0
A37: UE | B37: Koenig solutions - ADP B | C37: Souscription | D37: 45986 | E37: 87200 | F37: =IF(E37=0,0,G37/E37) -> 1 | G37: 87200 | I37: =IF(H37=0,0,J37/H37) -> 0 | K37: =+H37*N36 -> 0 | L37: =+L36+E37-H37 -> 87200 | M37: =+M36+G37-K37 -> 87200 | N37: =+IF(L37=0,0,M37/L37) -> 1 | O37: =IF(J37-K37>0,J37-K37,0) -> 0 | P37: =IF(J37-K37<0,J37-K37,0) -> 0 | Q37: =+J37-K37 -> 0 | R37: =+O37+P37 -> 0 | S37: =+Q37-R37 -> 0
A38: UE | B38: =B37 -> Koenig solutions - ADP B | C38: Prime d'émission | D38: 45986 | F38: =IF(E38=0,0,G38/E38) -> 0 | G38: 8632800 | I38: =IF(H38=0,0,J38/H38) -> 0 | K38: =+H38*N37 -> 0 | L38: =+L37+E38-H38 -> 87200 | M38: =+M37+G38-K38 -> 8720000 | N38: =+IF(L38=0,0,M38/L38) -> 100 | O38: =IF(J38-K38>0,J38-K38,0) -> 0 | P38: =IF(J38-K38<0,J38-K38,0) -> 0 | Q38: =+J38-K38 -> 0 | R38: =+O38+P38 -> 0 | S38: =+Q38-R38 -> 0
A39: UE | B39: =B38 -> Koenig solutions - ADP B | F39: =IF(E39=0,0,G39/E39) -> 0 | I39: =IF(H39=0,0,J39/H39) -> 0 | L39: =+L38+E39-H39 -> 87200 | M39: =+M38+G39-K39 -> 8720000 | N39: =+IF(L39=0,0,M39/L39) -> 100 | O39: =IF(J39-K39>0,J39-K39,0) -> 0 | P39: =IF(J39-K39<0,J39-K39,0) -> 0 | Q39: =+J39-K39 -> 0 | R39: =+O39+P39 -> 0 | S39: =+Q39-R39 -> 0
A40: UE | B40: =B39 -> Koenig solutions - ADP B | C40: Récap | D40: =+$K$1 -> 46022 | E40: =SUM(E37:E39) -> 87200 | F40: =+IF(E40=0,0,G40/E40) -> 100 | G40: =SUM(G36:G39) -> 8720000 | H40: =SUM(H36:H39) -> 0 | I40: =+IF(H40=0,0,J40/H40) -> 0 | J40: =SUM(J36:J39) -> 0 | K40: =SUM(K36:K39) -> 0 | L40: =+L39 -> 87200 | M40: =+M39 -> 8720000 | N40: =+IF(L40=0,0,M40/L40) -> 100 | O40: =SUM(O36:O39) -> 0 | P40: =SUM(P36:P39) -> 0 | Q40: =+J40-K40 -> 0 | R40: =+O40+P40 -> 0 | S40: =+Q40-R40 -> 0
A41: UE | C41: Report | Q41: =+J41-K41 -> 0 | R41: =+O41+P41 -> 0 | S41: =+Q41-R41 -> 0
A42: UE | B42: Koenig solutions - OC (SHL) | C42: Souscription | D42: 45986 | E42: 3200 | F42: =IF(E42=0,0,G42/E42) -> 1 | G42: 3200 | I42: =IF(H42=0,0,J42/H42) -> 0 | K42: =+H42*N41 -> 0 | L42: =+L41+E42-H42 -> 3200 | M42: =+M41+G42-K42 -> 3200 | N42: =+IF(L42=0,0,M42/L42) -> 1 | O42: =IF(J42-K42>0,J42-K42,0) -> 0 | P42: =IF(J42-K42<0,J42-K42,0) -> 0 | Q42: =+J42-K42 -> 0 | R42: =+O42+P42 -> 0 | S42: =+Q42-R42 -> 0
A43: UE | B43: =B42 -> Koenig solutions - OC (SHL) | C43: Prime d'émission | D43: 45986 | F43: =IF(E43=0,0,G43/E43) -> 0 | G43: 26156800 | I43: =IF(H43=0,0,J43/H43) -> 0 | K43: =+H43*N42 -> 0 | L43: =+L42+E43-H43 -> 3200 | M43: =+M42+G43-K43 -> 26160000 | N43: =+IF(L43=0,0,M43/L43) -> 8175 | O43: =IF(J43-K43>0,J43-K43,0) -> 0 | P43: =IF(J43-K43<0,J43-K43,0) -> 0 | Q43: =+J43-K43 -> 0 | R43: =+O43+P43 -> 0 | S43: =+Q43-R43 -> 0
A44: UE | B44: =B43 -> Koenig solutions - OC (SHL) | F44: =IF(E44=0,0,G44/E44) -> 0 | I44: =IF(H44=0,0,J44/H44) -> 0 | L44: =+L43+E44-H44 -> 3200 | M44: =+M43+G44-K44 -> 26160000 | N44: =+IF(L44=0,0,M44/L44) -> 8175 | O44: =IF(J44-K44>0,J44-K44,0) -> 0 | P44: =IF(J44-K44<0,J44-K44,0) -> 0 | Q44: =+J44-K44 -> 0 | R44: =+O44+P44 -> 0 | S44: =+Q44-R44 -> 0
A45: UE | B45: =B44 -> Koenig solutions - OC (SHL) | C45: Récap | D45: =+$K$1 -> 46022 | E45: =SUM(E42:E44) -> 3200 | F45: =+IF(E45=0,0,G45/E45) -> 8175 | G45: =SUM(G41:G44) -> 26160000 | H45: =SUM(H41:H44) -> 0 | I45: =+IF(H45=0,0,J45/H45) -> 0 | J45: =SUM(J41:J44) -> 0 | K45: =SUM(K41:K44) -> 0 | L45: =+L44 -> 3200 | M45: =+M44 -> 26160000 | N45: =+IF(L45=0,0,M45/L45) -> 8175 | O45: =SUM(O41:O44) -> 0 | P45: =SUM(P41:P44) -> 0 | Q45: =+J45-K45 -> 0 | R45: =+O45+P45 -> 0 | S45: =+Q45-R45 -> 0
A46: UE | C46: Report | Q46: =+J46-K46 -> 0 | R46: =+O46+P46 -> 0 | S46: =+Q46-R46 -> 0
A47: UE | B47: Koenig solutions - OC (Warehouse II - ADP A) | C47: Souscription | D47: 45986 | E47: 500 | F47: =IF(E47=0,0,G47/E47) -> 1000 | G47: 500000 | I47: =IF(H47=0,0,J47/H47) -> 0 | K47: =+H47*N46 -> 0 | L47: =+L46+E47-H47 -> 500 | M47: =+M46+G47-K47 -> 500000 | N47: =+IF(L47=0,0,M47/L47) -> 1000 | O47: =IF(J47-K47>0,J47-K47,0) -> 0 | P47: =IF(J47-K47<0,J47-K47,0) -> 0 | Q47: =+J47-K47 -> 0 | R47: =+O47+P47 -> 0 | S47: =+Q47-R47 -> 0
A48: UE | B48: =B47 -> Koenig solutions - OC (Warehouse II - ADP A) | F48: =IF(E48=0,0,G48/E48) -> 0 | I48: =IF(H48=0,0,J48/H48) -> 0 | K48: =+H48*N47 -> 0 | L48: =+L47+E48-H48 -> 500 | M48: =+M47+G48-K48 -> 500000 | N48: =+IF(L48=0,0,M48/L48) -> 1000 | O48: =IF(J48-K48>0,J48-K48,0) -> 0 | P48: =IF(J48-K48<0,J48-K48,0) -> 0 | Q48: =+J48-K48 -> 0 | R48: =+O48+P48 -> 0 | S48: =+Q48-R48 -> 0
A49: UE | B49: =B48 -> Koenig solutions - OC (Warehouse II - ADP A) | F49: =IF(E49=0,0,G49/E49) -> 0 | I49: =IF(H49=0,0,J49/H49) -> 0 | K49: =+H49*N48 -> 0 | L49: =+L48+E49-H49 -> 500 | M49: =+M48+G49-K49 -> 500000 | N49: =+IF(L49=0,0,M49/L49) -> 1000 | O49: =IF(J49-K49>0,J49-K49,0) -> 0 | P49: =IF(J49-K49<0,J49-K49,0) -> 0 | Q49: =+J49-K49 -> 0 | R49: =+O49+P49 -> 0 | S49: =+Q49-R49 -> 0
A50: UE | B50: =B49 -> Koenig solutions - OC (Warehouse II - ADP A) | F50: =IF(E50=0,0,G50/E50) -> 0 | I50: =IF(H50=0,0,J50/H50) -> 0 | K50: =+H50*N48 -> 0 | L50: =+L49+E50-H50 -> 500 | M50: =+M49+G50-K50 -> 500000 | N50: =+IF(L50=0,0,M50/L50) -> 1000 | O50: =IF(J50-K50>0,J50-K50,0) -> 0 | P50: =IF(J50-K50<0,J50-K50,0) -> 0 | Q50: =+J50-K50 -> 0 | R50: =+O50+P50 -> 0 | S50: =+Q50-R50 -> 0
A51: UE | B51: =B50 -> Koenig solutions - OC (Warehouse II - ADP A) | C51: Récap | D51: =+$K$1 -> 46022 | E51: =SUM(E47:E50) -> 500 | F51: =+IF(E51=0,0,G51/E51) -> 1000 | G51: =SUM(G46:G50) -> 500000 | H51: =SUM(H46:H50) -> 0 | I51: =+IF(H51=0,0,J51/H51) -> 0 | J51: =SUM(J46:J50) -> 0 | K51: =SUM(K46:K50) -> 0 | L51: =+L50 -> 500 | M51: =+M50 -> 500000 | N51: =+IF(L51=0,0,M51/L51) -> 1000 | O51: =SUM(O46:O50) -> 0 | P51: =SUM(P46:P50) -> 0 | Q51: =+J51-K51 -> 0 | R51: =+O51+P51 -> 0 | S51: =+Q51-R51 -> 0
A52: UE | C52: Report | Q52: =+J52-K52 -> 0 | R52: =+O52+P52 -> 0 | S52: =+Q52-R52 -> 0
A53: UE | B53: SNIC Technologies Group - OBSA | C53: Souscription | D53: 46007 | E53: 63750000 | F53: =IF(E53=0,0,G53/E53) -> 1 | G53: 63750000 | I53: =IF(H53=0,0,J53/H53) -> 0 | K53: =+H53*N52 -> 0 | L53: =+L52+E53-H53 -> 63750000 | M53: =+M52+G53-K53 -> 63750000 | N53: =+IF(L53=0,0,M53/L53) -> 1 | O53: =IF(J53-K53>0,J53-K53,0) -> 0 | P53: =IF(J53-K53<0,J53-K53,0) -> 0 | Q53: =+J53-K53 -> 0 | R53: =+O53+P53 -> 0 | S53: =+Q53-R53 -> 0
A54: UE | B54: SNIC Technologies Group - OBSA | F54: =IF(E54=0,0,G54/E54) -> 0 | I54: =IF(H54=0,0,J54/H54) -> 0 | K54: =+H54*N53 -> 0 | L54: =+L53+E54-H54 -> 63750000 | M54: =+M53+G54-K54 -> 63750000 | N54: =+IF(L54=0,0,M54/L54) -> 1 | O54: =IF(J54-K54>0,J54-K54,0) -> 0 | P54: =IF(J54-K54<0,J54-K54,0) -> 0 | Q54: =+J54-K54 -> 0 | R54: =+O54+P54 -> 0 | S54: =+Q54-R54 -> 0
A55: UE | B55: SNIC Technologies Group - OBSA | F55: =IF(E55=0,0,G55/E55) -> 0 | I55: =IF(H55=0,0,J55/H55) -> 0 | K55: =+H55*N54 -> 0 | L55: =+L54+E55-H55 -> 63750000 | M55: =+M54+G55-K55 -> 63750000 | N55: =+IF(L55=0,0,M55/L55) -> 1 | O55: =IF(J55-K55>0,J55-K55,0) -> 0 | P55: =IF(J55-K55<0,J55-K55,0) -> 0 | Q55: =+J55-K55 -> 0 | R55: =+O55+P55 -> 0 | S55: =+Q55-R55 -> 0
A56: UE | B56: =B55 -> SNIC Technologies Group - OBSA | C56: Récap | D56: =+$K$1 -> 46022 | E56: =SUM(E53:E55) -> 63750000 | F56: =+IF(E56=0,0,G56/E56) -> 1 | G56: =SUM(G52:G55) -> 63750000 | H56: =SUM(H52:H55) -> 0 | I56: =+IF(H56=0,0,J56/H56) -> 0 | J56: =SUM(J52:J55) -> 0 | K56: =SUM(K52:K55) -> 0 | L56: =+L55 -> 63750000 | M56: =+M55 -> 63750000 | N56: =+IF(L56=0,0,M56/L56) -> 1 | O56: =SUM(O52:O55) -> 0 | P56: =SUM(P52:P55) -> 0 | Q56: =+J56-K56 -> 0 | R56: =+O56+P56 -> 0 | S56: =+Q56-R56 -> 0
A57: UE | C57: Report | Q57: =+J57-K57 -> 0 | R57: =+O57+P57 -> 0 | S57: =+Q57-R57 -> 0
A58: UE | F58: =IF(E58=0,0,G58/E58) -> 0 | I58: =IF(H58=0,0,J58/H58) -> 0 | K58: =+H58*N57 -> 0 | L58: =+L57+E58-H58 -> 0 | M58: =+M57+G58-K58 -> 0 | N58: =+IF(L58=0,0,M58/L58) -> 0 | O58: =IF(J58-K58>0,J58-K58,0) -> 0 | P58: =IF(J58-K58<0,J58-K58,0) -> 0 | Q58: =+J58-K58 -> 0 | R58: =+O58+P58 -> 0 | S58: =+Q58-R58 -> 0
A59: UE | F59: =IF(E59=0,0,G59/E59) -> 0 | I59: =IF(H59=0,0,J59/H59) -> 0 | K59: =+H59*N58 -> 0 | L59: =+L58+E59-H59 -> 0 | M59: =+M58+G59-K59 -> 0 | N59: =+IF(L59=0,0,M59/L59) -> 0 | O59: =IF(J59-K59>0,J59-K59,0) -> 0 | P59: =IF(J59-K59<0,J59-K59,0) -> 0 | Q59: =+J59-K59 -> 0 | R59: =+O59+P59 -> 0 | S59: =+Q59-R59 -> 0
A60: UE | F60: =IF(E60=0,0,G60/E60) -> 0 | I60: =IF(H60=0,0,J60/H60) -> 0 | K60: =+H60*N59 -> 0 | L60: =+L59+E60-H60 -> 0 | M60: =+M59+G60-K60 -> 0 | N60: =+IF(L60=0,0,M60/L60) -> 0 | O60: =IF(J60-K60>0,J60-K60,0) -> 0 | P60: =IF(J60-K60<0,J60-K60,0) -> 0 | Q60: =+J60-K60 -> 0 | R60: =+O60+P60 -> 0 | S60: =+Q60-R60 -> 0
A61: UE | B61: =B60 -> 0 | C61: Récap | D61: =+$K$1 -> 46022 | E61: =SUM(E58:E60) -> 0 | F61: =+IF(E61=0,0,G61/E61) -> 0 | G61: =SUM(G57:G60) -> 0 | H61: =SUM(H57:H60) -> 0 | I61: =+IF(H61=0,0,J61/H61) -> 0 | J61: =SUM(J57:J60) -> 0 | K61: =SUM(K57:K60) -> 0 | L61: =+L60 -> 0 | M61: =+M60 -> 0 | N61: =+IF(L61=0,0,M61/L61) -> 0 | O61: =SUM(O57:O60) -> 0 | P61: =SUM(P57:P60) -> 0 | Q61: =+J61-K61 -> 0 | R61: =+O61+P61 -> 0 | S61: =+Q61-R61 -> 0
A62: UE | C62: Report | Q62: =+J62-K62 -> 0 | R62: =+O62+P62 -> 0 | S62: =+Q62-R62 -> 0
A63: UE | F63: =IF(E63=0,0,G63/E63) -> 0 | I63: =IF(H63=0,0,J63/H63) -> 0 | K63: =+H63*N62 -> 0 | L63: =+L62+E63-H63 -> 0 | M63: =+M62+G63-K63 -> 0 | N63: =+IF(L63=0,0,M63/L63) -> 0 | O63: =IF(J63-K63>0,J63-K63,0) -> 0 | P63: =IF(J63-K63<0,J63-K63,0) -> 0 | Q63: =+J63-K63 -> 0 | R63: =+O63+P63 -> 0 | S63: =+Q63-R63 -> 0
A64: UE | F64: =IF(E64=0,0,G64/E64) -> 0 | I64: =IF(H64=0,0,J64/H64) -> 0 | K64: =+H64*N63 -> 0 | L64: =+L63+E64-H64 -> 0 | M64: =+M63+G64-K64 -> 0 | N64: =+IF(L64=0,0,M64/L64) -> 0 | O64: =IF(J64-K64>0,J64-K64,0) -> 0 | P64: =IF(J64-K64<0,J64-K64,0) -> 0 | Q64: =+J64-K64 -> 0 | R64: =+O64+P64 -> 0 | S64: =+Q64-R64 -> 0
A65: UE | F65: =IF(E65=0,0,G65/E65) -> 0 | I65: =IF(H65=0,0,J65/H65) -> 0 | K65: =+H65*N64 -> 0 | L65: =+L64+E65-H65 -> 0 | M65: =+M64+G65-K65 -> 0 | N65: =+IF(L65=0,0,M65/L65) -> 0 | O65: =IF(J65-K65>0,J65-K65,0) -> 0 | P65: =IF(J65-K65<0,J65-K65,0) -> 0 | Q65: =+J65-K65 -> 0 | R65: =+O65+P65 -> 0 | S65: =+Q65-R65 -> 0
A66: UE | B66: =B65 -> 0 | C66: Récap | D66: =+$K$1 -> 46022 | E66: =SUM(E63:E65) -> 0 | F66: =+IF(E66=0,0,G66/E66) -> 0 | G66: =SUM(G62:G65) -> 0 | H66: =SUM(H62:H65) -> 0 | I66: =+IF(H66=0,0,J66/H66) -> 0 | J66: =SUM(J62:J65) -> 0 | K66: =SUM(K62:K65) -> 0 | L66: =+L65 -> 0 | M66: =+M65 -> 0 | N66: =+IF(L66=0,0,M66/L66) -> 0 | O66: =SUM(O62:O65) -> 0 | P66: =SUM(P62:P65) -> 0 | Q66: =+J66-K66 -> 0 | R66: =+O66+P66 -> 0 | S66: =+Q66-R66 -> 0
A67: UE | C67: Report | Q67: =+J67-K67 -> 0 | R67: =+O67+P67 -> 0 | S67: =+Q67-R67 -> 0
A68: UE | F68: =IF(E68=0,0,G68/E68) -> 0 | I68: =IF(H68=0,0,J68/H68) -> 0 | K68: =+H68*N67 -> 0 | L68: =+L67+E68-H68 -> 0 | M68: =+M67+G68-K68 -> 0 | N68: =+IF(L68=0,0,M68/L68) -> 0 | O68: =IF(J68-K68>0,J68-K68,0) -> 0 | P68: =IF(J68-K68<0,J68-K68,0) -> 0 | Q68: =+J68-K68 -> 0 | R68: =+O68+P68 -> 0 | S68: =+Q68-R68 -> 0
A69: UE | F69: =IF(E69=0,0,G69/E69) -> 0 | I69: =IF(H69=0,0,J69/H69) -> 0 | K69: =+H69*N68 -> 0 | L69: =+L68+E69-H69 -> 0 | M69: =+M68+G69-K69 -> 0 | N69: =+IF(L69=0,0,M69/L69) -> 0 | O69: =IF(J69-K69>0,J69-K69,0) -> 0 | P69: =IF(J69-K69<0,J69-K69,0) -> 0 | Q69: =+J69-K69 -> 0 | R69: =+O69+P69 -> 0 | S69: =+Q69-R69 -> 0
A70: UE | F70: =IF(E70=0,0,G70/E70) -> 0 | I70: =IF(H70=0,0,J70/H70) -> 0 | K70: =+H70*N69 -> 0 | L70: =+L69+E70-H70 -> 0 | M70: =+M69+G70-K70 -> 0 | N70: =+IF(L70=0,0,M70/L70) -> 0 | O70: =IF(J70-K70>0,J70-K70,0) -> 0 | P70: =IF(J70-K70<0,J70-K70,0) -> 0 | Q70: =+J70-K70 -> 0 | R70: =+O70+P70 -> 0 | S70: =+Q70-R70 -> 0
A71: UE | B71: =+B70 -> 0 | C71: Récap | D71: =+$K$1 -> 46022 | E71: =SUM(E68:E70) -> 0 | F71: =+IF(E71=0,0,G71/E71) -> 0 | G71: =SUM(G67:G70) -> 0 | H71: =SUM(H67:H70) -> 0 | I71: =+IF(H71=0,0,J71/H71) -> 0 | J71: =SUM(J67:J70) -> 0 | K71: =SUM(K67:K70) -> 0 | L71: =+L70 -> 0 | M71: =+M70 -> 0 | N71: =+IF(L71=0,0,M71/L71) -> 0 | O71: =SUM(O67:O70) -> 0 | P71: =SUM(P67:P70) -> 0 | Q71: =+J71-K71 -> 0 | R71: =+O71+P71 -> 0 | S71: =+Q71-R71 -> 0
A72: UE | C72: Report | Q72: =+J72-K72 -> 0 | R72: =+O72+P72 -> 0 | S72: =+Q72-R72 -> 0
A73: UE | F73: =IF(E73=0,0,G73/E73) -> 0 | I73: =IF(H73=0,0,J73/H73) -> 0 | K73: =+H73*N72 -> 0 | L73: =+L72+E73-H73 -> 0 | M73: =+M72+G73-K73 -> 0 | N73: =+IF(L73=0,0,M73/L73) -> 0 | O73: =IF(J73-K73>0,J73-K73,0) -> 0 | P73: =IF(J73-K73<0,J73-K73,0) -> 0 | Q73: =+J73-K73 -> 0 | R73: =+O73+P73 -> 0 | S73: =+Q73-R73 -> 0
A74: UE | F74: =IF(E74=0,0,G74/E74) -> 0 | I74: =IF(H74=0,0,J74/H74) -> 0 | K74: =+H74*N73 -> 0 | L74: =+L73+E74-H74 -> 0 | M74: =+M73+G74-K74 -> 0 | N74: =+IF(L74=0,0,M74/L74) -> 0 | O74: =IF(J74-K74>0,J74-K74,0) -> 0 | P74: =IF(J74-K74<0,J74-K74,0) -> 0 | Q74: =+J74-K74 -> 0 | R74: =+O74+P74 -> 0 | S74: =+Q74-R74 -> 0
A75: UE | F75: =IF(E75=0,0,G75/E75) -> 0 | I75: =IF(H75=0,0,J75/H75) -> 0 | K75: =+H75*N74 -> 0 | L75: =+L74+E75-H75 -> 0 | M75: =+M74+G75-K75 -> 0 | N75: =+IF(L75=0,0,M75/L75) -> 0 | O75: =IF(J75-K75>0,J75-K75,0) -> 0 | P75: =IF(J75-K75<0,J75-K75,0) -> 0 | Q75: =+J75-K75 -> 0 | R75: =+O75+P75 -> 0 | S75: =+Q75-R75 -> 0
A76: UE | B76: =+B75 -> 0 | C76: Récap | D76: =+$K$1 -> 46022 | E76: =SUM(E73:E75) -> 0 | F76: =+IF(E76=0,0,G76/E76) -> 0 | G76: =SUM(G72:G75) -> 0 | H76: =SUM(H72:H75) -> 0 | I76: =+IF(H76=0,0,J76/H76) -> 0 | J76: =SUM(J72:J75) -> 0 | K76: =SUM(K72:K75) -> 0 | L76: =+L75 -> 0 | M76: =+M75 -> 0 | N76: =+IF(L76=0,0,M76/L76) -> 0 | O76: =SUM(O72:O75) -> 0 | P76: =SUM(P72:P75) -> 0 | Q76: =+J76-K76 -> 0 | R76: =+O76+P76 -> 0 | S76: =+Q76-R76 -> 0
A77: UE | C77: Report | Q77: =+J77-K77 -> 0 | R77: =+O77+P77 -> 0 | S77: =+Q77-R77 -> 0
A78: UE | F78: =IF(E78=0,0,G78/E78) -> 0 | I78: =IF(H78=0,0,J78/H78) -> 0 | K78: =+H78*N77 -> 0 | L78: =+L77+E78-H78 -> 0 | M78: =+M77+G78-K78 -> 0 | N78: =+IF(L78=0,0,M78/L78) -> 0 | O78: =IF(J78-K78>0,J78-K78,0) -> 0 | P78: =IF(J78-K78<0,J78-K78,0) -> 0 | Q78: =+J78-K78 -> 0 | R78: =+O78+P78 -> 0 | S78: =+Q78-R78 -> 0
A79: UE | F79: =IF(E79=0,0,G79/E79) -> 0 | I79: =IF(H79=0,0,J79/H79) -> 0 | K79: =+H79*N78 -> 0 | L79: =+L78+E79-H79 -> 0 | M79: =+M78+G79-K79 -> 0 | N79: =+IF(L79=0,0,M79/L79) -> 0 | O79: =IF(J79-K79>0,J79-K79,0) -> 0 | P79: =IF(J79-K79<0,J79-K79,0) -> 0 | Q79: =+J79-K79 -> 0 | R79: =+O79+P79 -> 0 | S79: =+Q79-R79 -> 0
F80: =IF(E80=0,0,G80/E80) -> 0 | I80: =IF(H80=0,0,J80/H80) -> 0 | K80: =+H80*N79 -> 0 | L80: =+L79+E80-H80 -> 0 | M80: =+M79+G80-K80 -> 0 | N80: =+IF(L80=0,0,M80/L80) -> 0 | O80: =IF(J80-K80>0,J80-K80,0) -> 0 | P80: =IF(J80-K80<0,J80-K80,0) -> 0 | Q80: =+J80-K80 -> 0 | R80: =+O80+P80 -> 0 | S80: =+Q80-R80 -> 0
F81: =IF(E81=0,0,G81/E81) -> 0 | I81: =IF(H81=0,0,J81/H81) -> 0 | K81: =+H81*N80 -> 0 | L81: =+L80+E81-H81 -> 0 | M81: =+M80+G81-K81 -> 0 | N81: =+IF(L81=0,0,M81/L81) -> 0 | O81: =IF(J81-K81>0,J81-K81,0) -> 0 | P81: =IF(J81-K81<0,J81-K81,0) -> 0 | Q81: =+J81-K81 -> 0 | R81: =+O81+P81 -> 0 | S81: =+Q81-R81 -> 0
A82: UE | F82: =IF(E82=0,0,G82/E82) -> 0 | I82: =IF(H82=0,0,J82/H82) -> 0 | K82: =+H82*N81 -> 0 | L82: =+L81+E82-H82 -> 0 | M82: =+M81+G82-K82 -> 0 | N82: =+IF(L82=0,0,M82/L82) -> 0 | O82: =IF(J82-K82>0,J82-K82,0) -> 0 | P82: =IF(J82-K82<0,J82-K82,0) -> 0 | Q82: =+J82-K82 -> 0 | R82: =+O82+P82 -> 0 | S82: =+Q82-R82 -> 0
A83: UE | B83: =B82 -> 0 | C83: Récap | D83: =+$K$1 -> 46022 | E83: =SUM(E78:E82) -> 0 | F83: =+IF(E83=0,0,G83/E83) -> 0 | G83: =SUM(G77:G82) -> 0 | H83: =SUM(H77:H82) -> 0 | I83: =+IF(H83=0,0,J83/H83) -> 0 | J83: =SUM(J77:J82) -> 0 | K83: =SUM(K77:K82) -> 0 | L83: =+L82 -> 0 | M83: =+M82 -> 0 | N83: =+IF(L83=0,0,M83/L83) -> 0 | O83: =SUM(O77:O82) -> 0 | P83: =SUM(P77:P82) -> 0 | Q83: =+J83-K83 -> 0 | R83: =+O83+P83 -> 0 | S83: =+Q83-R83 -> 0
A84: UE | Q84: =+J84-K84 -> 0 | R84: =+O84+P84 -> 0 | S84: =+Q84-R84 -> 0
A85: UE | F85: =IF(E85=0,0,G85/E85) -> 0 | I85: =IF(H85=0,0,J85/H85) -> 0 | K85: =+H85*N84 -> 0 | L85: =+L84+E85-H85 -> 0 | M85: =+M84+G85-K85 -> 0 | N85: =+IF(L85=0,0,M85/L85) -> 0 | O85: =IF(J85-K85>0,J85-K85,0) -> 0 | P85: =IF(J85-K85<0,J85-K85,0) -> 0 | Q85: =+J85-K85 -> 0 | R85: =+O85+P85 -> 0 | S85: =+Q85-R85 -> 0
A86: UE | F86: =IF(E86=0,0,G86/E86) -> 0 | I86: =IF(H86=0,0,J86/H86) -> 0 | K86: =+H86*N85 -> 0 | L86: =+L85+E86-H86 -> 0 | M86: =+M85+G86-K86 -> 0 | N86: =+IF(L86=0,0,M86/L86) -> 0 | O86: =IF(J86-K86>0,J86-K86,0) -> 0 | P86: =IF(J86-K86<0,J86-K86,0) -> 0 | Q86: =+J86-K86 -> 0 | R86: =+O86+P86 -> 0 | S86: =+Q86-R86 -> 0
F87: =IF(E87=0,0,G87/E87) -> 0 | I87: =IF(H87=0,0,J87/H87) -> 0 | K87: =+H87*N86 -> 0 | L87: =+L86+E87-H87 -> 0 | M87: =+M86+G87-K87 -> 0 | N87: =+IF(L87=0,0,M87/L87) -> 0 | O87: =IF(J87-K87>0,J87-K87,0) -> 0 | P87: =IF(J87-K87<0,J87-K87,0) -> 0 | Q87: =+J87-K87 -> 0 | R87: =+O87+P87 -> 0
F88: =IF(E88=0,0,G88/E88) -> 0 | I88: =IF(H88=0,0,J88/H88) -> 0 | K88: =+H88*N87 -> 0 | L88: =+L87+E88-H88 -> 0 | M88: =+M87+G88-K88 -> 0 | N88: =+IF(L88=0,0,M88/L88) -> 0 | O88: =IF(J88-K88>0,J88-K88,0) -> 0 | P88: =IF(J88-K88<0,J88-K88,0) -> 0 | Q88: =+J88-K88 -> 0 | R88: =+O88+P88 -> 0
F89: =IF(E89=0,0,G89/E89) -> 0 | I89: =IF(H89=0,0,J89/H89) -> 0 | K89: =+H89*N88 -> 0 | L89: =+L88+E89-H89 -> 0 | M89: =+M88+G89-K89 -> 0 | N89: =+IF(L89=0,0,M89/L89) -> 0 | O89: =IF(J89-K89>0,J89-K89,0) -> 0 | P89: =IF(J89-K89<0,J89-K89,0) -> 0 | Q89: =+J89-K89 -> 0 | R89: =+O89+P89 -> 0
A90: UE | F90: =IF(E90=0,0,G90/E90) -> 0 | I90: =IF(H90=0,0,J90/H90) -> 0 | K90: =+H90*N89 -> 0 | L90: =+L89+E90-H90 -> 0 | M90: =+M89+G90-K90 -> 0 | N90: =+IF(L90=0,0,M90/L90) -> 0 | O90: =IF(J90-K90>0,J90-K90,0) -> 0 | P90: =IF(J90-K90<0,J90-K90,0) -> 0 | Q90: =+J90-K90 -> 0 | R90: =+O90+P90 -> 0 | S90: =+Q90-R90 -> 0
A91: UE | B91: =B90 -> 0 | C91: Récap | D91: =+$K$1 -> 46022 | E91: =SUM(E85:E90) -> 0 | F91: =+IF(E91=0,0,G91/E91) -> 0 | G91: =SUM(G84:G90) -> 0 | H91: =SUM(H84:H90) -> 0 | I91: =+IF(H91=0,0,J91/H91) -> 0 | J91: =SUM(J84:J90) -> 0 | K91: =SUM(K84:K90) -> 0 | L91: =+L90 -> 0 | M91: =+M90 -> 0 | N91: =+IF(L91=0,0,M91/L91) -> 0 | O91: =SUM(O84:O90) -> 0 | P91: =SUM(P84:P90) -> 0 | Q91: =+J91-K91 -> 0 | R91: =+O91+P91 -> 0 | S91: =+Q91-R91 -> 0
A92: UE | C92: Report | Q92: =+J92-K92 -> 0 | R92: =+O92+P92 -> 0 | S92: =+Q92-R92 -> 0
A93: UE | F93: =IF(E93=0,0,G93/E93) -> 0 | I93: =IF(H93=0,0,J93/H93) -> 0 | K93: =+H93*N92 -> 0 | L93: =+L92+E93-H93 -> 0 | M93: =+M92+G93-K93 -> 0 | N93: =+IF(L93=0,0,M93/L93) -> 0 | O93: =IF(J93-K93>0,J93-K93,0) -> 0 | P93: =IF(J93-K93<0,J93-K93,0) -> 0 | Q93: =+J93-K93 -> 0 | R93: =+O93+P93 -> 0 | S93: =+Q93-R93 -> 0
A94: UE | F94: =IF(E94=0,0,G94/E94) -> 0 | I94: =IF(H94=0,0,J94/H94) -> 0 | K94: =+H94*N93 -> 0 | L94: =+L93+E94-H94 -> 0 | M94: =+M93+G94-K94 -> 0 | N94: =+IF(L94=0,0,M94/L94) -> 0 | O94: =IF(J94-K94>0,J94-K94,0) -> 0 | P94: =IF(J94-K94<0,J94-K94,0) -> 0 | Q94: =+J94-K94 -> 0 | R94: =+O94+P94 -> 0 | S94: =+Q94-R94 -> 0
F95: =IF(E95=0,0,G95/E95) -> 0 | I95: =IF(H95=0,0,J95/H95) -> 0 | K95: =+H95*N94 -> 0 | L95: =+L94+E95-H95 -> 0 | M95: =+M94+G95-K95 -> 0 | N95: =+IF(L95=0,0,M95/L95) -> 0 | O95: =IF(J95-K95>0,J95-K95,0) -> 0 | P95: =IF(J95-K95<0,J95-K95,0) -> 0 | Q95: =+J95-K95 -> 0 | R95: =+O95+P95 -> 0 | S95: =+Q95-R95 -> 0
F96: =IF(E96=0,0,G96/E96) -> 0 | I96: =IF(H96=0,0,J96/H96) -> 0 | K96: =+H96*N95 -> 0 | L96: =+L95+E96-H96 -> 0 | M96: =+M95+G96-K96 -> 0 | N96: =+IF(L96=0,0,M96/L96) -> 0 | O96: =IF(J96-K96>0,J96-K96,0) -> 0 | P96: =IF(J96-K96<0,J96-K96,0) -> 0 | Q96: =+J96-K96 -> 0 | R96: =+O96+P96 -> 0 | S96: =+Q96-R96 -> 0
F97: =IF(E97=0,0,G97/E97) -> 0 | I97: =IF(H97=0,0,J97/H97) -> 0 | K97: =+H97*N96 -> 0 | L97: =+L96+E97-H97 -> 0 | M97: =+M96+G97-K97 -> 0 | N97: =+IF(L97=0,0,M97/L97) -> 0 | O97: =IF(J97-K97>0,J97-K97,0) -> 0 | P97: =IF(J97-K97<0,J97-K97,0) -> 0 | Q97: =+J97-K97 -> 0 | R97: =+O97+P97 -> 0 | S97: =+Q97-R97 -> 0
A98: UE | F98: =IF(E98=0,0,G98/E98) -> 0 | I98: =IF(H98=0,0,J98/H98) -> 0 | K98: =+H98*N97 -> 0 | L98: =+L97+E98-H98 -> 0 | M98: =+M97+G98-K98 -> 0 | N98: =+IF(L98=0,0,M98/L98) -> 0 | O98: =IF(J98-K98>0,J98-K98,0) -> 0 | P98: =IF(J98-K98<0,J98-K98,0) -> 0 | Q98: =+J98-K98 -> 0 | R98: =+O98+P98 -> 0 | S98: =+Q98-R98 -> 0
A99: UE | B99: =B98 -> 0 | C99: Récap | D99: =+$K$1 -> 46022 | E99: =SUM(E93:E98) -> 0 | F99: =+IF(E99=0,0,G99/E99) -> 0 | G99: =SUM(G92:G98) -> 0 | H99: =SUM(H92:H98) -> 0 | I99: =+IF(H99=0,0,J99/H99) -> 0 | J99: =SUM(J92:J98) -> 0 | K99: =SUM(K92:K98) -> 0 | L99: =+L98 -> 0 | M99: =+M98 -> 0 | N99: =+IF(L99=0,0,M99/L99) -> 0 | O99: =SUM(O92:O98) -> 0 | P99: =SUM(P92:P98) -> 0 | Q99: =+J99-K99 -> 0 | R99: =+O99+P99 -> 0 | S99: =+Q99-R99 -> 0
A100: UE | C100: Report | Q100: =+J100-K100 -> 0 | R100: =+O100+P100 -> 0 | S100: =+Q100-R100 -> 0
A101: UE | F101: =IF(E101=0,0,G101/E101) -> 0 | I101: =IF(H101=0,0,J101/H101) -> 0 | K101: =+H101*N100 -> 0 | L101: =+L100+E101-H101 -> 0 | M101: =+M100+G101-K101 -> 0 | N101: =+IF(L101=0,0,M101/L101) -> 0 | O101: =IF(J101-K101>0,J101-K101,0) -> 0 | P101: =IF(J101-K101<0,J101-K101,0) -> 0 | Q101: =+J101-K101 -> 0 | R101: =+O101+P101 -> 0 | S101: =+Q101-R101 -> 0
A102: UE | F102: =IF(E102=0,0,G102/E102) -> 0 | I102: =IF(H102=0,0,J102/H102) -> 0 | K102: =+H102*N101 -> 0 | L102: =+L101+E102-H102 -> 0 | M102: =+M101+G102-K102 -> 0 | N102: =+IF(L102=0,0,M102/L102) -> 0 | O102: =IF(J102-K102>0,J102-K102,0) -> 0 | P102: =IF(J102-K102<0,J102-K102,0) -> 0 | Q102: =+J102-K102 -> 0 | R102: =+O102+P102 -> 0 | S102: =+Q102-R102 -> 0
A103: UE | F103: =IF(E103=0,0,G103/E103) -> 0 | I103: =IF(H103=0,0,J103/H103) -> 0 | K103: =+H103*N102 -> 0 | L103: =+L102+E103-H103 -> 0 | M103: =+M102+G103-K103 -> 0 | N103: =+IF(L103=0,0,M103/L103) -> 0 | O103: =IF(J103-K103>0,J103-K103,0) -> 0 | P103: =IF(J103-K103<0,J103-K103,0) -> 0 | Q103: =+J103-K103 -> 0 | R103: =+O103+P103 -> 0 | S103: =+Q103-R103 -> 0
...

Sheet Intérêts Obligations
B1: =Sommaire!A1 -> BOLZEN - SLP | F1: Intérêts courus sur obligations convertibles | I1: =+Sommaire!C1 -> 46022
B4: Inflexion BIDCO - OCADP 2 | H4: Capitalisation : 29/07
B5: Date debut période | C5: Date fin période | D5: Jours | E5: Base | F5: Mouvement | G5: Capitalisation | H5: Base de calcul | I5: Taux fixe ou marge | J5: Taux variable : Euribor X mois | K5: Dividendes / coupons | L5: Intérêts courus
B7: 45867 | C7: 45930 | D7: =+C7-B7 -> 63 | E7: 365 | F7: 40320000 | H7: =+H6+F7+G7 -> 40320000 | I7: 0.1 | K7: =ROUND((H7*D7*(I7+J7))/E7,2) -> 695934.25 | L7: =+K7 -> 695934.25
B8: =C7 -> 45930 | C8: 46022 | D8: =+C8-B8 -> 92 | E8: 365 | H8: =+H7+F8+G8 -> 40320000 | I8: 0.1 | K8: =ROUND((H8*D8*(I8+J8))/E8,2) -> 1016284.9 | L8: =+K8 -> 1016284.9
B21: Total | F21: =SUM(F6:F20) -> 40320000 | G21: =SUM(G7:G20) -> 0 | H21: =+VLOOKUP($I$1,C5:H20,6,FALSE) -> 40320000 | K21: =SUM(K6:K20) -> 1712219.2 | L21: =SUM(L6:L20) -> 1712219.2
B22: échéance 29/01/2033 | J22: Provision | K22: 0 | L22: =K22*L21 -> 0
L23: =L21-L22 -> 1712219.2
B27: Koenig - ADP B | H27: Capitalisation : 27/11
B28: Date debut période | C28: Date fin période | D28: Jours | E28: Base | F28: Mouvement | G28: Capitalisation | H28: Base de calcul | I28: Taux fixe ou marge | J28: Taux variable : Euribor X mois | K28: Dividendes / coupons | L28: Intérêts courus
B30: 45988 | C30: 46022 | D30: =+C30-B30 -> 34 | E30: 360 | F30: 8720000 | H30: =+H29+F30+G30 -> 8720000 | I30: 0.11 | K30: =ROUND((H30*D30*(I30+J30))/E30,2) -> 90591.11 | L30: =+K30 -> 90591.11
B44: Total | F44: =SUM(F29:F43) -> 8720000 | G44: =SUM(G30:G43) -> 0 | H44: =+VLOOKUP($I$1,C28:H43,6,FALSE) -> 8720000 | K44: =SUM(K29:K43) -> 90591.11 | L44: =SUM(L29:L43) -> 90591.11
J45: Provision | K45: 0 | L45: =K45*L44 -> 0
L46: =L44-L45 -> 90591.11
B52: Koenig - OC (SHL) | H52: Capitalisation : 25/11
B53: Date debut période | C53: Date fin période | D53: Jours | E53: Base | F53: Mouvement | G53: Capitalisation | H53: Base de calcul | I53: Taux fixe ou marge | J53: Taux variable : Euribor X mois | K53: Dividendes / coupons | L53: Intérêts courus
B55: 45986 | C55: 46022 | D55: =+C55-B55 -> 36 | E55: 365 | F55: 26160000 | H55: =+H54+F55+G55 -> 26160000 | I55: 0 | K55: =ROUND((H55*D55*(I55+J55))/E55,2) -> 0 | L55: =+K55 -> 0
F57: Pas de calcul d'intérêts
B60: Total | F60: =SUM(F54:F59) -> 26160000 | G60: =SUM(G55:G59) -> 0 | H60: =+VLOOKUP($I$1,C53:H59,6,FALSE) -> 26160000 | K60: =SUM(K54:K59) -> 0 | L60: =SUM(L54:L59) -> 0
J61: Provision | K61: 0 | L61: =K61*L60 -> 0
B62: Taux d'intérêts : 0% | L62: =L60-L61 -> 0
B67: Koenig - OC (Warehouse II - ADP A) | H67: Capitalisation : 25/11
B68: Date debut période | C68: Date fin période | D68: Jours | E68: Base | F68: Mouvement | G68: Capitalisation | H68: Base de calcul | I68: Taux fixe ou marge | J68: Taux variable : Euribor X mois | K68: Dividendes / coupons | L68: Intérêts courus
B70: 45986 | C70: 46022 | D70: =+C70-B70 -> 36 | E70: 365 | F70: 500000 | H70: =+H69+F70+G70 -> 500000 | K70: =ROUND((H70*D70*(I70+J70))/E70,2) -> 0 | L70: =+K70 -> 0
F72: Pas de calcul d'intérêts
B75: Total | F75: =SUM(F69:F74) -> 500000 | G75: =SUM(G70:G74) -> 0 | H75: =+VLOOKUP($I$1,C68:H74,6,FALSE) -> 500000 | K75: =SUM(K69:K74) -> 0 | L75: =SUM(L69:L74) -> 0
J76: Provision | K76: 0 | L76: =K76*L75 -> 0
B77: Maturité : 31/12/2038 | L77: =L75-L76 -> 0
B78: Taux d'intérêts: 0%
B81: SNIC - OBSA | H81: Capitalisation : 17/12
B82: Date debut période | C82: Date fin période | D82: Jours | E82: Base | F82: Mouvement | G82: Capitalisation | H82: Base de calcul | I82: Taux fixe ou marge | J82: Taux variable : Euribor X mois | K82: Dividendes / coupons | L82: Intérêts courus
B84: 46008 | C84: 46022 | D84: =+C84-B84 -> 14 | E84: 360 | F84: 63750000 | H84: =+H83+F84+G84 -> 63750000 | I84: 0.1 | K84: =ROUND((H84*D84*(I84+J84))/E84,2) -> 247916.67 | L84: =+K84 -> 247916.67
B98: Total | F98: =SUM(F83:F97) -> 63750000 | G98: =SUM(G84:G97) -> 0 | H98: =+VLOOKUP($I$1,C82:H97,6,FALSE) -> 63750000 | K98: =SUM(K83:K97) -> 247916.67 | L98: =SUM(L83:L97) -> 247916.67
J99: Provision | K99: 0 | L99: =K99*L98 -> 0
B100: Date de maturité: 16/12/2033 | L100: =L98-L99 -> 247916.67
G104: Récap intérêt Obligations | H104: Inventaire | I104: Ecart | J104: Contrôle
F105: Intérêts Capitalisés | G105: =G21+G44+G60+G75 -> 0 | H105: =ROUND(SUMIF(Inventaire!B15:B83,"??OS*",Inventaire!I15:I83)+SUMIF(Inventaire!B15:B83,"??OR*",Inventaire!I15:I83)+SUMIF(Inventaire!B15:B83,"??CN*",Inventaire!I15:I83)+SUMIF(Inventaire!B12:B79,"??OC*",Inventaire!I12:I79),2) -> 0 | I105: =G105-H105 -> 0 | J105: =IF(ROUND(I105,2)=0,"OK","ANOMALIE") -> OK
F106: Intérêts Courus | G106: =L23+L46+L62+L77+L100 -> 2050727 | H106: =SUMIF(Inventaire!B15:B83,"??OS*",Inventaire!M15:M83)+SUMIF(Inventaire!B15:B83,"??OR*",Inventaire!M15:M83)+SUMIF(Inventaire!B15:B83,"??CN*",Inventaire!M15:M83)+SUMIF(Inventaire!B12:B79,"??OC*",Inventaire!M12:M79)+SUMIF(Inventaire!B15:B83,"??AD*",Inventaire!M15:M83) -> 2050727 | I106: =G106-H106 -> 0 | J106: =IF(ROUND(I106,2)=0,"OK","ANOMALIE") -> OK

Sheet Emprunt
B1: =Sommaire!A1 -> BOLZEN - SLP | G1: COMPTE COURANT AU | I1: =Sommaire!C1 -> 46022
B3: Emprunt - Facility agrement loan n°1
B4: Date de début de période | C4: Date de fin de période | D4: Durée | E4: Base | F4: Intitulé | G4: Mouvements | H4: Solde progressif | I4: marge | J4: Taux Euribor | K4: Intérêts | L4: Intérêt payé | M4: Intérêts courus
B6: 45862 | C6: 45930 | D6: =C6-B6 -> 68 | E6: 360 | F6: Tirage | G6: 50400000 | H6: =H5+G6 -> 50400000 | I6: 0.018 | J6: 0.02032 | K6: =ROUND((D6*(I6+J6)*H6)/E6,2) -> 364806.4 | M6: =K6+L6 -> 364806.4
B7: =C6 -> 45930 | C7: 46020 | D7: =C7-B7 -> 90 | E7: 360 | H7: =H6+G7 -> 50400000 | I7: 0.018 | J7: 0.02032 | K7: =ROUND((D7*(I7+J7)*H7)/E7,2) -> 482832 | M7: =K7+L7 -> 482832
F9: Remboursements | G9: -50400000 | K9: -847638.4 | M9: -847638.4
G16: =SUM(G5:G15) -> 0 | K16: =SUM(K6:K15) -> 0 | M16: =SUM(M6:M15) -> 0
B18: Maturité | D18: 46048
B19: intérêt au 26/01/2026 : | D19: 997852.8
B20: Mage: | D20: 0.018
B21: Montant emprunté | D21: =G16 -> 0
B22: Emprunt - Commiment fee loan n°1
B23: Date de début de période | C23: Date de fin de période | D23: Durée | E23: Base | F23: Intitulé | G23: Mouvements | H23: Solde progressif | I23: Taux appliqué | J23: Intérêts | K23: Intérêts courus
B25: 45862 | C25: 45930 | D25: =C25-B25 -> 68 | E25: 360 | F25: Commission de non utilisation | G25: =D21-G16 -> 0 | H25: =G25+H24 -> 0 | I25: 0.003 | J25: =ROUND((D25*(I25)*H25)/E25,2) -> 0
B26: =C25 -> 45930 | C26: 46020 | D26: =C26-B26 -> 90 | E26: 360 | H26: =G26+H25 -> 0 | I26: 0.003 | J26: =ROUND((D26*(I26)*H26)/E26,2) -> 0
G43: =G29 -> 0 | H43: =+H29 -> 0 | J43: =SUM(J25:J42) -> 0 | K43: =SUM(K25:K32) -> 0
B52: Emprunt - Facility agrement loan n°3
B53: Date de début de période | C53: Date de fin de période | D53: Durée | E53: Base | F53: Intitulé | G53: Mouvements | H53: Solde progressif | I53: marge | J53: Taux Euribor | K53: Intérêts | L53: Intérêt payé | M53: Intérêts courus
B55: 45982 | C55: 46020 | D55: =C55-B55 -> 38 | E55: 360 | F55: Tirage | G55: 35380000 | H55: =H54+G55 -> 35380000 | I55: 0.018 | J55: 0.021 | K55: =ROUND((D55*(I55+J55)*H55)/E55,2) -> 145647.67 | M55: =K55+L55 -> 145647.67
F57: Remboursement | G57: -35380000 | K57: -145647.67 | M57: -145647.67
G65: =SUM(G54:G64) -> 0 | K65: =SUM(K55:K64) -> 0 | M65: =SUM(M55:M64) -> 0
B67: Maturité | D67: 46346
B68: intérêt au 30/03/2026 : | D68: 494435.5
B69: Mage: | D69: 0.018
B70: Montant emprunté | D70: =G65 -> 0
B71: Emprunt - Commiment fee loan n°3
B72: Date de début de période | C72: Date de fin de période | D72: Durée | E72: Base | F72: Intitulé | G72: Mouvements | H72: Solde progressif | I72: Taux appliqué | J72: Intérêts | K72: Intérêts courus
B74: 45982 | C74: 46020 | D74: =C74-B74 -> 38 | E74: 360 | F74: Commission de non utilisation | G74: =D70-G65 -> 0 | H74: =G74+H73 -> 0 | I74: 0.003 | J74: =ROUND((D74*(I74)*H74)/E74,2) -> 0
G92: =G78 -> 0 | H92: =+H78 -> 0 | J92: =SUM(J74:J91) -> 0 | K92: =SUM(K74:K81) -> 0
B100: Emprunt - Facility agrement loan n°5
B101: Date de début de période | C101: Date de fin de période | D101: Durée | E101: Base | F101: Intitulé | G101: Mouvements | H101: Solde progressif | I101: marge | J101: Taux Euribor | K101: Intérêts | L101: Intérêt payé | M101: Intérêts courus
B103: 46006 | C103: 46022 | D103: =C103-B103 -> 16 | E103: 360 | F103: Tirage | G103: 57750000 | H103: =H102+G103 -> 57750000 | I103: 0.018 | J103: 0.02182 | K103: =ROUND((D103*(I103+J103)*H103)/E103,2) -> 102204.67 | M103: =K103+L103 -> 102204.67
G113: =SUM(G102:G112) -> 57750000 | K113: =SUM(K103:K112) -> 102204.67 | M113: =SUM(M103:M112) -> 102204.67
B115: Maturité | D115: 30/06/2026 (197 jours)
B116: intérêt au 30/06/2026 : | D116: 1258395
B117: Mage: | D117: 0.018
B118: Montant emprunté | D118: 57750000
B119: Emprunt - Commiment fee loan n°5
B120: Date de début de période | C120: Date de fin de période | D120: Durée | E120: Base | F120: Intitulé | G120: Mouvements | H120: Solde progressif | I120: Taux appliqué | J120: Intérêts | K120: Intérêts courus
B122: 46006 | C122: 46022 | D122: =C122-B122 -> 16 | E122: 360 | F122: Commission de non utilisation | G122: =D118-G113 -> 0 | H122: =G122+H121 -> 0 | I122: 0.003 | J122: =ROUND((D122*(I122)*H122)/E122,2) -> 0
G135: =G126 -> 0 | H135: =+H126 -> 0 | J135: =SUM(J122:J134) -> 0 | K135: =SUM(K122:K127) -> 0
B141: Emprunt - Facility agrement loan n°6
B142: Date de début de période | C142: Date de fin de période | D142: Durée | E142: Base | F142: Intitulé | G142: Mouvements | H142: Solde progressif | I142: marge | J142: Taux Euribor | K142: Intérêts | L142: Intérêt payé | M142: Intérêts courus
B144: 46006 | C144: 46022 | D144: =C144-B144 -> 16 | E144: 360 | F144: Tirage | G144: 6000000 | H144: =H143+G144 -> 6000000 | I144: 0.018 | J144: 0.021 | K144: =ROUND((D144*(I144+J144)*H144)/E144,2) -> 10400 | M144: =K144+L144 -> 10400
G154: =SUM(G143:G153) -> 6000000 | K154: =SUM(K144:K153) -> 10400 | M154: =SUM(M144:M153) -> 10400
B156: Maturité | D156: 16/03/2026 (91 jours)
B157: intérêt au 16/03/2026 : | D157: 59150
B158: Mage: | D158: 0.018
B159: Montant emprunté | D159: 6000000
B160: Emprunt - Commiment fee loan n°6
B161: Date de début de période | C161: Date de fin de période | D161: Durée | E161: Base | F161: Intitulé | G161: Mouvements | H161: Solde progressif | I161: Taux appliqué | J161: Intérêts | K161: Intérêts courus
B163: 46006 | C163: 46022 | D163: =C163-B163 -> 16 | E163: 360 | F163: Commission de non utilisation | G163: =D159-G154 -> 0 | H163: =G163+H162 -> 0 | I163: 0.003 | J163: =ROUND((D163*(I163)*H163)/E163,2) -> 0
G176: =G167 -> 0 | H176: =+H167 -> 0 | J176: =SUM(J163:J175) -> 0 | K176: =SUM(K163:K168) -> 0
J186: Intérêts courus | K186: =+K43+M16+M65+K92+M113+K135+M154+K176 -> 112604.67
J187: Emprunt | K187: =+G16+G65+G113+G154 -> 63750000

Sheet Sous rachat
B1: =Sommaire!A1 -> BOLZEN - SLP | E1: Suivi des parts au | F1: =Sommaire!C1 -> 46022
B2: =Sommaire!B30 -> Euro
D4: Nature opération
B5: Nominal Parts A1 | C5: 1000 | D5: NP | E5: Transfert de Parts
B6: Nominal Parts A2 | C6: 1000 | D6: ADF | E6: Appel de fonds
B7: Nominal Parts Commandité | C7: 1000 | D7: DD | E7: Distribution définitive
D8: DB | E8: Distribition Bloquée
D9: DP | E9: Distribution provisoire
D10: RD | E10: Rappel de distribution
D11: ENG | E11: Engagement supplémentaire
E13: Date opération | G13: 46020 | H13: 46020
E14: %ADF | G14: 0.002 | H14: 0.09223237
E15: Nature opération | F15: NP | G15: ADF | H15: ADF
J17: =F1 -> 46022 | U17: Matrice intégration appel de Fonds / Distribution
B18: Souscripteurs | C18: Nature des Souscripteurs | E18: Engagement initial en Euros | F18: Nombre de parts | G18: ADF | H18: ADF Tranche différée | J18: Nombre de parts à date de situation | K18: Total des versements à date de situation | L18: Montant libéré en % | M18: Engagement résiduel | N18: Distribution | O18: Distribution en % | P18: Engagement à date de situation
B19: Nominal 1000 € | D19: Parts A1
U20: DATE | V20: Compte | W20: Libellé | X20: montant
B21: EMZ 11-A SLP | D21: A1 | E21: =300000000+3040500 -> 303040500 | F21: 303040.5 | G21: 606081 | H21: 27950144 | J21: =+SUMIF($F$15:$I$15,"NP",$F21:$I21) -> 303040.5 | K21: =+SUMIF($F$15:$I$15,"ADF",$F21:$I21) -> 28556225 | L21: =IFERROR(K21/P21,0) -> 0.09423237 | M21: =P21-K21 -> 2.7448428e+08 | N21: =+SUMIF($F$15:$I$15,"DD",$F21:$I21)+SUMIF($F$15:$I$15,"DB",$F21:$I21)+SUMIF($F$15:$I$15,"DP",$F21:$I21)-SUMIF($F$15:$I$15,"RD",$F21:$I21) -> 0 | O21: =N21/P21 -> 0 | P21: =$C$5*J21 -> 303040500 | U21: =#REF! -> #REF! | V21: 10211001 | W21: =CONCATENATE(#REF!," - ",B21) -> #REF! | X21: =#REF! -> #REF!
B22: EMZ 11 Executive Fund SLP | D22: A1 | E22: 17210000 | F22: 17210 | G22: 34420 | H22: 1587319.1 | J22: =+SUMIF($F$15:$I$15,"NP",$F22:$I22) -> 17210 | K22: =+SUMIF($F$15:$I$15,"ADF",$F22:$I22) -> 1621739.1 | L22: =IFERROR(K22/P22,0) -> 0.09423237 | M22: =P22-K22 -> 15588261 | N22: =+SUMIF($F$15:$I$15,"DD",$F22:$I22)+SUMIF($F$15:$I$15,"DB",$F22:$I22)+SUMIF($F$15:$I$15,"DP",$F22:$I22)-SUMIF($F$15:$I$15,"RD",$F22:$I22) -> 0 | O22: =N22/P22 -> 0 | P22: =$C$5*J22 -> 17210000 | U22: =#REF! -> #REF! | V22: 10211001 | W22: =CONCATENATE(#REF!," - ",B22) -> #REF! | X22: =#REF! -> #REF!
B23: EMZ 11 SLP | D23: A1 | E23: =20446889+35308098.7+346052112.34+155000000+1564699.96+64646400 -> 623018200 | F23: =E23/1000 -> 623018.2 | G23: 1246036.4 | H23: 57462445 | J23: =+SUMIF($F$15:$I$15,"NP",$F23:$I23) -> 623018.2 | K23: =+SUMIF($F$15:$I$15,"ADF",$F23:$I23) -> 58708482 | L23: =IFERROR(K23/P23,0) -> 0.09423237 | M23: =P23-K23 -> 5.6430972e+08 | N23: =+SUMIF($F$15:$I$15,"DD",$F23:$I23)+SUMIF($F$15:$I$15,"DB",$F23:$I23)+SUMIF($F$15:$I$15,"DP",$F23:$I23)-SUMIF($F$15:$I$15,"RD",$F23:$I23) -> 0 | O23: =N23/P23 -> 0 | P23: =$C$5*J23 -> 623018200 | U23: =#REF! -> #REF! | V23: 10211001 | W23: =CONCATENATE(#REF!," - ",B23) -> #REF! | X23: =#REF! -> #REF!
B27: Total Parts A1 | E27: =SUM(E19:E26) -> 943268700 | F27: =SUM(F19:F26) -> 943268.7 | G27: =SUM(G19:G26) -> 1886537.4 | H27: =SUM(H19:H26) -> 86999908 | J27: =SUM(J21:J24) -> 943268.7 | K27: =SUM(K21:K24) -> 88886445 | L27: =K27/P27 -> 0.09423237 | M27: =SUM(M21:M24) -> 8.5438225e+08 | P27: =SUM(P21:P24) -> 943268700
B29: Nominal 1000 € | D29: Parts A2
D31: A2 | J31: =+SUMIF($F$16:$I$16,"NP",$F31:$I31) -> 0 | K31: =+SUMIF($F$15:$I$15,"ADF",$F31:$I31) -> 0 | L31: =IFERROR(K31/P31,0) -> 0 | M31: =P31-K31 -> 0 | N31: =+SUMIF($F$15:$I$15,"DD",$F31:$I31)+SUMIF($F$15:$I$15,"DB",$F31:$I31)+SUMIF($F$15:$I$15,"DP",$F31:$I31)-SUMIF($F$15:$I$15,"RD",$F31:$I31) -> 0 | O31: =N31/P31 -> #DIV/0! | P31: =$C$6*J31 -> 0 | U31: =#REF! -> #REF! | V31: 10211002 | W31: =CONCATENATE(#REF!," - ",B31) -> #REF! | X31: =#REF! -> #REF!
D32: A2 | J32: =+SUMIF($F$16:$I$16,"NP",$F32:$I32) -> 0 | K32: =+SUMIF($F$15:$I$15,"ADF",$F32:$I32) -> 0 | L32: =IFERROR(K32/P32,0) -> 0 | M32: =P32-K32 -> 0 | N32: =+SUMIF($F$15:$I$15,"DD",$F32:$I32)+SUMIF($F$15:$I$15,"DB",$F32:$I32)+SUMIF($F$15:$I$15,"DP",$F32:$I32)-SUMIF($F$15:$I$15,"RD",$F32:$I32) -> 0 | O32: =N32/P32 -> #DIV/0! | P32: =$C$6*J32 -> 0 | U32: =#REF! -> #REF! | V32: 10211002 | W32: =CONCATENATE(#REF!," - ",B32) -> #REF! | X32: =#REF! -> #REF!
D33: A2 | J33: =+SUMIF($F$16:$I$16,"NP",$F33:$I33) -> 0 | K33: =+SUMIF($F$15:$I$15,"ADF",$F33:$I33) -> 0 | L33: =IFERROR(K33/P33,0) -> 0 | M33: =P33-K33 -> 0 | N33: =+SUMIF($F$15:$I$15,"DD",$F33:$I33)+SUMIF($F$15:$I$15,"DB",$F33:$I33)+SUMIF($F$15:$I$15,"DP",$F33:$I33)-SUMIF($F$15:$I$15,"RD",$F33:$I33) -> 0 | O33: =N33/P33 -> #DIV/0! | P33: =$C$6*J33 -> 0 | U33: =#REF! -> #REF! | V33: 10211002 | W33: =CONCATENATE(#REF!," - ",B33) -> #REF! | X33: =#REF! -> #REF!
D34: A2 | J34: =+SUMIF($F$16:$I$16,"NP",$F34:$I34) -> 0 | K34: =+SUMIF($F$15:$I$15,"ADF",$F34:$I34) -> 0 | L34: =IFERROR(K34/P34,0) -> 0 | M34: =P34-K34 -> 0 | N34: =+SUMIF($F$15:$I$15,"DD",$F34:$I34)+SUMIF($F$15:$I$15,"DB",$F34:$I34)+SUMIF($F$15:$I$15,"DP",$F34:$I34)-SUMIF($F$15:$I$15,"RD",$F34:$I34) -> 0 | O34: =N34/P34 -> #DIV/0! | P34: =$C$6*J34 -> 0 | U34: =#REF! -> #REF! | V34: 10211002 | W34: =CONCATENATE(#REF!," - ",B34) -> #REF! | X34: =#REF! -> #REF!
B37: Total Parts A2 | E37: =SUM(E28:E36) -> 0 | F37: =SUM(F28:F36) -> 0 | H37: =SUM(H28:H36) -> 0 | J37: =SUM(J31:J34) -> 0 | K37: =SUM(K31:K34) -> 0 | L37: =K37/P37 -> #DIV/0! | M37: =SUM(M31:M34) -> 0 | P37: =SUM(P31:P34) -> 0
B39: Nominal 1000 €
B41: EMZ 11 GP | D41: Parts de Commandité | E41: 1000 | F41: 1 | G41: 2 | H41: =H14*E41 -> 92.23237 | J41: =+SUMIF($F$15:$I$15,"NP",$F41:$I41) -> 1 | K41: =+SUMIF($F$15:$I$15,"ADF",$F41:$I41) -> 94.23237 | L41: =IFERROR(K41/P41,0) -> 0.09423237 | M41: =P41-K41 -> 905.76763 | N41: =+SUMIF($F$15:$I$15,"DD",$F41:$I41)+SUMIF($F$15:$I$15,"DB",$F41:$I41)+SUMIF($F$15:$I$15,"DP",$F41:$I41)-SUMIF($F$15:$I$15,"RD",$F41:$I41) -> 0 | O41: =N41/P41 -> 0 | P41: =$C$7*J41 -> 1000 | U41: =#REF! -> #REF! | V41: 10213000 | W41: =CONCATENATE(#REF!," - ",B41) -> #REF! | X41: =#REF! -> #REF!
U42: =#REF! -> #REF! | V42: 10213000 | W42: =CONCATENATE(#REF!," - ",B42) -> #REF! | X42: =#REF! -> #REF!
U43: =#REF! -> #REF! | V43: 10213000 | W43: =CONCATENATE(#REF!," - ",B43) -> #REF! | X43: =#REF! -> #REF!
B45: Total Parts Commandité | E45: =SUM(E39:E44) -> 1000 | F45: =SUM(F39:F44) -> 1 | G45: =SUM(G39:G44) -> 2 | H45: =SUM(H39:H44) -> 92.23237 | J45: =SUM(J41:J43) -> 1 | K45: =SUM(K41:K43) -> 94.23237 | L45: =K45/P45 -> 0.09423237 | M45: =SUM(M41:M43) -> 905.76763 | N45: =SUM(N41:N43) -> 0 | O45: =SUM(O41:O43) -> 0 | P45: =SUM(P41:P43) -> 1000
B47: TOTAL FONDS (A1 + A2 + Commandité) | E47: =E45+E37+E27 -> 943269700 | F47: =F45+F37+F27 -> 943269.7 | G47: =G45+G37+G27 -> 1886539.4 | H47: =H45+H37+H27 -> 87000000 | J47: =J45+J37+J27 -> 943269.7 | K47: =K45+K37+K27 -> 88886539 | L47: =K47/P47 -> 0.09423237 | M47: =M45+M37+M27 -> 8.5438316e+08 | N47: =N45+N37+N27 -> 0 | O47: =O45+O37+O27 -> 0 | P47: =P45+P37+P27 -> 943269700

Sheet Liste porteurs selon versement 
B1: =Inventaire!B1 -> BOLZEN - SLP | D1: Liste des porteurs | F1: =Sommaire!C1 -> 46022 | H1: %age investisseurs
H2: =+SUMIF(A10:A15,"<="&5,D10:D15)/D7 -> 1
C3: Type de parts | D3: Nbre de parts | E3: VL
C4: A1 | D4: ='Calcul VL'!C8 -> 943268.7 | E4: =Inventaire!F9 -> 95.480211
C5: A2 | D5: ='Calcul VL'!C9 -> 0 | E5: =Inventaire!G9 -> 0
C6: Parts de Commandité | D6: ='Calcul VL'!C10 -> 1 | E6: =Inventaire!H9 -> 95.480211
C7: Total | D7: =SUM(D4:D6) -> 943269.7
B9: Souscripteurs | C9: Type de parts | D9: Nb de parts soucrites | E9: Valeur unitaire | F9: Evaluation
A10: =IFERROR(RANK(F10,F$10:F$15,),"") -> 2 | B10: ='Sous rachat'!B21 -> EMZ 11-A SLP | C10: =+IF($B10="","",VLOOKUP($B10,'Sous rachat'!B$4:D119,(3),0)) -> A1 | D10: =+IF($B10="","",VLOOKUP($B10,'Sous rachat'!$B$3:$R$191,(9),0)) -> 303040.5 | E10: =+VLOOKUP(C10,$C$3:$E$6,1+2,0) -> 95.480211 | F10: =D10*E10 -> 28934371
A11: =IFERROR(RANK(F11,F$10:F$15,),"") -> 3 | B11: ='Sous rachat'!B22 -> EMZ 11 Executive Fund SLP | C11: =+IF($B11="","",VLOOKUP($B11,'Sous rachat'!B$4:D120,(3),0)) -> A1 | D11: =+IF($B11="","",VLOOKUP($B11,'Sous rachat'!$B$3:$R$191,(9),0)) -> 17210 | E11: =+VLOOKUP(C11,$C$3:$E$6,1+2,0) -> 95.480211 | F11: =D11*E11 -> 1643214.4
A12: =IFERROR(RANK(F12,F$10:F$15,),"") -> 1 | B12: ='Sous rachat'!B23 -> EMZ 11 SLP | C12: =+IF($B12="","",VLOOKUP($B12,'Sous rachat'!B$4:D121,(3),0)) -> A1 | D12: =+IF($B12="","",VLOOKUP($B12,'Sous rachat'!$B$3:$R$191,(9),0)) -> 623018.2 | E12: =+VLOOKUP(C12,$C$3:$E$6,1+2,0) -> 95.480211 | F12: =D12*E12 -> 59485909
A14: =IFERROR(RANK(F14,F$10:F$15,),"") -> 4 | B14: ='Sous rachat'!B41 -> EMZ 11 GP | C14: =+IF($B14="","",VLOOKUP($B14,'Sous rachat'!B$4:D198,(3),0)) -> Parts de Commandité | D14: =+IF($B14="","",VLOOKUP($B14,'Sous rachat'!$B$3:$R$191,(9),0)) -> 1 | E14: =+VLOOKUP(C14,$C$3:$E$6,1+2,0) -> 95.480211 | F14: =D14*E14 -> 95.480211
D15: =+IF($B15="","",VLOOKUP($B15,#REF!,(43),0))
F16: =SUM(F10:F15) -> 90063590
C18: Nombre de parts | D18: =SUM(D10:D15) -> 943269.7 | E18: =+IF(D18=F23,"OK","Anomalie") -> OK
D20: Actif net selon inventaire | F20: =+Inventaire!C8 -> 90063591
D22: Actif net non affecté | F22: =+F20-SUM(F10:F15) -> 0.8040933
D23: Nombre de parts | F23: =SUM(D4:D6) -> 943269.7
D24: Ecart/part | F24: =+F22/F23 -> 8.5245323e-07
D25: Conclusion | F25: =IF(ABS(F24)<0.01,"OK","ANOMALIE") -> OK

Sheet Frais de gestion
B1: =+Inventaire!B1 -> BOLZEN - SLP | D1: Frais de gestion | J1: =Sommaire!C1 -> 46022
B4: Frais de gestion de la société de gestion | C4: Date de départ | D4: Fin de période | E4: Prorata | G4: Taux de frais de gestion | H4: Base de calcul | J4: Charges | K4: Contrôle
B5: Rémunération de la société de gestion (Article 20.1)
B6: Pas de commission de gestion
B9: Sous-total frais de gestion de la société de gestion | J9: =ROUND(SUM(J6:J8),2) -> 0 | K9: =ROUND(SUM(K6:K8),2) -> 0
B12: Autres frais de gestion | C12: Taux ou montant | D12: Taux proratisé | E12: TVA | H12: Base de calcul | J12: Charges
B13: Rémunération Associé Commandité | C13: date départ | D13: date fin
B14: Budget maximum 20 000€ | C14: 45726 | D14: 46022 | F14: nbre j
B16: Provision 2024 | C16: 630.25 | D16: 1 | E16: 1.2 | F16: 0 | I16: =+ROUND(E16*D16*C16,2) -> 756.3 | J16: =+I16 -> 756.3
B17: Provision 2025 | C17: 630.25 | D17: 1 | E17: 1.2 | F17: 0 | I17: =+ROUND(E17*D17*C17,2) -> 756.3 | J17: =+I17 -> 756.3
C19: =C20/1.2 -> 1260.4917 | J19: =SUM(J16:J17) -> 1512.6
B20: Honoraires CAC - Deloitte | C20: 1512.59
B21: Budget annuel HT (8500€) du budget annuel HT
B22: Provision 3T2025 | C22: 8500 | D22: 0.25 | E22: 1.2 | I22: =+C22*D22*E22 -> 2550 | J22: =I22 -> 2550
B23: Provision 4T2025 | C23: =(4760*2) -> 9520 | D23: 0.25 | E23: 1.2 | I23: =+C23*D23*E23 -> 2856 | J23: =I23 -> 2856
B24: Régul provision 3T2025 | J24: 306
J26: =SUM(J22:J25) -> 5712
B27: Honoraires comptables - Aplitec
B28: Frais annuel HT 11 800 €)
B30: Facture Frais de démarrage | J30: 1100
B31: Facture frais de démarrage AIFM | J31: 200
B33: Facture EC 3T2025 | C33: 11800 | D33: 0.25 | E33: 1 | I33: =+ROUND(C33*D33,2) -> 2950 | J33: =I33 -> 2950
B34: Facture AIFM 3T2025 | C34: 644 | D34: 0.25 | E34: 1 | I34: =+ROUND(C34*D34,2) -> 161 | J34: =I34 -> 161
B35: Facture BDF OPC 2 3T2025 | C35: 440 | D35: 0.25 | E35: 1 | I35: =+ROUND(C35*D35,2) -> 110 | J35: =I35 -> 110
B36: Facture Dépôt VL (semestriel) Base GECO AMF 3T2025 | C36: 280 | D36: 0.25 | E36: 1 | I36: =+ROUND(C36*D36,2) -> 70 | J36: =I36 -> 70
B38: Provision EC 4T2025 | C38: 11800 | D38: 0.25 | E38: 1 | I38: =+ROUND(C38*D38,2) -> 2950 | J38: =I38 -> 2950
B39: Provision AIFM 4T2025 | C39: 644 | D39: 0.25 | E39: 1 | I39: =+ROUND(C39*D39,2) -> 161 | J39: =I39 -> 161
B40: Provision BDF OPC 2 4T2025 | C40: 440 | D40: 0.25 | E40: 1 | I40: =+ROUND(C40*D40,2) -> 110 | J40: =I40 -> 110
B41: Provision Dépôt VL (semestriel) Base GECO AMF 4T2025 | C41: 280 | D41: 0.25 | E41: 1 | I41: =+ROUND(C41*D41,2) -> 70 | J41: =I41 -> 70
J46: =SUM(J30:J43) -> 7882 | L46: Actif net
B47: Frais de dépositaire | L47: =Inventaire!C7 -> 90063591
D48: A réutiliser chaque trimestre
B49: Commission dépositaire barême: | C49: Taux | D49: Actif Net | G49: Base de calcul
B50: De 0 à 100M€ d'actif net | C50: 0.00025 | D50: 100000000 | G50: =C50*D50 -> 25000
B51: De 100M€ à 200M€ d'actif net | C51: 0.0002 | D51: 100000000 | G51: =C51*D51 -> 20000
B52: Au-delà de 200M€ d'actif net | C52: 7e-05 | D52: =H61-200000000 -> -1.0993641e+08 | G52: =C52*D52 -> -7695.5486
D53: =SUM(D50:D52) -> 90063591 | G53: =ROUND(SUM(G50:G52),2) -> 37304.45
B54: Minimum annuel de facturation | D54: =IF(D53=H61,"OK","ANOMALIE") -> OK
B55: Jusqu'à 50 investisseurs | C55: 15000
B56: De 51 à 100 investisseurs | C56: 17500
B57: De 101 à 200 investisseurs | C57: 20000
B61: Frais 3T2020 | C61: =H61 -> 90063591 | D61: =C50 -> 0.00025 | E61: 1.2 | G61: Actif Net du fonds | H61: =Inventaire!D74 -> 90063591 | I61: 0
B62: Forfait annuel minimum | C62: 15000 | E62: 1.2 | I62: =+ROUND(C62*D62*E62,2) -> 0
B63: Forfait AIFM | E63: 1.2 | I63: =+ROUND(C63*D63*E63,2) -> 0
B65: Frais 4T2020 | E65: 1.2 | G65: Actif Net du fonds | I65: =ROUND(C65*D65*E65,2) -> 0
B66: Forfait annuel minimum | E66: 1.2 | I66: =+ROUND(C66*D66*E66,2) -> 0
B67: Forfait AIFM | E67: 1.2 | I67: =+ROUND(C67*D67*E67,2) -> 0
E69: 1.2 | G69: Actif Net du fonds | I69: =ROUND(C69*D69*E69,2) -> 0
E70: 1.2 | I70: =+ROUND(C70*D70*E70,2) -> 0
E71: 1.2
E73: 1.2 | G73: Actif Net du fonds | I73: =ROUND(C73*D73*E73,2) -> 0
E74: 1.2 | I74: =+ROUND(C74*D74*E74,2) -> 0
E75: 1.2 | I75: =+ROUND(C75*D75*E75,2) -> 0
B76: Budget minimum 20 000 HT par an plafond 170 000€
B77: Minimum de facturation | C77: 20000 | D77: =D14-C14 -> 296 | E77: 1.2 | G77: =ROUND((C77*D77*E77)/365,2) -> 19463.01
B78: Actif net jusqu'à 500M€ 0,012% de l'actif net | C78: =IF(L47>500000000,500000000,L47) -> 90063591 | D78: 296 | E78: 1.2 | F78: 0.00012 | G78: =ROUND((C78*F78*E78*D78)/365,2) -> 10517.45
B79: Actif net entre 500M€ et 1 Milliard€ 0,010% de l'actif net | C79: =IF(1000000000>L47>500000000,L47-C78,0) -> 0 | E79: 1.2 | F79: 0.0001 | G79: =ROUND(C79*F79*E79,2) -> 0
B80: Actif net > 1Milliard€ 0,008% de l'actif net | C80: =IF(L47>1000000000,L47-C79-C78,0) -> 0 | E80: 1.2 | F80: 8e-05 | G80: =ROUND(C80*F80*E80,2) -> 0
G81: =MAX(G77,G78+G79+G80) -> 19463.01
B82: Provision 3T2025 | J82: 13413
B83: Provision 4T2025 | J83: 6050.01
J86: =SUM(J76:J84) -> 19463.01
B88: Assistance juridique
J92: =SUM(J88:J91) -> 0
B94: Frs d'audit, d'études s/acquis de titre
J103: =SUM(J95:J102) -> 0
B105: Sous-total autres frais de gestion | J105: =J26+J46+J86+J92+J19+J103 -> 34569.61
B106: Total frais de gestion | J106: =J9+J105 -> 34569.61
H108: Compta | J108: ='Rappro Balance'!E11 -> -1148966.5
G110: 61500000 | H110: Autres charges de gestion courante | J110: =Résultat!H87 -> 0
G111: 60830000 | H111: Agios | J111: =Résultat!H60 -> 0
G112: 60840000 | H112: Compte d'écart | J112: 0
G113: 61510000 | H113: Frais bancaires | J113: =Résultat!H88 -> 8506.17
G114: 61512000 | H114: Frais bancaires sur prêts
G115: 60810000 | H115: Charges sur emprunt | J115: =Résultat!H58 -> 1105890.7
G116: 61125000 | H116: Assistance juridique | J116: =Résultat!H80 -> 0
G117: 61200000 | H117: Frais d'audit, d'études | J117: =Résultat!H84 -> 0
G119: 61520000 | H119: Droits enregistrement | J119: =Résultat!H86 -> 0
G120: 64500000 | H120: Frais de transactions | J120: 0
G121: 61600000 | H121: Autres charges | J121: 0
G122: 65100000 | H122: Solde d’ouverture PVMV latentes nettes | J122: 0
H123: Moins-values réalisées de l'exercice
G124: 61560000 | H124: Primes d'assurance | J124: =Résultat!H89 -> 0
H125: Ecart | J125: =SUM(J106:J124) -> 0
H126: Contrôle | J126: =IF(ABS(J125)<0.01,"OK","ANOMALIE") -> OK

Sheet Créances_&_dettes
B1: =+Inventaire!B1 -> BOLZEN - SLP | E1: Créances et dettes au : | G1: =Sommaire!C1 -> 46022
B4: Créances | G4: =G1 -> 46022
B5: Charges constatées d'avance
F8: Solde | G8: =SUM(G6:G7) -> 0
B9: Ventes à reglement différé
F12: Solde | G12: =SUM(G10:G11) -> 0
B13: Débiteurs divers
F16: Solde | G16: =SUM(G14:G15) -> 0
B17: Porteurs de parts appelé non reçu
F21: Solde | G21: =SUM(G18:G19) -> 0
B22: Crédit vendeur
C23: Nominal crédit vendeur | G23: 0 | I23: compte 46220010
C24: Intérêt crédit vendeur | G24: 0 | I24: compte 46220011
F27: Solde | G27: =SUM(G23:G26) -> 0
B28: Compte d'attente
F34: Solde | G34: =SUM(G29:G33) -> 0
B35: TOTAL | G35: =SUM(G5:G34)/2 -> 0
B38: Dettes | G38: =G1 -> 46022
B39: Société de Gestion - EMZ
F45: Solde | G45: =SUM(G40:G44) -> 0
B46: Commissaires aux comptes
B47: Provision 3T2025 | G47: 2550
B48: Provision 4T2025 | G48: 2856
B49: Régul provision 3T2025 | G49: 306
F56: Solde | G56: =SUM(G47:G53) -> 5712
B57: Expert Comptable - APLITEC
B58: Provision EC 4T2025 | G58: 2950
B59: Provision AIFM 4T2025 | G59: 161
B60: Provision BDF OPC 2 4T2025 | G60: 110
B61: Provision Dépôt VL (semestriel) Base GECO AMF 4T2025 | G61: 70
F64: Solde | G64: =SUM(G58:H63) -> 3291
B65: Dépositaire
B66: Provision 3T2025 | G66: 13413
B67: Provision 4T2025 | G67: 6050.01
F72: Solde | G72: =SUM(G66:G69) -> 19463.01
B73: Créditeurs divers
B74: Provision Frais de constitution (avocats) | G74: 25000
B75: Bolzen - Break costs loan n°1 et n°3 | G75: 8506.17
F77: Solde | G77: =SUM(G74:G76) -> 33506.17
B78: Prime de souscription à reverser
F83: Solde | G83: =SUM(G79:G82) -> 0
B84: Porteurs de Parts appelé non perçu
F90: Solde | G90: =SUM(G85:G88) -> 0
B91: Rémunération GP
B92: Provision 2024 | G92: 756.3
B93: Provision 2025 | G93: 756.3
F95: Solde | G95: =SUM(G92:G93) -> 1512.6
B96: Compte d'attente
G102: =SUM(G96:G101) -> 0
B103: Sous-total avant réserve | G103: =SUM(G39:G102)/2 -> 63484.78
B105: Fonds de réserve | G105: 0
B108: TOTAL | G108: =SUM(G103:G107) -> 63484.78

Sheet Bilan
B1: =Sommaire!A1 -> BOLZEN - SLP | G1: Bilan au | I1: =Sommaire!C1 -> 46022
G2: en euros | L2: Texte de référence :
L3: article 421-1 Bilan actif du rglt ANC 2020-07
B4: ACTIF | L4: article 421-2 Bilan passif du rglt ANC 2020-07
I5: Exercice N | J5: Exercice N-1 | L5: annexe n°9 du guide d'implantation
I6: =I1 -> 46022 | L6: article L214-20 du Comofi
B8: TITRES FINANCIERS | I8: =+I10+I15+I20+I30+I38+I51 -> 1.5187551e+08 | J8: =+J10+J15+J20+J30+J38+J51 -> 0
C10: Actions et valeurs assimilées (A) | I10: =SUM(I12:I13) -> 8878534.4 | J10: =SUM(J12:J13) -> 0
D12: - négociés sur un marché réglementé ou assimilé | I12: =SUMIFS(Inventaire!N15:N75,Inventaire!A15:A75,"I",Inventaire!C15:C75,"*Action*") -> 0 | J12: 0 | L12: Actions
D13: - non négociés sur un marché réglementé ou assimilé | I13: =SUMIF(Inventaire!$B$12:$B$67,"??AC*",Inventaire!$N$12:$N$67)+SUMIF(Inventaire!B12:B67,"??AD*",Inventaire!N12:N67)+SUMIF(Inventaire!B12:B67,"??SA*",Inventaire!N12:N67)+SUMIF(Inventaire!B12:B67,"??BS*",Inventaire!N12:N67) -> 8878534.4 | J13: 0 | L13: AC/AD/SA/BS
C15: Obligations convertibles en actions (B) | I15: =SUM(I17:I18) -> 68919059 | J15: =SUM(J17:J18) -> 0
D17: - négociés sur un marché réglementé ou assimilé
D18: - non négociés sur un marché réglementé ou assimilé | I18: =SUMIF(Inventaire!$B$12:$B$67,"??OC*",Inventaire!$N$12:$N$67) -> 68919059 | J18: 0 | L18: OC
C20: Obligations et valeurs assimilées (C) | I20: =SUM(I22:I23) -> 74077917 | J20: =SUM(J22:J23) -> 0
D22: - négociés sur un marché réglementé ou assimilé
D23: - non négociés sur un marché réglementé ou assimilé | I23: =SUMIF(Inventaire!$B$12:$B$67,"??OS*",Inventaire!$N$12:$N$67)+SUMIF(Inventaire!$B$12:$B$67,"??OR*",Inventaire!$N$12:$N$67)+SUMIF(Inventaire!$B$12:$B$67,"??CN*",Inventaire!$N$12:$N$67) -> 74077917 | L23: OS/OR/CN
C25: Titres de créances (D)
D27: - négociés sur un marché réglementé ou assimilé
D28: - non négociés sur un marché réglementé ou assimilé
C30: Parts d'OPC et de fonds d'investissements (E) | I30: =SUM(I32:I34) -> 0 | J30: =SUM(J32:J34) -> 0
D32: - OPCVM | I32: =SUMIF(Inventaire!$C$27:$C$80,"*FCP*",Inventaire!$N$27:$N$80)+SUMIF(Inventaire!$C$27:$C$80,"*SICAV*",Inventaire!$N$27:$N$80) -> 0 | L32: FCP/SICAV
D33: - FIA et équivalents d'autres Etats membres de l'Union Européenne | I33: =SUMIF(Inventaire!$C$12:$C$80,"*FPCI*",Inventaire!$N$12:$N$80)+SUMIF(Inventaire!$C$12:$C$80,"*SLP*",Inventaire!$N$12:$N$80)+SUMIF(Inventaire!$C$12:$C$80,"*FCPR*",Inventaire!$N$12:$N$80)+SUMIF(Inventaire!$C$12:$C$80,"*FCPI*",Inventaire!$N$12:$N$80) -> 0 | L33: FCPR/FPCI/FCPI/SLP
D34: - Autres OPC et fonds d'investissement
C36: Dépôts (F) | I36: =SUMIF(Inventaire!$B$12:$B$67,"??CT*",Inventaire!$N$12:$N$67) -> 0 | L36: CT
C38: Instruments financiers à terme (G) | I38: 0
C40: Opérations temporaires sur titres (H) | I40: =SUM(I42:I46) -> 0
D42: - Créances représentatives de titres financiers reçus en pension
D43: - Créances représentatives de titres donnés en garantie
D44: - Créances représentatives de titres financiers prêtés
D45: - Titres financiers donnés en pension
D46: - Autres opérations temporaires
C49: Prêts (I) | I49: =SUMIF(Inventaire!$B$12:$B$67,"??CC*",Inventaire!$N$12:$N$67)+SUMIF(Inventaire!$B$12:$B$67,"??PR*",Inventaire!$N$12:$NT$67)+SUMIF(Inventaire!$B$12:$B$67,"??NO*",Inventaire!$N$12:$NT$67) -> 0 | L49: CC/PR/NO
C51: Autres actifs éligibles (J) | I51: =SUMIF(Inventaire!$B$12:$B$67,"??CT*",Inventaire!$N$12:$N$67) -> 0
B53: Sous-total actifs éligibles I = (A + B + C + D + E + F + G + H + I + J) | I53: =+I10+I15+I20+I30+I38+I51+I49+I40+I36+I25 -> 1.5187551e+08 | J53: =+J10+J15+J20+J30+J38+J51 -> 0
B55: CREANCES ET COMPTES D'AJUSTEMENT ACTIFS | I55: =Inventaire!D68 -> 0 | J55: 0
B57: COMPTES FINANCIERS | I57: =Inventaire!D66 -> 2114169.8 | J57: 0
B59: Sous-total actifs autres que les actifs éligibles II | I59: =+I55+I57 -> 2114169.8 | J59: =+J55+J57 -> 0
B61: TOTAL DE L'ACTIF I + II | I61: =+I53+I59 -> 1.5398968e+08 | J61: =+J53+J59 -> 0
B63: PASSIF
I64: =+I6 -> 46022
B65: CAPITAUX PROPRES
C67: Capital (1) | I67: =+I78-I75-I73-I71-I69 -> 88861539 | J67: =+J78-J75-J73-J71-J69 -> 0
C69: Report à nouveau sur revenu net
C71: Report à nouveau des plus et moins-values latentes nettes
C73: Report à nouveau des plus et moins-values réalisées nettes
C75: Résultat net de l'exercice | I75: =Résultat!H189 -> 1202051.4 | J75: 0
B77: Sous-total capitaux propres I
D78: ( = montant représentatif de l'actif net ) | I78: =Inventaire!C7 -> 90063591 | J78: 0
B80: PASSIFS ELIGIBLES
C82: Instruments financiers
C84: Emprunts | I84: =-Inventaire!D49 -> 63862605
C86: Autres passifs éligibles
B88: Sous-total passifs éligibles II | I88: =+I82+I84+I86 -> 63862605 | J88: =+J82+J84+J86 -> 0
B90: AUTRES PASSIFS
C92: Dettes et comptes d'ajustement passifs | I92: =-Inventaire!D70 -> 63484.78 | J92: 0
C94: Concours bancaires
B96: Sous-total autres passifs III | I96: =+I92+I94 -> 63484.78 | J96: =+J92+J94 -> 0
B98: TOTAL DU PASSIF : I + II + III | I98: =+I78+I88+I96 -> 1.5398968e+08 | J98: =+J78+J88+J96 -> 0
B99: (1) capital sous déduction du capital souscrit non appelé et des répartitions d'actifs
I100: =I61-I98 -> 0 | J100: =J61-J98 -> 0
G101: Contrôle | I101: =IF(ABS((I98-I61))<0.01,"OK","ANOMALIE") -> OK | J101: =IF(ABS((J61-J98))<0.01,"OK","ANOMALIE") -> OK

Sheet Résultat
B1: =Sommaire!A1 -> BOLZEN - SLP | E1: Compte de résultat au | G1: =Sommaire!C1 -> 46022
B3: Zone de saisie | K3: Changements significatifs :
I8: Exercice précédent
B9: Compte de résultat en | F9: =Sommaire!B30 -> Euro | H9: =G1 -> 46022 | I9: 45657
B12: REVENUS FINANCIERS NETS
B14: PRODUITS SUR OPERATIONS FINANCIERES
C16: Produits sur instruments financiers de capital investissement
C17: 7000000 | D17: sur actions | H17: =SUMIF('Balance '!A:A,"700000*",'Balance '!F:F)-SUMIF('Balance '!A:A,"700000*",'Balance '!E:E) -> 90591.11
C18: 7011000 | D18: sur des obligations convertibles en actions | H18: =SUMIF('Balance '!A:A,"701100*",'Balance '!F:F)-SUMIF('Balance '!A:A,"701100*",'Balance '!E:E) -> 1712219.2
C19: 7012000 | D19: sur autres obligations | H19: =SUMIF('Balance '!A:A,"701200*",'Balance '!F:F)-SUMIF('Balance '!A:A,"701200*",'Balance '!E:E) -> 247916.67
C21: Produits sur instruments du marché monétaire
C22: 70210000 | D22: Sur titres de créances négociables | H22: =SUMIF('Balance '!A:A,"702100*",'Balance '!F:F)-SUMIF('Balance '!A:A,"702100*",'Balance '!E:E) -> 0
C23: 70220000 | D23: Sur autres titres de créances négociés sur un marché réglementé | H23: =SUMIF('Balance '!A:A,"702200*",'Balance '!F:F)-SUMIF('Balance '!A:A,"702200*",'Balance '!E:E) -> 0
C24: 70230000 | D24: Sur titres de créances non négociés sur un marché réglementé | H24: =SUMIF('Balance '!A:A,"702300*",'Balance '!F:F)-SUMIF('Balance '!A:A,"702300*",'Balance '!E:E) -> 0
C26: Produit sur les parts d'OPC
C27: 70300000 | D27: Produits sur parts d'OPC | H27: =SUMIF('Balance '!A:A,"703000*",'Balance '!F:F)-SUMIF('Balance '!A:A,"703000*",'Balance '!E:E) -> 0
C29: Produits sur instruments financiers à termes
C30: 7041000 | D30: sur opérations d'échange de taux | H30: =SUMIF('Balance '!A:A,"704100*",'Balance '!F:F)-SUMIF('Balance '!A:A,"704100*",'Balance '!E:E) -> 0
C31: 7042000 | D31: sur autres contrats financiers | H31: =SUMIF('Balance '!A:A,"704200*",'Balance '!F:F)-SUMIF('Balance '!A:A,"704200*",'Balance '!E:E) -> 0
C33: Produits sur opérations temporaires de titres
C34: 70500000 | D34: Produits sur opération temporaires de titres | H34: =SUMIF('Balance '!A:A,"705000*",'Balance '!F:F)-SUMIF('Balance '!A:A,"705000*",'Balance '!E:E) -> 0
C36: Produits sur prêts et créances
C37: 7066000 | D37: sur avance en compte courant | H37: =SUMIF('Balance '!A:A,"706600*",'Balance '!F:F)-SUMIF('Balance '!A:A,"706600*",'Balance '!E:E) -> 0
C39: Produits sur autres actifs et passifs éligibles
C40: 70710000 | D40: Sur dépôts | H40: =SUMIF('Balance '!A:A,"707100*",'Balance '!F:F)-SUMIF('Balance '!A:A,"707100*",'Balance '!E:E) -> 0
C41: 70760000 | D41: Fonds de capital investissement - sur avances en compte-courant | H41: =SUMIF('Balance '!A:A,"707600*",'Balance '!F:F)-SUMIF('Balance '!A:A,"707600*",'Balance '!E:E) -> 0
C42: 70770000 | D42: Sur autres instruments financiers | H42: =SUMIF('Balance '!A:A,"707700*",'Balance '!F:F)-SUMIF('Balance '!A:A,"707700*",'Balance '!E:E) -> 0
C44: Autres produits financiers
C45: 7083000 | D45: Intérêts comptes bancaires | H45: =SUMIF('Balance '!A:A,"708300*",'Balance '!F:F)-SUMIF('Balance '!A:A,"708300*",'Balance '!E:E) -> 5507.44
B49: Sous-total produits sur opérations financières | H49: =+SUM(H16:H47) -> 2056234.4 | I49: =SUM(I16:I46) -> 0
B51: CHARGES SUR OPERATIONS FINANCIERES
C53: Charges sur instruments finaciers à terme
C54: 6031000 | D54: sur opérations d'échange de taux | H54: =SUMIF('Balance '!A:A,"603100*",'Balance '!E:E)-SUMIF('Balance '!A:A,"603100*",'Balance '!F:F) -> 0
C55: 6032000 | D55: sur autres contrats financiers | H55: =SUMIF('Balance '!A:A,"603200*",'Balance '!E:E)-SUMIF('Balance '!A:A,"603200*",'Balance '!F:F) -> 0
C57: Charges sur emprunts
C58: 6050000 | D58: Charges sur emprunts | H58: =SUMIF('Balance '!A:A,"605000*",'Balance '!E:E)-SUMIF('Balance '!A:A,"605000*",'Balance '!F:F) -> 1105890.7
C59: Autres charges financières
C60: 6083000 | D60: Agios | H60: =SUMIF('Balance '!A:A,"608300*",'Balance '!E:E)-SUMIF('Balance '!A:A,"608300*",'Balance '!F:F) -> 0
B62: Sous-total charges sur opérations financières | H62: =SUM(H53:H60) -> 1105890.7 | I62: =SUM(I53:I60) -> 0
B64: TOTAL REVENUS FINANCIERS NETS (A) | H64: =H49-H62 -> 950343.66 | I64: =I49-I62 -> 0
B66: AUTRES PRODUITS
H67: =+SUM(H68:H71) -> 0 | I67: =+SUM(I68:I71) -> 0
C68: 7110000 | D68: Rétrocession des frais de gestion au bénéfice de l'OPC | H68: =SUMIF('Balance '!A:A,"711000*",'Balance '!F:F)-SUMIF('Balance '!A:A,"711000*",'Balance '!E:E) -> 0
C69: 7200000 | D69: Autres Produits | H69: =SUMIF('Balance '!A:A,"720000*",'Balance '!F:F)-SUMIF('Balance '!A:A,"720000*",'Balance '!E:E) -> 0
C70: 7210000 | D70: Versements en garantie de capital ou de performance | H70: =SUMIF('Balance '!A:A,"721000*",'Balance '!F:F)-SUMIF('Balance '!A:A,"721000*",'Balance '!E:E) -> 0
C71: 7240000 | D71: Produits sur autres actifs éligibles | H71: =SUMIF('Balance '!A:A,"724000*",'Balance '!F:F)-SUMIF('Balance '!A:A,"724000*",'Balance '!E:E) -> 0
B73: AUTRES CHARGES | H73: =+SUM(H75:H91) -> 43075.78 | I73: =+SUM(I75:I91) -> 0
C75: 6111000 | D75: Frais de gestion de la société de gestion | H75: =SUMIF('Balance '!A:A,"611100*",'Balance '!E:E)-SUMIF('Balance '!A:A,"611100*",'Balance '!F:F) -> 0
C76: 6112100 | D76: Frais CAC | H76: =SUMIF('Balance '!A:A,"6112100*",'Balance '!E:E)-SUMIF('Balance '!A:A,"6112100*",'Balance '!F:F) -> 5712
C77: 6112200 | D77: Frais délégation comptable | H77: =SUMIF('Balance '!A:A,"6112200*",'Balance '!E:E)-SUMIF('Balance '!A:A,"6112200*",'Balance '!F:F) -> 7882
C78: 6112300 | D78: Frais dépositaire | H78: =SUMIF('Balance '!A:A,"6112300*",'Balance '!E:E)-SUMIF('Balance '!A:A,"6112300*",'Balance '!F:F) -> 19463.01
C79: 6112400 | D79: Autres assurances | H79: =SUMIF('Balance '!A:A,"6112400*",'Balance '!E:E)-SUMIF('Balance '!A:A,"6112400*",'Balance '!F:F) -> 0
C80: 6112500 | D80: Assistance juridique | H80: =SUMIF('Balance '!A:A,"6112500*",'Balance '!E:E)-SUMIF('Balance '!A:A,"6112500*",'Balance '!F:F) -> 0
C81: 6113000 | D81: Rémunération General Partner | H81: =SUMIF('Balance '!A:A,"6111300*",'Balance '!E:E)-SUMIF('Balance '!A:A,"6111300*",'Balance '!F:F) -> 1512.6
C84: 6120000 | D84: Frais d'audit et d'étude | H84: =SUMIF('Balance '!A:A,"6120000*",'Balance '!E:E)-SUMIF('Balance '!A:A,"6120000*",'Balance '!F:F) -> 0
C85: 6130000 | D85: Impôts, taxes et versements assimilés | H85: =SUMIF('Balance '!A:A,"6130000*",'Balance '!E:E)-SUMIF('Balance '!A:A,"6130000*",'Balance '!F:F) -> 0
C86: 6130001 | D86: Droit d'enregistrement | H86: =SUMIF('Balance '!A:A,"6130001*",'Balance '!E:E)-SUMIF('Balance '!A:A,"6130001*",'Balance '!F:F) -> 0
C87: 6150000 | D87: Autres charges de gestion courante | H87: =SUMIF('Balance '!A:A,"6150000*",'Balance '!E:E)-SUMIF('Balance '!A:A,"6150000*",'Balance '!F:F) -> 0
C88: 6151000 | D88: Frais bancaires | H88: =SUMIF('Balance '!A:A,"6151000*",'Balance '!E:E)-SUMIF('Balance '!A:A,"6151000*",'Balance '!F:F) -> 8506.17
C89: 6156000 | D89: Primes d'assurance | H89: =SUMIF('Balance '!A:A,"6156000*",'Balance '!E:E)-SUMIF('Balance '!A:A,"6156000*",'Balance '!F:F) -> 0
C90: 6160000 | D90: Autres charges | H90: =SUMIF('Balance '!A:A,"6160000*",'Balance '!E:E)-SUMIF('Balance '!A:A,"6160000*",'Balance '!F:F) -> 0
C91: 6190000 | D91: Rétrocessions de frais de gestion | H91: =SUMIF('Balance '!A:A,"6190000*",'Balance '!E:E)-SUMIF('Balance '!A:A,"6190000*",'Balance '!F:F) -> 0
B93: Sous-total autres produits et autres charges (B) | H93: =-H67+H73 -> 43075.78 | I93: =+I67+I73 -> 0
B95: REVENUS NETS AVANT COMPTE DE REGULARISATION C = A - B | H95: =+H64-H93 -> 907267.88 | I95: =+I64-I93 -> 0
C97: Régularisation des revenus nets de l'exercice (D) | H97: =SUMIF('Balance '!A:A,"771000*",'Balance '!F:F)-SUMIF('Balance '!A:A,"771000*",'Balance '!E:E) -> 0
B99: REVENUS NETS I = C + D | H99: =+H95+H97 -> 907267.88 | I99: =+I95+I97 -> 0
B101: PLUS OU MOINS-VALUES REALISEES NETTES AVANT COMPTE DE REGULARISATION
C103: Plus-values et Moins-values réalisées | H103: =SUM(H105:H132) -> 0 | I103: =SUM(I105:I132) -> 0
C104: Dont Moins-values réalisées:
C105: 6440000 | D105: sur actions | H105: =-(SUMIF('Balance '!A:A,"6440000*",'Balance '!E:E)-SUMIF('Balance '!A:A,"6440000*",'Balance '!F:F)) -> 0
C106: 6441200 | D106: sur obligations convertibles en actions | H106: =-(SUMIF('Balance '!A:A,"6441200*",'Balance '!E:E)-SUMIF('Balance '!A:A,"6441200*",'Balance '!F:F)) -> 0
C107: 6441500 | D107: sur autres obligations | H107: =-(SUMIF('Balance '!A:A,"6441500*",'Balance '!E:E)-SUMIF('Balance '!A:A,"6441500*",'Balance '!F:F)) -> 0
C108: 6442000 | D108: sur titres de créances | H108: =-(SUMIF('Balance '!A:A,"6442000*",'Balance '!E:E)-SUMIF('Balance '!A:A,"6442000*",'Balance '!F:F)) -> 0
C109: 6443000 | D109: sur parts d’OPC | H109: =-(SUMIF('Balance '!A:A,"6443000*",'Balance '!E:E)-SUMIF('Balance '!A:A,"6443000*",'Balance '!F:F)) -> 0
C110: 6444000 | D110: sur opérations temporaires de titres financiers | H110: =-(SUMIF('Balance '!A:A,"6444000*",'Balance '!E:E)-SUMIF('Balance '!A:A,"6444000*",'Balance '!F:F)) -> 0
C111: 6445000 | D111: sur instruments financiers à terme (y compris change à terme) | H111: =-(SUMIF('Balance '!A:A,"6445000*",'Balance '!E:E)-SUMIF('Balance '!A:A,"6445000*",'Balance '!F:F)) -> 0
C112: 6446100 | D112: sur dépôts et autres instruments financiers | H112: =-(SUMIF('Balance '!A:A,"6446100*",'Balance '!E:E)-SUMIF('Balance '!A:A,"6446100*",'Balance '!F:F)) -> 0
C113: 6446200 | D113: sur autres actifs éligibles | H113: =-(SUMIF('Balance '!A:A,"6446200*",'Balance '!E:E)-SUMIF('Balance '!A:A,"6446200*",'Balance '!F:F)) -> 0
C114: 6447000 | D114: sur comptes financiers | H114: =-(SUMIF('Balance '!A:A,"6447000*",'Balance '!E:E)-SUMIF('Balance '!A:A,"6447000*",'Balance '!F:F)) -> 0
C115: 6448000 | D115: sur instruments financiers vendus à découvert | H115: =-(SUMIF('Balance '!A:A,"6448000*",'Balance '!E:E)-SUMIF('Balance '!A:A,"6448000*",'Balance '!F:F)) -> 0
C116: 6449000 | D116: sur les passifs de financement émis par l’OFS | H116: =-(SUMIF('Balance '!A:A,"6449000*",'Balance '!E:E)-SUMIF('Balance '!A:A,"6449000*",'Balance '!F:F)) -> 0
C118: Dont Plus-values réalisées:
C119: 7440000 | D119: sur actions | H119: =SUMIF('Balance '!A:A,"7440000*",'Balance '!F:F)-SUMIF('Balance '!A:A,"7440000*",'Balance '!E:E) -> 0
C120: 7441200 | D120: sur obligations convertibles en actions | H120: =SUMIF('Balance '!A:A,"7441200*",'Balance '!F:F)-SUMIF('Balance '!A:A,"7441200*",'Balance '!E:E) -> 0
C121: 7441500 | D121: sur autres obligations | H121: =SUMIF('Balance '!A:A,"7441500*",'Balance '!F:F)-SUMIF('Balance '!A:A,"7441500*",'Balance '!E:E) -> 0
C122: 7442000 | D122: sur titres de créances | H122: =SUMIF('Balance '!A:A,"7442000*",'Balance '!F:F)-SUMIF('Balance '!A:A,"7442000*",'Balance '!E:E) -> 0
C123: 7443000 | D123: sur parts d’OPC | H123: =SUMIF('Balance '!A:A,"7443000*",'Balance '!F:F)-SUMIF('Balance '!A:A,"7443000*",'Balance '!E:E) -> 0
C124: 7444000 | D124: sur opérations temporaires de titres financiers | H124: =SUMIF('Balance '!A:A,"7444000*",'Balance '!F:F)-SUMIF('Balance '!A:A,"7444000*",'Balance '!E:E) -> 0
C125: 7445000 | D125: sur instruments financiers à terme (y compris change à terme) | H125: =SUMIF('Balance '!A:A,"7445000*",'Balance '!F:F)-SUMIF('Balance '!A:A,"7445000*",'Balance '!E:E) -> 0
C126: 7446100 | D126: sur dépôts et autres instruments financiers | H126: =SUMIF('Balance '!A:A,"7446100*",'Balance '!F:F)-SUMIF('Balance '!A:A,"7446100*",'Balance '!E:E) -> 0
C127: 7446200 | D127: sur autres actifs éligibles | H127: =SUMIF('Balance '!A:A,"7446200*",'Balance '!F:F)-SUMIF('Balance '!A:A,"7446200*",'Balance '!E:E) -> 0
C128: 7447000 | D128: sur comptes financiers | H128: =SUMIF('Balance '!A:A,"7447000*",'Balance '!F:F)-SUMIF('Balance '!A:A,"7447000*",'Balance '!E:E) -> 0
C129: 7448000 | D129: sur instruments financiers vendus à découvert | H129: =SUMIF('Balance '!A:A,"7448000*",'Balance '!F:F)-SUMIF('Balance '!A:A,"7448000*",'Balance '!E:E) -> 0
C130: 7460000 | D130: Différences de change réalisées sur comptes financiers | H130: =SUMIF('Balance '!A:A,"7460000*",'Balance '!F:F)-SUMIF('Balance '!A:A,"7460000*",'Balance '!E:E) -> 0
C131: 7471000 | D131: Indemnités d’assurances perçues | H131: =SUMIF('Balance '!A:A,"7471000*",'Balance '!F:F)-SUMIF('Balance '!A:A,"7471000*",'Balance '!E:E) -> 0
C132: 7479000 | D132: Versements reçus en garantie de performance | H132: =SUMIF('Balance '!A:A,"7479000*",'Balance '!F:F)-SUMIF('Balance '!A:A,"7479000*",'Balance '!E:E) -> 0
C134: Frais de transactions externes
C135: 64511100 | D135: Frais de transactions externes - Frais d'achat de titres | H135: =-SUMIF('Balance '!A:A,"64511100*",'Balance '!E:E)-SUMIF('Balance '!A:A,"64511100*",'Balance '!F:F) -> 0
C136: 64511200 | D136: Frais de transactions externes - Frais de vente de titres | H136: =-SUMIF('Balance '!A:A,"64511200*",'Balance '!E:E)-SUMIF('Balance '!A:A,"64511200*",'Balance '!F:F) -> 0
C138: 6451200 | D138: Frais de cession | H138: =-SUMIF('Balance '!A:A,"6451200*",'Balance '!E:E)-SUMIF('Balance '!A:A,"6451200*",'Balance '!F:F) -> 0
...

Sheet Capitaux propres
B1: =Sommaire!A1 -> BOLZEN - SLP | D1: Evolution des capitaux propres | F1: =Sommaire!C1 -> 46022
B4: Reconstitution de la ligne des capitaux propres depuis l'origine | D4: =F1 -> 46022 | F4: Variation | H4: Texte de référence : article 433-2
B5: Apports | C5: + | D5: =+D6+D7 -> 88886539 | E5: =SUM(E6:E7) -> 0 | F5: =D5-E5 -> 88886539 | H5: Reconstitution de la ligne "capitaux propres" des fonds de capital investissement et autres véhicules
B6: Capital souscrit | C6: + | D6: 943269700 | E6: 0 | F6: =D6-E6 -> 943269700
B7: Capital non appelé | C7: - | D7: -8.5438316e+08 | E7: 0 | F7: =D7-E7 -> -8.5438316e+08
B8: Emission de passifs de financement (ne concerne que les OFS) | C8: +
B9: Résultat de gestion | C9: +/- | D9: =SUM(D10:D11) -> 907267.88 | E9: =SUM(E10:E11) -> 0 | F9: =D9-E9 -> 907267.88
B10: Revenus nets de l'exercice | C10: +/- | D10: =Résultat!H99 -> 907267.88 | E10: 0 | F10: =D10-E10 -> 907267.88
B11: Cumul des revenus nets des exercices précédents | C11: +/- | D11: =E10+E11 -> 0 | E11: 0 | F11: =D11-E11 -> 0 | H11: #10150010
B12: Plus ou moins-values réalisées nettes | C12: +/- | D12: =SUM(D13:D14) -> 0 | E12: =E14+E13 -> 0 | F12: =D12-E12 -> 0
B13: Plus ou moins-values réalisées nettes de l'exercice | C13: +/- | D13: =Résultat!H146 -> 0 | E13: 0 | F13: =D13-E13 -> 0
B14: Cumul plus ou moins-values réalisées nettes des exercices précédents | C14: +/- | D14: =E13+E14 -> 0 | E14: 0 | F14: =D14-E14 -> 0 | H14: #10150020
B15: Variation des plus ou moins-values latentes nettes | C15: +/- | D15: =SUM(D16:D17) -> 294783.51 | E15: =E16+E17 -> 0 | F15: =D15-E15 -> 294783.51
B16: Plus ou moins-values latentes nettes de l'exercice | C16: +/- | D16: =Résultat!H176 -> 294783.51 | E16: 0 | F16: =D16-E16 -> 294783.51
B17: Cumul plus ou moins-values latentes nettes des exercices précédents | C17: +/- | D17: =E17+E16 -> 0 | E17: 0 | F17: =D17-E17 -> 0 | H17: #10150030
B18: Boni de liquidation | C18: - | F18: =D18-E18 -> 0
B19: Rachats et répartitions d'actifs | C19: - | D19: =SUM(D20:D23) -> 0 | E19: =SUM(E20:E23) -> 0 | F19: =D19-E19 -> 0
B20: Rachats | C20: - | F20: =D20-E20 -> 0
B21: Répartition d'actifs | C21: - | D21: 0 | E21: 0 | F21: =D21-E21 -> 0
B22: Distribution de résultats nets | C22: - | F22: =D22-E22 -> 0
B23: Distribution de plus et moins-values réalisées nettes | C23: - | F23: =D23-E23 -> 0
B24: Remboursement de passifs de financement (ne concerne que les OFS) | C24: +/- | F24: =D24-E24 -> 0
B25: Autres éléments | C25: +/- | D25: =D33 -> -25000 | E25: 0 | F25: =D25-E25 -> -25000 | H25: Comptabilité
B26: Capitaux propres en fin d'exercice | C26: = | D26: =D25+D19+D9+D5+D12+D15 -> 90063591 | E26: =E25+E9+E19+E5+E15+E12 -> 0 | F26: =D26-E26 -> 90063591 | H26: 1.3486967e+08
H27: =H26-D26 -> 44806077
B29: Autres éléments :
B30: Frais de constitution | D30: =-25000 -> -25000
B31: Prime de souscription | D31: 0 | E31: 0
B32: Provision sur dépréciation | D32: 0
D33: =SUM(D30:D32) -> -25000
B35: Contrôle de l'actif net selon l'inventaire : | D35: =Inventaire!C7 -> 90063591 | E35: =E25+E19+E9+E5+E12+E15 -> 0 | F35: =F25+F19+F9+F5+F12+F15 -> 90063591
B36: Ecart | D36: =D26-D35 -> 0 | E36: =E26-E35 -> 0 | F36: =ROUND(F26-F35,2) -> 0 | H36: =Inventaire!L34+Inventaire!M34 -> 2345510.5
B37: Conclusion après valorisation | D37: =+IF(ABS(D36)<0.01,"OK","ANOMALIE") -> OK | E37: =+IF(ABS(E36)<0.01,"OK","ANOMALIE") -> OK | F37: =+IF(ABS(F36)<0.01,"OK","ANOMALIE") -> OK | H37: =ROUNDDOWN(D36+H36,0) -> 2345510
B39: Ecart | D39: =ROUNDDOWN(+D36+Inventaire!L25+Inventaire!M25-H40,0) -> 2232905 | H39: Emprunt
B40: Conclusion avant valorisation | D40: =IF(D37="OK","OK",+IF(D39<0.0000001,"OK","ANOMALIE")) -> OK | H40: =Emprunt!K186 -> 112604.67

Sheet Rappro Banque
B1: =+Inventaire!B1 -> BOLZEN - SLP | D1: Rapprochement bancaire au | F1: =Sommaire!C1 -> 46022
B5: ING Bank
C6: OPCVM | F6: DEPOSITAIRE
B7: Libellé | C7: Montant | D7: Date de régularisation | E7: Libellé | F7: Montant | G7: Date de régularisation
B8: Solde comptable | C8: 0 | E8: Solde dépositaire | F8: 0
B10: TOTAL | C10: =SUM(C8:C9) -> 0 | E10: TOTAL | F10: =SUM(F8:F9) -> 0
B11: Ecart pour contrôle | C11: =F10-C10 -> 0
C12: =IF(C11=0,"OK","ANOMALIE") -> OK
B14: CACEIS Compte principal 00500313674
C15: FPCI | F15: DEPOSITAIRE
B16: Libellé | C16: Montant | D16: Date de régularisation | E16: Libellé | F16: Montant | G16: Date de régularisation
B18: Solde comptable au | E18: Solde bancaire au
B19: =+F1 -> 46022 | C19: 2114169.8 | E19: =+F1 -> 46022 | F19: 2114169.8
B21: TOTAL | C21: =C19 -> 2114169.8 | E21: TOTAL | F21: =SUM(F19:F20) -> 2114169.8
B22: Ecart pour contrôle | C22: =F21-C21 -> 0
C23: =IF(C22=0,"OK","ANOMALIE") -> OK
B26: Intérêts sur emprunt tiré | C26: 0
B27: Intérêts sur emprunt non tiré | C27: 0
C28: =SUM(C26:C27) -> 0
B30: TOTAL DISPONIBILITES | C30: =F21+C28 -> 2114169.8

Sheet Rappro Balance
B1: =Sommaire!A1 -> BOLZEN - SLP | E1: Rapprochement Portefeuille/ balance : | G1: =Sommaire!C1 -> 46022
B4: Classe | C4: Comptes débiteurs/créditeurs | D4: Soldes balance | E4: Solde net | F4: Calcul VL | G4: Différence | H4: Contrôle
B6: Classe 1 | C6: comptes débiteurs | D6: =SUMIF('Balance '!A:A,"1*",'Balance '!E:E) -> 943294700
C7: comptes créditeurs | D7: =SUMIF('Balance '!A:A,"1*",'Balance '!F:F) -> 1.0321562e+09
C8: Sous total | E8: =D7-D6 -> 88861539
B9: Classe 6 | C9: comptes débiteurs | D9: =SUMIF('Balance '!A:A,"6*",'Balance '!E:E) -> 1148966.5
C10: comptes créditeurs | D10: =SUMIF('Balance '!A:A,"6*",'Balance '!F:F) -> 0
C11: Sous total | E11: =D10-D9 -> -1148966.5
B12: Classe 7 | C12: comptes débiteurs | D12: =SUMIF('Balance '!A:A,"7*",'Balance '!E:E) -> 0
C13: comptes créditeurs | D13: =SUMIF('Balance '!A:A,"7*",'Balance '!F:F) -> 2351017.9
C14: Sous total | E14: =D13-D12 -> 2351017.9
C15: Résultat | D15: =+E11+E14 -> 1202051.4
B16: Actif net | E16: =SUM(E8:E15) -> 90063591 | F16: =ROUND(+Inventaire!D74,2) -> 90063591 | G16: =ROUND((E16-F16),2) -> 0 | H16: =IF(ABS(G16)<0.01,"OK","ANOMALIE") -> OK | I16: Ecart = valorisation
B18: Classe | C18: Comptes débiteurs/créditeurs | D18: Soldes balance | E18: Solde net | F18: Calcul VL | G18: Différence
B20: Classe 3 | C20: comptes débiteurs | D20: =SUMIF('Balance '!A:A,"3*",'Balance '!E:E) -> 1.5187551e+08 | I20: Contrôle efficient avant comptabilisation différence d'estimation
C21: comptes créditeurs | D21: =SUMIF('Balance '!A:A,"3*",'Balance '!F:F) -> 63862605 | I21: Diff. Estim. Inventaire | J21: Ecart | K21: Conclusion
C22: Sous total | E22: =-(D21-D20) -> 88012906 | F22: =ROUND(+Inventaire!D64+Inventaire!D72,2) -> 88012906 | G22: =ROUND(-(E22-F22),2) -> 0 | I22: =+Inventaire!L34+Inventaire!M34 -> 2345510.5 | J22: =ROUND(G22-I22,2)+I25 -> -2232905.8 | K22: =IF(G22=0,"OK",IF(ABS(J22)=0,"OK","ERREUR")) -> OK
B23: Classe 4 | C23: comptes débiteurs | D23: =SUMIF('Balance '!A:A,"4*",'Balance '!E:E) -> 0
C24: comptes créditeurs | D24: =SUMIF('Balance '!A:A,"4*",'Balance '!F:F) -> 63484.78 | I24: Intérêts Emprunt
C25: Sous total | E25: =D23-D24 -> -63484.78 | F25: =Inventaire!D68+Inventaire!D70 -> -63484.78 | G25: =ROUND(-(E25-F25),2) -> 0 | I25: =Emprunt!K186 -> 112604.67
B26: Classe 5 | C26: comptes débiteurs | D26: =SUMIF('Balance '!A:A,"5*",'Balance '!E:E) -> 2114169.8
C27: comptes créditeurs | D27: =SUMIF('Balance '!A:A,"5*",'Balance '!F:F) -> 0
C28: Sous total | E28: =+D26-D27 -> 2114169.8 | F28: =ROUND(Inventaire!D66,2) -> 2114169.8 | G28: =E28-F28 -> 0
B30: Actif net | E30: =SUM(E22:E29) -> 90063591 | F30: =SUM(F20:F29) -> 90063591 | G30: =ROUND((F30-E30),2) -> 0 | H30: =IF(ABS(G30)<0.01,"OK","ANOMALIE") -> OK
E32: =E16-E30 -> 0 | F32: CONTRÔLE | G32: =G16+G30 -> 0
E33: =IF(ABS(E32)<0.01,"OK","ANOMALIE") -> OK | F33: Conclusion | G33: =IF(ABS(G32)<0.01,"OK","ANOMALIE") -> OK

Sheet Balance 
A1: BOLZEN - SLP
A3: BALANCE GENERALE
A4: Période du 01/03/2025 au 31/12/2025 | B4: Exporté le14/01/2026
A5: Compte | B5: Libellé | C5: Débit | D5: Crédit | E5: Solde Débit | F5: Solde Crédit
A6: 10111000 | B6: Capital souscrit part A1 | C6: 0 | D6: 943268700 | E6: 0 | F6: 943268700
A7: 10113000 | B7: Capital souscrit parts commandité | C7: 0 | D7: 1000 | E7: 0 | F7: 1000
A8: 10191100 | B8: Parts A1 souscrite non appelées | C8: 943268700 | D8: 0 | E8: 943268700 | F8: 0
A9: 10191300 | B9: Parts Commandité souscrites non appelées | C9: 1000 | D9: 0 | E9: 1000 | F9: 0
A10: 10211000 | B10: Emission parts A1 | C10: 0 | D10: 88886445 | E10: 0 | F10: 88886445
A11: 10213000 | B11: Emission parts GP | C11: 0 | D11: 94.23 | E11: 0 | F11: 94.23
A12: 13000000 | B12: Frais de constitut°, de fusion, d'apport | C12: 25710.32 | D12: 710.32 | E12: 25000 | F12: 0
A13: 30260030 | B13: Koenig solutions - ADP B | C13: 8720000 | D13: 0 | E13: 8720000 | F13: 0
A14: 31260010 | B14: Inflexion BIDCO - OCADP 2 | C14: 40320000 | D14: 0 | E14: 40320000 | F14: 0
A15: 31260030 | B15: Koenig solutions - OC (SHL) | C15: 26160000 | D15: 0 | E15: 26160000 | F15: 0
A16: 31260031 | B16: Koenig solutions - OC (Warehouse II - ADP A) | C16: 500000 | D16: 0 | E16: 500000 | F16: 0
A17: 31460010 | B17: Inflexion BIDCO - ORADP 1 | C17: 10080000 | D17: 0 | E17: 10080000 | F17: 0
... A41: 75512000 | B41: PVMV latentes nettes s/OCA | C41: 0 | D41: 226840.18 | E41: 0 | F41: 226840.18

Sheet Grand livre
A1: 10111000 Capital souscrit part A1 | F1: Débit | G1: Crédit | I1: Solde Débit | J1: Solde Crédit
B2: 45726 | C2: OD --> E | D2: CSOUS | E2: EMZ 11-A SLP - Engagements Parts A1 | F2: 0 | G2: 303040500 | I2: 0 | J2: 303040500
B3: 45726 | C3: OD --> E | D3: CSOUS1 | E3: EMZ 11 Executive - Engagements Parts A1 | F3: 0 | G3: 17210000 | I3: 0 | J3: 320250500
B4: 45726 | C4: OD --> E | D4: CSOUS2 | E4: EMZ 11SLP - Engagements Parts A1 | F4: 0 | G4: 4.018071e+08 | I4: 0 | J4: 7.220576e+08
B5: 45861 | C5: OD --> E | D5: 13 | E5: Engement complémentaire EMZ 11 | F5: 0 | G5: 155000000 | I5: 0 | J5: 8.770576e+08
B6: 45930 | C6: OD --> E | D6: 14 | E6: Souscription complémentaire sept 2025 | F6: 0 | G6: 1564700 | I6: 0 | J6: 878622300
B7: 45995 | C7: OD --> E | D7: 15 | E7: Souscription complémentaire decembre 2025 | F7: 0 | G7: 64646400 | I7: 0 | J7: 943268700
A8: Total 10111000 | F8: 0 | G8: 943268700 | I8: 0 | J8: 943268700
A10: 10113000 Capital souscrit parts commandité | F10: Débit | G10: Crédit | I10: Solde Débit | J10: Solde Crédit
B11: 45726 | C11: OD --> E | D11: CSOUS3 | E11: AMZ 11 GP - E,gagements Parts Commandité | F11: 0 | G11: 1000 | I11: 0 | J11: 1000
A12: Total 10113000 | F12: 0 | G12: 1000 | I12: 0 | J12: 1000
A14: 10191100 Parts A1 souscrite non appelées | F14: Débit | G14: Crédit | I14: Solde Débit | J14: Solde Crédit
B15: 45726 | C15: OD --> E | D15: CSOUS | E15: EMZ 11-A SLP - Engagements Parts A1 | F15: 303040500 | G15: 0 | I15: 303040500 | J15: 0
B16: 45726 | C16: OD --> E | D16: CSOUS1 | E16: EMZ 11 Executive - Engagements Parts A1 | F16: 17210000 | G16: 0 | I16: 320250500 | J16: 0
B17: 45726 | C17: OD --> E | D17: CSOUS2 | E17: EMZ 11SLP - Engagements Parts A1 | F17: 4.018071e+08 | G17: 0 | I17: 7.220576e+08 | J17: 0
B18: 45861 | C18: OD --> E | D18: 13 | E18: Engement complémentaire EMZ 11 | F18: 155000000 | G18: 0 | I18: 8.770576e+08 | J18: 0
B19: 45930 | C19: OD --> E | D19: 14 | E19: Souscription complémentaire sept 2025 | F19: 1564700 | G19: 0 | I19: 878622300 | J19: 0
B20: 45995 | C20: OD --> E | D20: 15 | E20: Souscription complémentaire decembre 2025 | F20: 64646400 | G20: 0 | I20: 943268700 | J20: 0
A21: Total 10191100 | F21: 943268700 | G21: 0 | I21: 943268700 | J21: 0
A23: 10191300 Parts Commandité souscrites non appelées | F23: Débit | G23: Crédit | I23: Solde Débit | J23: Solde Crédit
B24: 45726 | C24: OD --> E | D24: CSOUS3 | E24: AMZ 11 GP - E,gagements Parts Commandité | F24: 1000 | G24: 0 | I24: 1000 | J24: 0
A25: Total 10191300 | F25: 1000 | G25: 0 | I25: 1000 | J25: 0
A27: 10211000 Emission parts A1 | F27: Débit | G27: Crédit | I27: Solde Débit | J27: Solde Crédit
B28: 45726 | C28: BQCaceis --> E | D28: 1 | E28: EMZ 11 SLP - Appel capital social | F28: 0 | G28: 2 | I28: 0 | J28: 2
B29: 46020 | C29: BQCaceis --> E | D29: ADFn°1 | E29: EMZ 11 SLP - ADF n°1 - Parts A | F29: 0 | G29: 1246034.4 | I29: 0 | J29: 1246036.4
B30: 46020 | C30: BQCaceis --> E | D30: ADFn°1 | E30: EMZ 11 A SLP - ADF n°1 - Parts A | F30: 0 | G30: 606081 | I30: 0 | J30: 1852117.4
B31: 46020 | C31: BQCaceis --> E | D31: ADFn°1 | E31: EMZ 11 Executive Fund SLP - ADF n°1 - Parts A | F31: 0 | G31: 34420 | I31: 0 | J31: 1886537.4
B32: 46020 | C32: BQCaceis --> E | D32: ADFn°1bis | E32: EMZ 11 SLP - ADF n°1 - Parts A | F32: 0 | G32: 57462445 | I32: 0 | J32: 59348983
B33: 46020 | C33: BQCaceis --> E | D33: ADFn°1bis | E33: EMZ 11 A SLP - ADF n°1 - Parts A | F33: 0 | G33: 27950144 | I33: 0 | J33: 87299126
B34: 46020 | C34: BQCaceis --> E | D34: ADFn°1bis | E34: EMZ 11 Executive Fund SLP - ADF n°1 - Parts A | F34: 0 | G34: 1587319.1 | I34: 0 | J34: 88886445
A35: Total 10211000 | F35: 0 | G35: 88886445 | I35: 0 | J35: 88886445
A37: 10213000 Emission parts GP | F37: Débit | G37: Crédit | I37: Solde Débit | J37: Solde Crédit
B38: 45726 | C38: BQCaceis --> E | D38: 2 | E38: EMZ GP - Appel capital social | F38: 0 | G38: 2 | I38: 0 | J38: 2
B39: 46020 | C39: BQCaceis --> E | D39: ADFn°1bis | E39: EMZ 11 GP - ADF n°1 - Parts de commandité | F39: 0 | G39: 92.23 | I39: 0 | J39: 94.23
A40: Total 10213000 | F40: 0 | G40: 94.23 | I40: 0 | J40: 94.23
A42: 13000000 Frais de constitut°, de fusion, d'apport | F42: Débit | G42: Crédit | I42: Solde Débit | J42: Solde Crédit
B43: 45930 | C43: OD --> E | D43: 7 | E43: Frais de constitution | F43: 710.32 | G43: 0 | I43: 710.32 | J43: 0
B44: 45930 | C44: OD --> E | D44: 12 | E44: Provision Frais de constitution (avocats) | F44: 25000 | G44: 0 | I44: 25710.32 | J44: 0
B45: 45931 | C45: OD --> E | D45: 18 | E45: Extourne Frais de constitution | F45: 0 | G45: 710.32 | I45: 25000 | J45: 0
A46: Total 13000000 | F46: 25710.32 | G46: 710.32 | I46: 25000 | J46: 0
A48: 30260030 Koenig solutions - ADP B | F48: Débit | G48: Crédit | I48: Solde Débit | J48: Solde Crédit
B49: 45986 | C49: BQCaceis --> E | D49: KOENING | E49: Koenig - ADP B - Sous 87 200 titres (nominal) | F49: 87200 | G49: 0 | I49: 87200 | J49: 0
B50: 45986 | C50: BQCaceis --> E | D50: KOENING | E50: Koenig - ADP B - Sous 87 200 titres (Prime emissi) | F50: 8632800 | G50: 0 | I50: 8720000 | J50: 0
A51: Total 30260030 | F51: 8720000 | G51: 0 | I51: 8720000 | J51: 0
A53: 31260010 Inflexion BIDCO - OCADP 2 | F53: Débit | G53: Crédit | I53: Solde Débit | J53: Solde Crédit
B54: 45863 | C54: BQCaceis --> E | D54: SOUSBIDCO | E54: Inflexion BIDCO - souscription OCADP2 | F54: 40320000 | G54: 0 | I54: 40320000 | J54: 0
A55: Total 31260010 | F55: 40320000 | G55: 0 | I55: 40320000 | J55: 0
A57: 31260030 Koenig solutions - OC (SHL) | F57: Débit | G57: Crédit | I57: Solde Débit | J57: Solde Crédit
B58: 45986 | C58: BQCaceis --> E | D58: KOENING | E58: Koenig - OC (SHL)-Sous 26 160 000 titres (nominal) | F58: 3200 | G58: 0 | I58: 3200 | J58: 0
B59: 45986 | C59: BQCaceis --> E | D59: KOENING | E59: Koenig - OC (SHL)- (Prime emiss) | F59: 26156800 | G59: 0 | I59: 26160000 | J59: 0
A60: Total 31260030 | F60: 26160000 | G60: 0 | I60: 26160000 | J60: 0
A62: 31260031 Koenig solutions - OC (Warehouse II - ADP A) | F62: Débit | G62: Crédit | I62: Solde Débit | J62: Solde Crédit
B63: 45986 | C63: BQCaceis --> E | D63: KOENING | E63: Koenig - OC (Warehouse II - ADP A) sousc 500 000 | F63: 500000 | G63: 0 | I63: 500000 | J63: 0
A64: Total 31260031 | F64: 500000 | G64: 0 | I64: 500000 | J64: 0
A66: 31460010 Inflexion BIDCO - ORADP 1 | F66: Débit | G66: Crédit | I66: Solde Débit | J66: Solde Crédit
B67: 45863 | C67: BQCaceis --> E | D67: SOUSBIDCO | E67: Inflexion BIDCO - souscription ORADP1 | F67: 10080000 | G67: 0 | I67: 10080000 | J67: 0
A68: Total 31460010 | F68: 10080000 | G68: 0 | I68: 10080000 | J68: 0
A70: 31460020 SNIC Technologies Group - OBSA | F70: Débit | G70: Crédit | I70: Solde Débit | J70: Solde Crédit
B71: 46007 | C71: BQCaceis --> E | D71: SNIC | E71: SNIC - OBSA - sous 63 750 000 titres | F71: 63750000 | G71: 0 | I71: 63750000 | J71: 0
A72: Total 31460020 | F72: 63750000 | G72: 0 | I72: 63750000 | J72: 0
A74: 31800000 Intérêts courus sur OC | F74: Débit | G74: Crédit | I74: Solde Débit | J74: Solde Crédit
B75: 45930 | C75: ODSITU --> E | D75: 3 | E75: Valorisation au 30/09/25 | F75: 695934.25 | G75: 0 | I75: 695934.25 | J75: 0
B76: 45931 | C76: ODSITU --> E | D76: 3 | E76: EXT Valorisation au 30/09/25 | F76: 0 | G76: 695934.25 | I76: 0 | J76: 0
B77: 46022 | C77: OD --> E | D77: 17 | E77: Valorisation au 31/12/25 | F77: 1712219.2 | G77: 0 | I77: 1712219.2 | J77: 0
B78: 46022 | C78: OD --> E | D78: 17 | E78: Valorisation au 31/12/25 | F78: 247916.67 | G78: 0 | I78: 1960135.9 | J78: 0
B79: 46022 | C79: OD --> E | D79: 17 | E79: Valorisation au 31/12/25 | F79: 90591.11 | G79: 0 | I79: 2050727 | J79: 0
A80: Total 31800000 | F80: 2746661.2 | G80: 695934.25 | I80: 2050727 | J80: 0
A82: 37000000 Diff d’estim s/actions | F82: Débit | G82: Crédit | I82: Solde Débit | J82: Solde Crédit
B83: 46022 | C83: OD --> E | D83: 17 | E83: Valorisation au 31/12/25 | F83: 67943.33 | G83: 0 | I83: 67943.33 | J83: 0
A84: Total 37000000 | F84: 67943.33 | G84: 0 | I84: 67943.33 | J84: 0
A86: 37100000 Diff d’estimation s/obligations | F86: Débit | G86: Crédit | I86: Solde Débit | J86: Solde Crédit
B87: 46022 | C87: OD --> E | D87: 17 | E87: Valorisation au 31/12/25 | F87: 226840.18 | G87: 0 | I87: 226840.18 | J87: 0
A88: Total 37100000 | F88: 226840.18 | G88: 0 | I88: 226840.18 | J88: 0
A90: 39000000 Emprunts | F90: Débit | G90: Crédit | I90: Solde Débit | J90: Solde Crédit
B91: 45862 | C91: BQCaceis --> E | D91: Emprunt1 | E91: Emprunt - Tirage 1 | F91: 0 | G91: 50400000 | I91: 0 | J91: 50400000
B92: 45982 | C92: BQCaceis --> E | D92: Emprunt3 | E92: Emprunt - Tirage 3 | F92: 0 | G92: 35380000 | I92: 0 | J92: 85780000
B93: 46007 | C93: BQCaceis --> E | D93: Emprunt5et6 | E93: Emprunt Tirage n°5 | F93: 0 | G93: 40906250 | I93: 0 | J93: 126686250
B94: 46007 | C94: BQCaceis --> E | D94: Emprunt5et6 | E94: Emprunt Tirage n°5 | F94: 0 | G94: 16843750 | I94: 0 | J94: 143530000
B95: 46007 | C95: BQCaceis --> E | D95: Emprunt5et6 | E95: Emprunt Tirage n°6 | F95: 0 | G95: 4250000 | I95: 0 | J95: 147780000
B96: 46007 | C96: BQCaceis --> E | D96: Emprunt5et6 | E96: Emprunt Tirage n°6 | F96: 0 | G96: 1750000 | I96: 0 | J96: 149530000
B97: 46020 | C97: BQCaceis --> E | D97: Rembloan1et3 | E97: Loan 1 - Remboursement nominal | F97: 50400000 | G97: 0 | I97: 0 | J97: 99130000
B98: 46020 | C98: BQCaceis --> E | D98: Rembloan1et3 | E98: Loan 3 - Remboursement nominal | F98: 35380000 | G98: 0 | I98: 0 | J98: 63750000
A99: Total 39000000 | F99: 85780000 | G99: 149530000 | I99: 0 | J99: 63750000
A101: 39800000 Intérêts sur emprunts | F101: Débit | G101: Crédit | I101: Solde Débit | J101: Solde Crédit
B102: 45930 | C102: ODSITU --> E | D102: 1 | E102: Valorisation au 30/09/25 | F102: 0 | G102: 364806.4 | I102: 0 | J102: 364806.4
B103: 45931 | C103: ODSITU --> E | D103: 1 | E103: EXT Valorisation au 30/09/25 | F103: 364806.4 | G103: 0 | I103: 0 | J103: 0
B104: 46022 | C104: OD --> E | D104: 17 | E104: Valorisation au 31/12/25 | F104: 0 | G104: 112604.67 | I104: 0 | J104: 112604.67
A105: Total 39800000 | F105: 364806.4 | G105: 477411.07 | I105: 0 | J105: 112604.67
A107: 46210000 Créditeurs divers | F107: Débit | G107: Crédit | I107: Solde Débit | J107: Solde Crédit
B108: 45930 | C108: OD --> E | D108: 7 | E108: Frais de constitution | F108: 0 | G108: 710.32 | H108: A | I108: 0 | J108: 710.32
B109: 45930 | C109: OD --> E | D109: 12 | E109: Provision Frais de constitution (avocats) | F109: 0 | G109: 25000 | I109: 0 | J109: 25710.32
B110: 45931 | C110: OD --> E | D110: 18 | E110: Extourne Frais de constitution | F110: 710.32 | G110: 0 | H110: A | I110: 0 | J110: 25000
B111: 46022 | C111: OD --> E | D111: Break1et3 | E111: Bolzen - Break costs loan n°1 et n°3 | F111: 0 | G111: 8506.17 | I111: 0 | J111: 33506.17
A112: Total 46210000 | F112: 710.32 | G112: 34216.49 | I112: 0 | J112: 33506.17
A114: 46310000 Commissaire aux comptes | F114: Débit | G114: Crédit | I114: Solde Débit | J114: Solde Crédit
B115: 45930 | C115: OD --> E | D115: 1 | E115: Deloitte - Provision 3T2025 | F115: 0 | G115: 2550 | I115: 0 | J115: 2550
B116: 45931 | C116: OD --> E | D116: 14 | E116: Deloitte - Regul provision 3T2025 | F116: 0 | G116: 306 | I116: 0 | J116: 2856
B117: 46022 | C117: OD --> E | D117: 15 | E117: Deloitte - Provision 4T2025 | F117: 0 | G117: 2856 | I117: 0 | J117: 5712
A118: Total 46310000 | F118: 0 | G118: 5712 | I118: 0 | J118: 5712
A120: 46320000 Expert comptable | F120: Débit | G120: Crédit | I120: Solde Débit | J120: Solde Crédit
...
